Workbook

Sheet Resumo
C1: Cliente: DENSO Projeto: APLICAÇÃO AUTOMÁTICA DE ETIQUETA
A2: # | B2: RUBRICAS | C2: VALOR | D2: % | E2: EXECUÇÃO (MESES)
E3: 1 | F3: 2 | G3: 3 | H3: 4 | I3: 5 | J3: 6 | K3: 7 | L3: 8 | M3: 9 | N3: 10 | O3: 11 | P3: 12 | Q3: 13 | R3: 14 | S3: 15 | T3: 16 | U3: 17 | V3: 18 | W3: 19 | X3: 20 | Y3: 21 | Z3: 22 | AA3: 23
A4: 1 | B4: Programas de Computador, Maq e Equip. | C4: =SUM(E4:AA4) -> 340084.8 | D4: =IFERROR(C4/$C$21,0) -> 0.094797678 | E4: =SUMIFS(tbRubrica[Custo Total],tbRubrica[Rubrica],Configuração!$A$2,tbRubrica[Mês],E$3)+SUMIFS(tbRubrica[Custo Total],tbRubrica[Rubrica],Configuração!$A$3,tbRubrica[Mês],E$3) -> 340084.8 | F4: =SUMIFS(tbRubrica[Custo Total],tbRubrica[Rubrica],Configuração!$A$2,tbRubrica[Mês],F$3)+SUMIFS(tbRubrica[Custo Total],tbRubrica[Rubrica],Configuração!$A$3,tbRubrica[Mês],F$3) -> 0 | G4: =SUMIFS(tbRubrica[Custo Total],tbRubrica[Rubrica],Configuração!$A$2,tbRubrica[Mês],G$3)+SUMIFS(tbRubrica[Custo Total],tbRubrica[Rubrica],Configuração!$A$3,tbRubrica[Mês],G$3) -> 0 | H4: =SUMIFS(tbRubrica[Custo Total],tbRubrica[Rubrica],Configuração!$A$2,tbRubrica[Mês],H$3)+SUMIFS(tbRubrica[Custo Total],tbRubrica[Rubrica],Configuração!$A$3,tbRubrica[Mês],H$3) -> 0 | I4: =SUMIFS(tbRubrica[Custo Total],tbRubrica[Rubrica],Configuração!$A$2,tbRubrica[Mês],I$3)+SUMIFS(tbRubrica[Custo Total],tbRubrica[Rubrica],Configuração!$A$3,tbRubrica[Mês],I$3) -> 0 | J4: =SUMIFS(tbRubrica[Custo Total],tbRubrica[Rubrica],Configuração!$A$2,tbRubrica[Mês],J$3)+SUMIFS(tbRubrica[Custo Total],tbRubrica[Rubrica],Configuração!$A$3,tbRubrica[Mês],J$3) -> 0 | K4: =SUMIFS(tbRubrica[Custo Total],tbRubrica[Rubrica],Configuração!$A$2,tbRubrica[Mês],K$3)+SUMIFS(tbRubrica[Custo Total],tbRubrica[Rubrica],Configuração!$A$3,tbRubrica[Mês],K$3) -> 0 | L4: =SUMIFS(tbRubrica[Custo Total],tbRubrica[Rubrica],Configuração!$A$2,tbRubrica[Mês],L$3)+SUMIFS(tbRubrica[Custo Total],tbRubrica[Rubrica],Configuração!$A$3,tbRubrica[Mês],L$3) -> 0 | ... AA4: =SUMIFS(tbRubrica[Custo Total],tbRubrica[Rubrica],Configuração!$A$2,tbRubrica[Mês],AA$3)+SUMIFS(tbRubrica[Custo Total],tbRubrica[Rubrica],Configuração!$A$3,tbRubrica[Mês],AA$3) -> 0 | AE4: =SUM(AF6:AQ6)/12 -> 69161.305
A5: 2 | B5: Implant., Ampliação ou Moderniz. | C5: =SUM(E5:AA5) -> 0 | D5: =IFERROR(C5/$C$21,0) -> 0 | E5: =SUMIFS(tbRubrica[Custo Total],tbRubrica[Rubrica],Configuração!$A$4,tbRubrica[Mês],E$3) -> 0 | F5: =SUMIFS(tbRubrica[Custo Total],tbRubrica[Rubrica],Configuração!$A$4,tbRubrica[Mês],F$3) -> 0 | G5: =SUMIFS(tbRubrica[Custo Total],tbRubrica[Rubrica],Configuração!$A$4,tbRubrica[Mês],G$3) -> 0 | H5: =SUMIFS(tbRubrica[Custo Total],tbRubrica[Rubrica],Configuração!$A$4,tbRubrica[Mês],H$3) -> 0 | I5: =SUMIFS(tbRubrica[Custo Total],tbRubrica[Rubrica],Configuração!$A$4,tbRubrica[Mês],I$3) -> 0 | J5: =SUMIFS(tbRubrica[Custo Total],tbRubrica[Rubrica],Configuração!$A$4,tbRubrica[Mês],J$3) -> 0 | K5: =SUMIFS(tbRubrica[Custo Total],tbRubrica[Rubrica],Configuração!$A$4,tbRubrica[Mês],K$3) -> 0 | L5: =SUMIFS(tbRubrica[Custo Total],tbRubrica[Rubrica],Configuração!$A$4,tbRubrica[Mês],L$3) -> 0 | ... V5: =SUMIFS(tbRubrica[Custo Total],tbRubrica[Rubrica],Configuração!$A$4,tbRubrica[Mês],V$3) -> 0 | W5: =SUMIFS(tbEquipe[Custo],tbEquipe[Tipo],Configuração!$F$2,tbEquipe[Mês],W$3) -> 0 | X5: =SUMIFS(tbEquipe[Custo],tbEquipe[Tipo],Configuração!$F$2,tbEquipe[Mês],X$3) -> 0 | Y5: =SUMIFS(tbEquipe[Custo],tbEquipe[Tipo],Configuração!$F$2,tbEquipe[Mês],Y$3) -> 0 | Z5: =SUMIFS(tbEquipe[Custo],tbEquipe[Tipo],Configuração!$F$2,tbEquipe[Mês],Z$3) -> 0 | AA5: =SUMIFS(tbEquipe[Custo],tbEquipe[Tipo],Configuração!$F$2,tbEquipe[Mês],AA$3) -> 0 | AE5: =SUM(AF7:AQ7)/12 -> 14523.874
A6: 3.1 | B6: Recursos Humanos Diretos | C6: =SUM(E6:AA6) -> 847815.23 | D6: =IFERROR(C6/$C$21,0) -> 0.2363261 | E6: =SUMIFS(tbEquipe[Custo],tbEquipe[Tipo],Configuração!$F$2,tbEquipe[Mês],E$3)+SUMIFS(tbEquipe[Custo],tbEquipe[Tipo],Configuração!$F$4,tbEquipe[Mês],E$3) -> 67089.43 | F6: =SUMIFS(tbEquipe[Custo],tbEquipe[Tipo],Configuração!$F$2,tbEquipe[Mês],F$3)+SUMIFS(tbEquipe[Custo],tbEquipe[Tipo],Configuração!$F$4,tbEquipe[Mês],F$3) -> 69436.33 | G6: =SUMIFS(tbEquipe[Custo],tbEquipe[Tipo],Configuração!$F$2,tbEquipe[Mês],G$3)+SUMIFS(tbEquipe[Custo],tbEquipe[Tipo],Configuração!$F$4,tbEquipe[Mês],G$3) -> 69436.33 | H6: =SUMIFS(tbEquipe[Custo],tbEquipe[Tipo],Configuração!$F$2,tbEquipe[Mês],H$3)+SUMIFS(tbEquipe[Custo],tbEquipe[Tipo],Configuração!$F$4,tbEquipe[Mês],H$3) -> 69436.33 | I6: =SUMIFS(tbEquipe[Custo],tbEquipe[Tipo],Configuração!$F$2,tbEquipe[Mês],I$3)+SUMIFS(tbEquipe[Custo],tbEquipe[Tipo],Configuração!$F$4,tbEquipe[Mês],I$3) -> 69436.33 | J6: =SUMIFS(tbEquipe[Custo],tbEquipe[Tipo],Configuração!$F$2,tbEquipe[Mês],J$3)+SUMIFS(tbEquipe[Custo],tbEquipe[Tipo],Configuração!$F$4,tbEquipe[Mês],J$3) -> 69436.33 | K6: =SUMIFS(tbEquipe[Custo],tbEquipe[Tipo],Configuração!$F$2,tbEquipe[Mês],K$3)+SUMIFS(tbEquipe[Custo],tbEquipe[Tipo],Configuração!$F$4,tbEquipe[Mês],K$3) -> 69436.33 | L6: =SUMIFS(tbEquipe[Custo],tbEquipe[Tipo],Configuração!$F$2,tbEquipe[Mês],L$3)+SUMIFS(tbEquipe[Custo],tbEquipe[Tipo],Configuração!$F$4,tbEquipe[Mês],L$3) -> 69436.33 | ... AA6: =SUMIFS(tbEquipe[Custo],tbEquipe[Tipo],Configuração!$F$2,tbEquipe[Mês],AA$3)+SUMIFS(tbEquipe[Custo],tbEquipe[Tipo],Configuração!$F$4,tbEquipe[Mês],AA$3) -> 0 | AD6: Recursos Humanos Diretos | AE6: 829935.65 | AF6: 92476.046 | AG6: 105351.37 | AH6: 105351.37 | AI6: 105351.37 | AJ6: 105351.37 | AK6: 105351.37 | AL6: 105351.37 | AM6: 105351.37 | AN6: 0 | AO6: 0 | AP6: 0 | AQ6: 0 | AS6: =SUM(AF6:AQ6)-C6 -> -17879.58
A7: 3.2 | B7: Recursos Humanos Indiretos | C7: =SUM(E7:AA7) -> 169563.05 | D7: =IFERROR(C7/$C$21,0) -> 0.04726522 | E7: =SUMIFS(tbEquipe[Custo],tbEquipe[Tipo],Configuração!$F$3,tbEquipe[Mês],E$3)+SUM(tbRHI[1]) -> 13417.886 | F7: =SUMIFS(tbEquipe[Custo],tbEquipe[Tipo],Configuração!$F$3,tbEquipe[Mês],F$3)+SUM(tbRHI[2]) -> 13887.266 | G7: =SUMIFS(tbEquipe[Custo],tbEquipe[Tipo],Configuração!$F$3,tbEquipe[Mês],G$3)+SUM(tbRHI[3]) -> 13887.266 | H7: =SUMIFS(tbEquipe[Custo],tbEquipe[Tipo],Configuração!$F$3,tbEquipe[Mês],H$3)+SUM(tbRHI[4]) -> 13887.266 | I7: =SUMIFS(tbEquipe[Custo],tbEquipe[Tipo],Configuração!$F$3,tbEquipe[Mês],I$3)+SUM(tbRHI[5]) -> 13887.266 | J7: =SUMIFS(tbEquipe[Custo],tbEquipe[Tipo],Configuração!$F$3,tbEquipe[Mês],J$3)+SUM(tbRHI[6]) -> 13887.266 | K7: =SUMIFS(tbEquipe[Custo],tbEquipe[Tipo],Configuração!$F$3,tbEquipe[Mês],K$3)+SUM(tbRHI[7]) -> 13887.266 | L7: =SUMIFS(tbEquipe[Custo],tbEquipe[Tipo],Configuração!$F$3,tbEquipe[Mês],L$3)+SUM(tbRHI[8]) -> 13887.266 | M7: =SUMIFS(tbEquipe[Custo],tbEquipe[Tipo],Configuração!$F$3,tbEquipe[Mês],M$3)+SUM(tbRHI[9]) -> 13887.266 | N7: =SUMIFS(tbEquipe[Custo],tbEquipe[Tipo],Configuração!$F$3,tbEquipe[Mês],N$3)+SUM(tbRHI[10]) -> 13887.266 | O7: =SUMIFS(tbEquipe[Custo],tbEquipe[Tipo],Configuração!$F$3,tbEquipe[Mês],O$3)+SUM(tbRHI[11]) -> 13887.266 | P7: =SUMIFS(tbEquipe[Custo],tbEquipe[Tipo],Configuração!$F$3,tbEquipe[Mês],P$3)+SUM(tbRHI[12]) -> 13887.266 | Q7: =SUMIFS(tbEquipe[Custo],tbEquipe[Tipo],Configuração!$F$3,tbEquipe[Mês],Q$3)+SUM(tbRHI[13]) -> 1085.0114 | R7: =SUMIFS(tbEquipe[Custo],tbEquipe[Tipo],Configuração!$F$3,tbEquipe[Mês],R$3)+SUM(tbRHI[14]) -> 1150.1121 | S7: =SUMIFS(tbEquipe[Custo],tbEquipe[Tipo],Configuração!$F$3,tbEquipe[Mês],S$3)+SUM(tbRHI[15]) -> 1150.1121 | T7: =SUMIFS(tbEquipe[Custo],tbEquipe[Tipo],Configuração!$F$3,tbEquipe[Mês],T$3)+SUM(tbRHI[16]) -> 0 | U7: =SUMIFS(tbEquipe[Custo],tbEquipe[Tipo],Configuração!$F$3,tbEquipe[Mês],U$3)+SUM(tbRHI[17]) -> 0 | V7: =SUMIFS(tbEquipe[Custo],tbEquipe[Tipo],Configuração!$F$3,tbEquipe[Mês],V$3)+SUM(tbRHI[18]) -> 0 | W7: =SUMIFS(tbEquipe[Custo],tbEquipe[Tipo],Configuração!$F$3,tbEquipe[Mês],W$3)+SUM(tbRHI[19]) -> 0 | X7: =SUMIFS(tbEquipe[Custo],tbEquipe[Tipo],Configuração!$F$3,tbEquipe[Mês],X$3)+SUM(tbRHI[20]) -> 0 | Y7: =SUMIFS(tbEquipe[Custo],tbEquipe[Tipo],Configuração!$F$3,tbEquipe[Mês],Y$3)+SUM(tbRHI[21]) -> 0 | Z7: =SUMIFS(tbEquipe[Custo],tbEquipe[Tipo],Configuração!$F$3,tbEquipe[Mês],Z$3)+SUM(tbRHI[22]) -> 0 | AA7: =SUMIFS(tbEquipe[Custo],tbEquipe[Tipo],Configuração!$F$3,tbEquipe[Mês],AA$3)+SUM(tbRHI[23]) -> 0 | AD7: Recursos Humanos Indiretos | AE7: 174286.49 | AF7: 19419.97 | AG7: 22123.788 | AH7: 22123.788 | AI7: 22123.788 | AJ7: 22123.788 | AK7: 22123.788 | AL7: 22123.788 | AM7: 22123.788 | AN7: 0 | AO7: 0 | AP7: 0 | AQ7: 0 | AS7: =SUM(AF7:AQ7)-C7 -> 4723.4405
A8: 4 | B8: Serviço Técnico de Terceiros | C8: =SUM(E8:AA8) -> 390226.14 | D8: =IFERROR(C8/$C$21,0) -> 0.10877443 | E8: =SUMIFS(tbRubrica[Custo Total],tbRubrica[Rubrica],Configuração!$A$5,tbRubrica[Mês],E$3) -> 0 | F8: =SUMIFS(tbRubrica[Custo Total],tbRubrica[Rubrica],Configuração!$A$5,tbRubrica[Mês],F$3) -> 0 | G8: =SUMIFS(tbRubrica[Custo Total],tbRubrica[Rubrica],Configuração!$A$5,tbRubrica[Mês],G$3) -> 390226.14 | H8: =SUMIFS(tbRubrica[Custo Total],tbRubrica[Rubrica],Configuração!$A$5,tbRubrica[Mês],H$3) -> 0 | I8: =SUMIFS(tbRubrica[Custo Total],tbRubrica[Rubrica],Configuração!$A$5,tbRubrica[Mês],I$3) -> 0 | J8: =SUMIFS(tbRubrica[Custo Total],tbRubrica[Rubrica],Configuração!$A$5,tbRubrica[Mês],J$3) -> 0 | K8: =SUMIFS(tbRubrica[Custo Total],tbRubrica[Rubrica],Configuração!$A$5,tbRubrica[Mês],K$3) -> 0 | L8: =SUMIFS(tbRubrica[Custo Total],tbRubrica[Rubrica],Configuração!$A$5,tbRubrica[Mês],L$3) -> 0 | ... AA8: =SUMIFS(tbRubrica[Custo Total],tbRubrica[Rubrica],Configuração!$A$5,tbRubrica[Mês],AA$3) -> 0
A9: 5 | B9: Material de Consumo | C9: =SUM(E9:AA9) -> 720254.41 | D9: =IFERROR(C9/$C$21,0) -> 0.20076888 | E9: =SUMIFS(tbRubrica[Custo Total],tbRubrica[Rubrica],Configuração!$A$6,tbRubrica[Mês],E$3) -> 0 | F9: =SUMIFS(tbRubrica[Custo Total],tbRubrica[Rubrica],Configuração!$A$6,tbRubrica[Mês],F$3) -> 720254.41 | G9: =SUMIFS(tbRubrica[Custo Total],tbRubrica[Rubrica],Configuração!$A$6,tbRubrica[Mês],G$3) -> 0 | H9: =SUMIFS(tbRubrica[Custo Total],tbRubrica[Rubrica],Configuração!$A$6,tbRubrica[Mês],H$3) -> 0 | I9: =SUMIFS(tbRubrica[Custo Total],tbRubrica[Rubrica],Configuração!$A$6,tbRubrica[Mês],I$3) -> 0 | J9: =SUMIFS(tbRubrica[Custo Total],tbRubrica[Rubrica],Configuração!$A$6,tbRubrica[Mês],J$3) -> 0 | K9: =SUMIFS(tbRubrica[Custo Total],tbRubrica[Rubrica],Configuração!$A$6,tbRubrica[Mês],K$3) -> 0 | L9: =SUMIFS(tbRubrica[Custo Total],tbRubrica[Rubrica],Configuração!$A$6,tbRubrica[Mês],L$3) -> 0 | ... AA9: =SUMIFS(tbRubrica[Custo Total],tbRubrica[Rubrica],Configuração!$A$6,tbRubrica[Mês],AA$3) -> 0 | AE9: =SUM(AF11:AQ11)/12 -> 18493.443
B10: SUB-TOTAL 1 | C10: =SUM(C4:C9) -> 2467943.6 | D10: =IFERROR(C10/$C$21,0) -> 0.68793231 | E10: =SUM(E4:E9) -> 420592.12 | F10: =SUM(F4:F9) -> 803578.01 | G10: =SUM(G4:G9) -> 473549.74 | H10: =SUM(H4:H9) -> 83323.596 | I10: =SUM(I4:I9) -> 83323.596 | J10: =SUM(J4:J9) -> 83323.596 | K10: =SUM(K4:K9) -> 83323.596 | L10: =SUM(L4:L9) -> 83323.596 | ... AA10: =SUM(AA4:AA9) -> 0
A11: 6.1 | B11: =Configuração!A7 -> Outros correlatos | C11: =SUM(E11:AA11) -> 222666.6 | D11: =IFERROR(C11/$C$21,0) -> 0.062067686 | E11: =SUMIFS(tbRubrica[Custo Total],tbRubrica[Rubrica],Configuração!$A$7,tbRubrica[Mês],E$3)+SUM(tbRateio[1]) -> 110059.96 | F11: =SUMIFS(tbRubrica[Observações],tbRubrica[Descrição],Configuração!$A$7,tbRubrica[Quantidade],F$3)+SUM(tbRateio[2]) -> 10102.461 | G11: =SUMIFS(tbRubrica[Coluna1],tbRubrica[Justificativa],Configuração!$A$7,tbRubrica[Custo Unitário],G$3)+SUM(tbRateio[3]) -> 10102.461 | H11: =SUMIFS(tbRubrica[Rubrica],tbRubrica[Mês],Configuração!$A$7,tbRubrica[Frete],H$3)+SUM(tbRateio[4]) -> 10102.461 | I11: =SUMIFS(tbRubrica[Descrição],tbRubrica[Quantidade],Configuração!$A$7,tbRubrica[Custo Total],I$3)+SUM(tbRateio[5]) -> 10102.461 | J11: =SUMIFS(tbRubrica[Justificativa],tbRubrica[Custo Unitário],Configuração!$A$7,tbRubrica[Observações],J$3)+SUM(tbRateio[6]) -> 10102.461 | K11: =SUMIFS(tbRubrica[Mês],tbRubrica[Frete],Configuração!$A$7,tbRubrica[Coluna1],K$3)+SUM(tbRateio[7]) -> 10102.461 | L11: =SUMIFS(tbRubrica[Quantidade],tbRubrica[Custo Total],Configuração!$A$7,tbRubrica[Rubrica],L$3)+SUM(tbRateio[8]) -> 10102.461 | M11: =SUMIFS(tbRubrica[Custo Unitário],tbRubrica[Observações],Configuração!$A$7,tbRubrica[Descrição],M$3)+SUM(tbRateio[9]) -> 10102.461 | N11: =SUMIFS(tbRubrica[Frete],tbRubrica[Coluna1],Configuração!$A$7,tbRubrica[Justificativa],N$3)+SUM(tbRateio[10]) -> 10102.461 | O11: =SUMIFS(tbRubrica[Custo Total],tbRubrica[Rubrica],Configuração!$A$7,tbRubrica[Mês],O$3)+SUM(tbRateio[11]) -> 10102.461 | P11: =SUMIFS(tbRubrica[Observações],tbRubrica[Descrição],Configuração!$A$7,tbRubrica[Quantidade],P$3)+SUM(tbRateio[12]) -> 10102.461 | Q11: =SUMIFS(tbRubrica[Coluna1],tbRubrica[Justificativa],Configuração!$A$7,tbRubrica[Custo Unitário],Q$3)+SUM(tbRateio[13]) -> 489.2604 | R11: =SUMIFS(tbRubrica[Rubrica],tbRubrica[Mês],Configuração!$A$7,tbRubrica[Frete],R$3)+SUM(tbRateio[14]) -> 495.15565 | S11: =SUMIFS(tbRubrica[Descrição],tbRubrica[Quantidade],Configuração!$A$7,tbRubrica[Custo Total],S$3)+SUM(tbRateio[15]) -> 495.15565 | T11: =SUMIFS(tbRubrica[Custo Total],tbRubrica[Rubrica],Configuração!$A$7,tbRubrica[Mês],T$3)+SUM(tbRateio[16]) -> 0 | U11: =SUMIFS(tbRubrica[Custo Total],tbRubrica[Rubrica],Configuração!$A$7,tbRubrica[Mês],U$3)+SUM(tbRateio[17]) -> 0 | V11: =SUMIFS(tbRubrica[Custo Total],tbRubrica[Rubrica],Configuração!$A$7,tbRubrica[Mês],V$3)+SUM(tbRateio[18]) -> 0 | W11: =SUMIFS(tbRubrica[Custo Total],tbRubrica[Rubrica],Configuração!$A$7,tbRubrica[Mês],W$3)+SUM(tbRateio[19]) -> 0 | X11: =SUMIFS(tbRubrica[Custo Total],tbRubrica[Rubrica],Configuração!$A$7,tbRubrica[Mês],X$3)+SUM(tbRateio[20]) -> 0 | Y11: =SUMIFS(tbRubrica[Custo Total],tbRubrica[Rubrica],Configuração!$A$7,tbRubrica[Mês],Y$3)+SUM(tbRateio[21]) -> 0 | Z11: =SUMIFS(tbRubrica[Custo Total],tbRubrica[Rubrica],Configuração!$A$7,tbRubrica[Mês],Z$3)+SUM(tbRateio[22]) -> 0 | AA11: =SUMIFS(tbRubrica[Custo Total],tbRubrica[Rubrica],Configuração!$A$7,tbRubrica[Mês],AA$3)+SUM(tbRateio[23]) -> 0 | AD11: Outros correlatos | AE11: 291921.32 | AF11: 113606.08 | AG11: 15473.605 | AH11: 15473.605 | AI11: 15473.605 | AJ11: 15473.605 | AK11: 15473.605 | AL11: 15473.605 | AM11: 15473.605 | AN11: 0 | AO11: 0 | AP11: 0 | AQ11: 0 | AS11: =SUM(AF11:AQ11)-C11 -> -745.28404
A12: 6.2 | B12: =Configuração!A8 -> Treinamentos | C12: =SUM(E12:AA12) -> 0 | D12: =IFERROR(C12/$C$21,0) -> 0 | E12: =SUMIFS(tbRubrica[Custo Total],tbRubrica[Rubrica],Configuração!$A$8,tbRubrica[Mês],E$3) -> 0 | F12: =SUMIFS(tbRubrica[Custo Total],tbRubrica[Rubrica],Configuração!$A$8,tbRubrica[Mês],F$3) -> 0 | G12: =SUMIFS(tbRubrica[Custo Total],tbRubrica[Rubrica],Configuração!$A$8,tbRubrica[Mês],G$3) -> 0 | H12: =SUMIFS(tbRubrica[Custo Total],tbRubrica[Rubrica],Configuração!$A$8,tbRubrica[Mês],H$3) -> 0 | I12: =SUMIFS(tbRubrica[Custo Total],tbRubrica[Rubrica],Configuração!$A$8,tbRubrica[Mês],I$3) -> 0 | J12: =SUMIFS(tbRubrica[Custo Total],tbRubrica[Rubrica],Configuração!$A$8,tbRubrica[Mês],J$3) -> 0 | K12: =SUMIFS(tbRubrica[Custo Total],tbRubrica[Rubrica],Configuração!$A$8,tbRubrica[Mês],K$3) -> 0 | L12: =SUMIFS(tbRubrica[Custo Total],tbRubrica[Rubrica],Configuração!$A$8,tbRubrica[Mês],L$3) -> 0 | ... AA12: =SUMIFS(tbRubrica[Custo Total],tbRubrica[Rubrica],Configuração!$A$8,tbRubrica[Mês],AA$3) -> 0
A13: 6.3 | B13: =Configuração!A9 -> Livros e Periódicos | C13: =SUM(E13:AA13) -> 0 | D13: =IFERROR(C13/$C$21,0) -> 0 | E13: =SUMIFS(tbRubrica[Custo Total],tbRubrica[Rubrica],Configuração!$A$9,tbRubrica[Mês],E$3) -> 0 | F13: =SUMIFS(tbRubrica[Custo Total],tbRubrica[Rubrica],Configuração!$A$9,tbRubrica[Mês],F$3) -> 0 | G13: =SUMIFS(tbRubrica[Custo Total],tbRubrica[Rubrica],Configuração!$A$9,tbRubrica[Mês],G$3) -> 0 | H13: =SUMIFS(tbRubrica[Custo Total],tbRubrica[Rubrica],Configuração!$A$9,tbRubrica[Mês],H$3) -> 0 | I13: =SUMIFS(tbRubrica[Custo Total],tbRubrica[Rubrica],Configuração!$A$9,tbRubrica[Mês],I$3) -> 0 | J13: =SUMIFS(tbRubrica[Custo Total],tbRubrica[Rubrica],Configuração!$A$9,tbRubrica[Mês],J$3) -> 0 | K13: =SUMIFS(tbRubrica[Custo Total],tbRubrica[Rubrica],Configuração!$A$9,tbRubrica[Mês],K$3) -> 0 | L13: =SUMIFS(tbRubrica[Custo Total],tbRubrica[Rubrica],Configuração!$A$9,tbRubrica[Mês],L$3) -> 0 | ... AA13: =SUMIFS(tbRubrica[Custo Total],tbRubrica[Rubrica],Configuração!$A$9,tbRubrica[Mês],AA$3) -> 0
A14: 6.4 | B14: =Configuração!A10 -> Viagens | C14: =SUM(E14:AA14) -> 0 | D14: =IFERROR(C14/$C$21,0) -> 0 | E14: =SUMIFS(tbRubrica[Custo Total],tbRubrica[Rubrica],Configuração!$A$10,tbRubrica[Mês],E$3) -> 0 | F14: =SUMIFS(tbRubrica[Custo Total],tbRubrica[Rubrica],Configuração!$A$10,tbRubrica[Mês],F$3) -> 0 | G14: =SUMIFS(tbRubrica[Custo Total],tbRubrica[Rubrica],Configuração!$A$10,tbRubrica[Mês],G$3) -> 0 | H14: =SUMIFS(tbRubrica[Custo Total],tbRubrica[Rubrica],Configuração!$A$10,tbRubrica[Mês],H$3) -> 0 | I14: =SUMIFS(tbRubrica[Custo Total],tbRubrica[Rubrica],Configuração!$A$10,tbRubrica[Mês],I$3) -> 0 | J14: =SUMIFS(tbRubrica[Custo Total],tbRubrica[Rubrica],Configuração!$A$10,tbRubrica[Mês],J$3) -> 0 | K14: =SUMIFS(tbRubrica[Custo Total],tbRubrica[Rubrica],Configuração!$A$10,tbRubrica[Mês],K$3) -> 0 | L14: =SUMIFS(tbRubrica[Custo Total],tbRubrica[Rubrica],Configuração!$A$10,tbRubrica[Mês],L$3) -> 0 | ... AA14: =SUMIFS(tbRubrica[Custo Total],tbRubrica[Rubrica],Configuração!$A$10,tbRubrica[Mês],AA$3) -> 0
A15: 6.5 | B15: ISSQN | C15: =SUM(E15:AA15) -> 179374.02 | D15: =IFERROR(C15/$C$21,0) -> 0.05 | E15: =SUM(E10:E14)/(1-SUM(Configuração!$D$2,Configuração!$D$5:$D$6))*Configuração!$D$5 -> 35376.805 | F15: =SUM(F10:F14)/(1-SUM(Configuração!$D$2,Configuração!$D$5:$D$6))*Configuração!$D$5 -> 54245.365 | G15: =SUM(G10:G14)/(1-SUM(Configuração!$D$2,Configuração!$D$5:$D$6))*Configuração!$D$5 -> 32243.48 | H15: =SUM(H10:H14)/(1-SUM(Configuração!$D$2,Configuração!$D$5:$D$6))*Configuração!$D$5 -> 6228.4038 | I15: =SUM(I10:I14)/(1-SUM(Configuração!$D$2,Configuração!$D$5:$D$6))*Configuração!$D$5 -> 6228.4038 | J15: =SUM(J10:J14)/(1-SUM(Configuração!$D$2,Configuração!$D$5:$D$6))*Configuração!$D$5 -> 6228.4038 | K15: =SUM(K10:K14)/(1-SUM(Configuração!$D$2,Configuração!$D$5:$D$6))*Configuração!$D$5 -> 6228.4038 | L15: =SUM(L10:L14)/(1-SUM(Configuração!$D$2,Configuração!$D$5:$D$6))*Configuração!$D$5 -> 6228.4038 | ... AA15: =SUM(AA10:AA14)/(1-SUM(Configuração!$D$2,Configuração!$D$5:$D$6))*Configuração!$D$5 -> 0
B16: SUB-TOTAL 2 | C16: =SUM(C11:C15) -> 402040.62 | D16: =IFERROR(C16/$C$21,0) -> 0.11206769 | E16: =SUM(E11:E15) -> 145436.76 | F16: =SUM(F11:F15) -> 64347.826 | G16: =SUM(G11:G15) -> 42345.941 | H16: =SUM(H11:H15) -> 16330.865 | I16: =SUM(I11:I15) -> 16330.865 | J16: =SUM(J11:J15) -> 16330.865 | K16: =SUM(K11:K15) -> 16330.865 | L16: =SUM(L11:L15) -> 16330.865 | ... AA16: =SUM(AA11:AA15) -> 0
B17: SUB-TOTAL DISPÊNDIOS | C17: =C10+C16 -> 2869984.3 | D17: =IFERROR(C17/$C$21,0) -> 0.8 | E17: =E10+E16 -> 566028.88 | F17: =F10+F16 -> 867925.83 | G17: =G10+G16 -> 515895.68 | H17: =H10+H16 -> 99654.461 | I17: =I10+I16 -> 99654.461 | J17: =J10+J16 -> 99654.461 | K17: =K10+K16 -> 99654.461 | L17: =L10+L16 -> 99654.461 | ... AA17: =AA10+AA16 -> 0
A18: 7 | B18: Custos Incorridos & Reserva de P&D | C18: =SUM(E18:AA18) -> 717496.06 | D18: =IFERROR(C18/C21,0) -> 0.2 | E18: =E19+E20 -> 141507.22 | F18: =F19+F20 -> 216981.46 | G18: =G19+G20 -> 128973.92 | H18: =H19+H20 -> 24913.615 | I18: =I19+I20 -> 24913.615 | J18: =J19+J20 -> 24913.615 | K18: =K19+K20 -> 24913.615 | L18: =L19+L20 -> 24913.615 | ... AA18: =AA19+AA20 -> 0
A19: 7.1 | B19: Custos Incorridos / Constituição de Reserva - Conecthus | C19: =SUM(E19:AA19) -> 717496.06 | D19: =IFERROR(C19/$AD$21,0) -> 0 | E19: =(E17/(1-SUM(Configuração!$D$2,Configuração!$D$6))*Configuração!$D$2) -> 141507.22 | F19: =(F17/(1-SUM(Configuração!$D$2,Configuração!$D$6))*Configuração!$D$2) -> 216981.46 | G19: =(G17/(1-SUM(Configuração!$D$2,Configuração!$D$6))*Configuração!$D$2) -> 128973.92 | H19: =(H17/(1-SUM(Configuração!$D$2,Configuração!$D$6))*Configuração!$D$2) -> 24913.615 | I19: =(I17/(1-SUM(Configuração!$D$2,Configuração!$D$6))*Configuração!$D$2) -> 24913.615 | J19: =(J17/(1-SUM(Configuração!$D$2,Configuração!$D$6))*Configuração!$D$2) -> 24913.615 | K19: =(K17/(1-SUM(Configuração!$D$2,Configuração!$D$6))*Configuração!$D$2) -> 24913.615 | L19: =(L17/(1-SUM(Configuração!$D$2,Configuração!$D$6))*Configuração!$D$2) -> 24913.615 | ... AA19: =(AA17/(1-SUM(Configuração!$D$2,Configuração!$D$6))*Configuração!$D$2) -> 0
A20: 7.2 | B20: Outros Custos Incorridos - CITS | C20: =SUM(E20:AA20) -> 0 | D20: =IFERROR(C20/$AD$21,0) -> 0 | E20: =(E17/(1-SUM(Configuração!$D$2,Configuração!$D$6)))*Configuração!$D$6 -> 0 | F20: =(F17/(1-SUM(Configuração!$D$2,Configuração!$D$6)))*Configuração!$D$6 -> 0 | G20: =(G17/(1-SUM(Configuração!$D$2,Configuração!$D$6)))*Configuração!$D$6 -> 0 | H20: =(H17/(1-SUM(Configuração!$D$2,Configuração!$D$6)))*Configuração!$D$6 -> 0 | I20: =(I17/(1-SUM(Configuração!$D$2,Configuração!$D$6)))*Configuração!$D$6 -> 0 | J20: =(J17/(1-SUM(Configuração!$D$2,Configuração!$D$6)))*Configuração!$D$6 -> 0 | K20: =(K17/(1-SUM(Configuração!$D$2,Configuração!$D$6)))*Configuração!$D$6 -> 0 | L20: =(L17/(1-SUM(Configuração!$D$2,Configuração!$D$6)))*Configuração!$D$6 -> 0 | ... AA20: =(AA17/(1-SUM(Configuração!$D$2,Configuração!$D$6)))*Configuração!$D$6 -> 0
B21: TOTAL | C21: =C17+C18 -> 3587480.3 | D21: =SUM(D17:D18) -> 1 | E21: =E17+E18 -> 707536.1 | F21: =F17+F18 -> 1084907.3 | G21: =G17+G18 -> 644869.6 | H21: =H17+H18 -> 124568.08 | I21: =I17+I18 -> 124568.08 | J21: =J17+J18 -> 124568.08 | K21: =K17+K18 -> 124568.08 | L21: =L17+L18 -> 124568.08 | ... AA21: =AA17+AA18 -> 0 | AE21: 3705346.8
B23: Outros Correlatos/Outros Dispêndios | C23: =IFERROR(C16/C10,0) -> 0.16290511
B24: Serviço de Terceiros | C24: =IFERROR(C8/AD21,0) -> 0 | D24: 1 + 4 + 5 | E24: VALOR SYSMAQ | F24: =SERVICO!N10+SERVICO!N14+SERVICO!N15 -> 1600565.4
B25: Dissídio | C25: =Configuração!D4 -> 0.06 | E25: RH SYSMAQ | F25: =SERVICO!P18 -> 315833.7
B26: Inicio do Projeto - Mês/Ano | C26: =Configuração!D3 -> 45597 | E26: TOTAL SYSMAQ | F26: =SUM(F24:F25) -> 1916399.1
B27: Mês de Dissidio 1 | C27: =Configuração!D7 -> 2
B28: Rateio | C28: =Configuração!D13 -> 141 | E28: RHD CONECTHUS | F28: =C6-F25 -> 531981.53
B29: Meses de projeto | C29: =Configuração!D9 -> 12
B30: % RH Indireto | C30: =Configuração!D10 -> 0.2
D31: 1 | E31: VALOR DO PROJETO | F31: =C21-Q21-R21-S21 -> 3558425.7 | G31: 3158389.3
D32: 2 | E32: VALOR + 3 MESES | F32: =Q21+R21+S21 -> 29054.646 | G32: 408714.49
B33: Valor fechado | C33: 0 | E33: VALOR TOTAL (1 + 2) | F33: =SUM(F31:F32) -> 3587480.3 | G33: 3567103.8
B34: Diferença | C34: =C33-AD21 -> 0
D35: Obs: Adicionado o Dispensador
D36: Adicionado a impressora compatível ao dispensador
E38: Valor Anterior SYSMAQ | F38: 1868327.1 | G38: # Diferença
E39: Valor Atual SYSMAQ | F39: =F26 -> 1916399.1 | G39: =F39-F38 -> 48072.002

Sheet Configuração
A1: Rubrica | C1: Parametro | D1: Valor | F1: Tipo de RH
A2: Programas de Computador | C2: Custos Incorridos | D2: 0.2 | F2: Direto
A3: Máquinas e Equipamentos | C3: Inicio Projeto - Mês/Ano | D3: 45597 | F3: Indireto
A4: Implantação, Ampliação ou Modernização | C4: Dissídio | D4: 0.06 | F4: Terceiro
A5: Serviço Técnico de Terceiros | C5: Imposto | D5: 0.05
A6: Material de Consumo | C6: Outros Custos Incorridos | D6: 0
A7: Outros correlatos | C7: Mês Dissidio 1 | D7: 2 | F7: sobre dissídio: Mês deve ser confirmado com o RH. Caso não tenha a confirmação pode ser usado para gerar saldo de rh (mês a definir)
A8: Treinamentos | C8: Mês Dissidio 2 | D8: =D7+12 -> 14
A9: Livros e Periódicos | C9: Meses de Projeto | D9: 12
A10: Viagens | C10: % RH Indireto | D10: 0.2
C11: Vlr Cesta Natalina | D11: 350
C12: Vlr Premiação | D12: 0
C13: Headcount Total | D13: 141
C14: Alocação de Rateio RHD | D14: 1
C15: Alocação de Rateio RHI | D15: 1

Sheet DBFolha
A1: Nome | B1: Cargo | C1: Custo Total | D1: Mês Reajuste | E1: % Reajuste
A2: A Definir - ANALISTA ADMINISTRATIVO | B2: ANALISTA ADMINISTRATIVO | C2: 9501.04 | E2: 0
A3: A definir - ANALISTA DE AUTOMAÇÃO PL | B3: ANALISTA DE AUTOMAÇÃO PL | C3: 15824.93 | E3: 0
A4: A Definir - ANALISTA DE DESENVOLVIMENTO DE EMBALAGEM | B4: ANALISTA DE DESENVOLVIMENTO DE EMBALAGEM | C4: 12370.07 | E4: 0
A5: A Definir - ANALISTA DE ENGENHARIA JR | B5: ANALISTA DE ENGENHARIA JR | C5: 13727.744 | E5: 0
A6: A Definir - ANALISTA DE ENGENHARIA PL | B6: ANALISTA DE ENGENHARIA PL | C6: 14848.8 | E6: 0
A7: A Definir - ANALISTA DE FACILITIES PL | B7: ANALISTA DE FACILITIES PL | C7: 9961.14 | E7: 0
A8: A Definir - ANALISTA DE NECOGIOS JR | B8: ANALISTA DE NEGÓCIOS JR | C8: 11370.22 | E8: 0
A9: A Definir - ANALISTA DE NEGÓCIOS PL | B9: ANALISTA DE NEGÓCIOS PL | C9: 23616.88 | E9: 0
A10: A Definir - ANALISTA DE NEGOCIOS SR | B10: ANALISTA DE NEGOCIOS SR | C10: 17213.231 | E10: 0
A11: A Definir - ANALISTA DE NEGÓCIOS SR | B11: ANALISTA DE NEGÓCIOS SR | C11: 26782.327 | E11: 0
A12: A Definir - ANALISTA DE PD&I JR | B12: ANALISTA DE PD&I JR | C12: 10468.72 | E12: 0
A13: A Definir - ANALISTA DE PD&I SR | B13: ANALISTA DE PD&I SR | C13: 21099.33 | E13: 0
... A231: LIRIAN CORREA DA SILVA | B231: COORDENADOR DE REGULAMENTAÇÃO DE P&D | C231: 16879 | E231: 0

Sheet Equipe
A1: Nome | B1: Cargo | C1: Tipo | D1: Mês | E1: Horas | F1: Alocação | G1: Custo | H1: Justificativa | I1: Vlr R$ | J1: Aloc_ToT | M1: Tot | N1: Tot/12
A2: A Definir - GERENTE DE PROJETOS SR | B2: =IFERROR(VLOOKUP(tbEquipe[[#This Row],[Nome]],tbFOPAG[[Nome]:[Cargo]],2,0),"<Selecionar Nome>") -> GERENTE DE PROJETOS SR | C2: Direto | D2: 1 | E2: =176*tbEquipe[[#This Row],[Alocação]] -> 23.466667 | F2: 0.13333333 | G2: =IFERROR((VLOOKUP(tbEquipe[[#This Row],[Nome]],tbFOPAG[[Nome]:[Custo Total]],3,0)*tbEquipe[[#This Row],[Alocação]]*IF(OR(tbEquipe[[#This Row],[Mês]]>Configuração!$D$7,tbEquipe[[#This Row],[Mês]]=Configuração!$D$7),(1+Configuração!$D$4),1))*IF(OR(tbEquipe[[#This Row],[Mês]]>Configuração!$D$8,tbEquipe[[#This Row],[Mês]]=Configuração!$D$8),(1+Configuração!$D$4),1)+(IF(tbEquipe[[#This Row],[Mês]]=(Configuração!$D$7-1),Configuração!$D$11*tbEquipe[[#This Row],[Alocação]],0))+(IF(tbEquipe[[#This Row],[Mês]]=(Configuração!$D$9),Configuração!$D$12*tbEquipe[[#This Row],[Alocação]],0)),0) -> 5975.6533
A3: A Definir - GERENTE DE PROJETOS SR | B3: =IFERROR(VLOOKUP(tbEquipe[[#This Row],[Nome]],tbFOPAG[[Nome]:[Cargo]],2,0),"<Selecionar Nome>") -> GERENTE DE PROJETOS SR | C3: Direto | D3: 2 | E3: =176*tbEquipe[[#This Row],[Alocação]] -> 23.466667 | F3: 0.13333333 | G3: =IFERROR((VLOOKUP(tbEquipe[[#This Row],[Nome]],tbFOPAG[[Nome]:[Custo Total]],3,0)*tbEquipe[[#This Row],[Alocação]]*IF(OR(tbEquipe[[#This Row],[Mês]]>Configuração!$D$7,tbEquipe[[#This Row],[Mês]]=Configuração!$D$7),(1+Configuração!$D$4),1))*IF(OR(tbEquipe[[#This Row],[Mês]]>Configuração!$D$8,tbEquipe[[#This Row],[Mês]]=Configuração!$D$8),(1+Configuração!$D$4),1)+(IF(tbEquipe[[#This Row],[Mês]]=(Configuração!$D$7-1),Configuração!$D$11*tbEquipe[[#This Row],[Alocação]],0))+(IF(tbEquipe[[#This Row],[Mês]]=(Configuração!$D$9),Configuração!$D$12*tbEquipe[[#This Row],[Alocação]],0)),0) -> 6284.7258
A4: A Definir - GERENTE DE PROJETOS SR | B4: =IFERROR(VLOOKUP(tbEquipe[[#This Row],[Nome]],tbFOPAG[[Nome]:[Cargo]],2,0),"<Selecionar Nome>") -> GERENTE DE PROJETOS SR | C4: Direto | D4: 3 | E4: =176*tbEquipe[[#This Row],[Alocação]] -> 23.466667 | F4: 0.13333333 | G4: =IFERROR((VLOOKUP(tbEquipe[[#This Row],[Nome]],tbFOPAG[[Nome]:[Custo Total]],3,0)*tbEquipe[[#This Row],[Alocação]]*IF(OR(tbEquipe[[#This Row],[Mês]]>Configuração!$D$7,tbEquipe[[#This Row],[Mês]]=Configuração!$D$7),(1+Configuração!$D$4),1))*IF(OR(tbEquipe[[#This Row],[Mês]]>Configuração!$D$8,tbEquipe[[#This Row],[Mês]]=Configuração!$D$8),(1+Configuração!$D$4),1)+(IF(tbEquipe[[#This Row],[Mês]]=(Configuração!$D$7-1),Configuração!$D$11*tbEquipe[[#This Row],[Alocação]],0))+(IF(tbEquipe[[#This Row],[Mês]]=(Configuração!$D$9),Configuração!$D$12*tbEquipe[[#This Row],[Alocação]],0)),0) -> 6284.7258
A5: A Definir - GERENTE DE PROJETOS SR | B5: =IFERROR(VLOOKUP(tbEquipe[[#This Row],[Nome]],tbFOPAG[[Nome]:[Cargo]],2,0),"<Selecionar Nome>") -> GERENTE DE PROJETOS SR | C5: Direto | D5: 4 | E5: =176*tbEquipe[[#This Row],[Alocação]] -> 23.466667 | F5: 0.13333333 | G5: =IFERROR((VLOOKUP(tbEquipe[[#This Row],[Nome]],tbFOPAG[[Nome]:[Custo Total]],3,0)*tbEquipe[[#This Row],[Alocação]]*IF(OR(tbEquipe[[#This Row],[Mês]]>Configuração!$D$7,tbEquipe[[#This Row],[Mês]]=Configuração!$D$7),(1+Configuração!$D$4),1))*IF(OR(tbEquipe[[#This Row],[Mês]]>Configuração!$D$8,tbEquipe[[#This Row],[Mês]]=Configuração!$D$8),(1+Configuração!$D$4),1)+(IF(tbEquipe[[#This Row],[Mês]]=(Configuração!$D$7-1),Configuração!$D$11*tbEquipe[[#This Row],[Alocação]],0))+(IF(tbEquipe[[#This Row],[Mês]]=(Configuração!$D$9),Configuração!$D$12*tbEquipe[[#This Row],[Alocação]],0)),0) -> 6284.7258
A6: A Definir - GERENTE DE PROJETOS SR | B6: =IFERROR(VLOOKUP(tbEquipe[[#This Row],[Nome]],tbFOPAG[[Nome]:[Cargo]],2,0),"<Selecionar Nome>") -> GERENTE DE PROJETOS SR | C6: Direto | D6: 5 | E6: =176*tbEquipe[[#This Row],[Alocação]] -> 23.466667 | F6: 0.13333333 | G6: =IFERROR((VLOOKUP(tbEquipe[[#This Row],[Nome]],tbFOPAG[[Nome]:[Custo Total]],3,0)*tbEquipe[[#This Row],[Alocação]]*IF(OR(tbEquipe[[#This Row],[Mês]]>Configuração!$D$7,tbEquipe[[#This Row],[Mês]]=Configuração!$D$7),(1+Configuração!$D$4),1))*IF(OR(tbEquipe[[#This Row],[Mês]]>Configuração!$D$8,tbEquipe[[#This Row],[Mês]]=Configuração!$D$8),(1+Configuração!$D$4),1)+(IF(tbEquipe[[#This Row],[Mês]]=(Configuração!$D$7-1),Configuração!$D$11*tbEquipe[[#This Row],[Alocação]],0))+(IF(tbEquipe[[#This Row],[Mês]]=(Configuração!$D$9),Configuração!$D$12*tbEquipe[[#This Row],[Alocação]],0)),0) -> 6284.7258
A7: A Definir - GERENTE DE PROJETOS SR | B7: =IFERROR(VLOOKUP(tbEquipe[[#This Row],[Nome]],tbFOPAG[[Nome]:[Cargo]],2,0),"<Selecionar Nome>") -> GERENTE DE PROJETOS SR | C7: Direto | D7: 6 | E7: =176*tbEquipe[[#This Row],[Alocação]] -> 23.466667 | F7: 0.13333333 | G7: =IFERROR((VLOOKUP(tbEquipe[[#This Row],[Nome]],tbFOPAG[[Nome]:[Custo Total]],3,0)*tbEquipe[[#This Row],[Alocação]]*IF(OR(tbEquipe[[#This Row],[Mês]]>Configuração!$D$7,tbEquipe[[#This Row],[Mês]]=Configuração!$D$7),(1+Configuração!$D$4),1))*IF(OR(tbEquipe[[#This Row],[Mês]]>Configuração!$D$8,tbEquipe[[#This Row],[Mês]]=Configuração!$D$8),(1+Configuração!$D$4),1)+(IF(tbEquipe[[#This Row],[Mês]]=(Configuração!$D$7-1),Configuração!$D$11*tbEquipe[[#This Row],[Alocação]],0))+(IF(tbEquipe[[#This Row],[Mês]]=(Configuração!$D$9),Configuração!$D$12*tbEquipe[[#This Row],[Alocação]],0)),0) -> 6284.7258
A8: A Definir - GERENTE DE PROJETOS SR | B8: =IFERROR(VLOOKUP(tbEquipe[[#This Row],[Nome]],tbFOPAG[[Nome]:[Cargo]],2,0),"<Selecionar Nome>") -> GERENTE DE PROJETOS SR | C8: Direto | D8: 7 | E8: =176*tbEquipe[[#This Row],[Alocação]] -> 23.466667 | F8: 0.13333333 | G8: =IFERROR((VLOOKUP(tbEquipe[[#This Row],[Nome]],tbFOPAG[[Nome]:[Custo Total]],3,0)*tbEquipe[[#This Row],[Alocação]]*IF(OR(tbEquipe[[#This Row],[Mês]]>Configuração!$D$7,tbEquipe[[#This Row],[Mês]]=Configuração!$D$7),(1+Configuração!$D$4),1))*IF(OR(tbEquipe[[#This Row],[Mês]]>Configuração!$D$8,tbEquipe[[#This Row],[Mês]]=Configuração!$D$8),(1+Configuração!$D$4),1)+(IF(tbEquipe[[#This Row],[Mês]]=(Configuração!$D$7-1),Configuração!$D$11*tbEquipe[[#This Row],[Alocação]],0))+(IF(tbEquipe[[#This Row],[Mês]]=(Configuração!$D$9),Configuração!$D$12*tbEquipe[[#This Row],[Alocação]],0)),0) -> 6284.7258
A9: A Definir - GERENTE DE PROJETOS SR | B9: =IFERROR(VLOOKUP(tbEquipe[[#This Row],[Nome]],tbFOPAG[[Nome]:[Cargo]],2,0),"<Selecionar Nome>") -> GERENTE DE PROJETOS SR | C9: Direto | D9: 8 | E9: =176*tbEquipe[[#This Row],[Alocação]] -> 23.466667 | F9: 0.13333333 | G9: =IFERROR((VLOOKUP(tbEquipe[[#This Row],[Nome]],tbFOPAG[[Nome]:[Custo Total]],3,0)*tbEquipe[[#This Row],[Alocação]]*IF(OR(tbEquipe[[#This Row],[Mês]]>Configuração!$D$7,tbEquipe[[#This Row],[Mês]]=Configuração!$D$7),(1+Configuração!$D$4),1))*IF(OR(tbEquipe[[#This Row],[Mês]]>Configuração!$D$8,tbEquipe[[#This Row],[Mês]]=Configuração!$D$8),(1+Configuração!$D$4),1)+(IF(tbEquipe[[#This Row],[Mês]]=(Configuração!$D$7-1),Configuração!$D$11*tbEquipe[[#This Row],[Alocação]],0))+(IF(tbEquipe[[#This Row],[Mês]]=(Configuração!$D$9),Configuração!$D$12*tbEquipe[[#This Row],[Alocação]],0)),0) -> 6284.7258 | I9: =SUM(G2:G9) -> 49968.734 | J9: =SUM(F2:F9) -> 1.0666667 | K9: =J9/12 -> 0.088888889 | M9: 1.6 | N9: 0.13333333
A10: A Definir - GERENTE DE PROJETOS SR | B10: =IFERROR(VLOOKUP(tbEquipe[[#This Row],[Nome]],tbFOPAG[[Nome]:[Cargo]],2,0),"<Selecionar Nome>") -> GERENTE DE PROJETOS SR | C10: Direto | D10: 9 | E10: =176*tbEquipe[[#This Row],[Alocação]] -> 23.466667 | F10: 0.13333333 | G10: =IFERROR((VLOOKUP(tbEquipe[[#This Row],[Nome]],tbFOPAG[[Nome]:[Custo Total]],3,0)*tbEquipe[[#This Row],[Alocação]]*IF(OR(tbEquipe[[#This Row],[Mês]]>Configuração!$D$7,tbEquipe[[#This Row],[Mês]]=Configuração!$D$7),(1+Configuração!$D$4),1))*IF(OR(tbEquipe[[#This Row],[Mês]]>Configuração!$D$8,tbEquipe[[#This Row],[Mês]]=Configuração!$D$8),(1+Configuração!$D$4),1)+(IF(tbEquipe[[#This Row],[Mês]]=(Configuração!$D$7-1),Configuração!$D$11*tbEquipe[[#This Row],[Alocação]],0))+(IF(tbEquipe[[#This Row],[Mês]]=(Configuração!$D$9),Configuração!$D$12*tbEquipe[[#This Row],[Alocação]],0)),0) -> 6284.7258
A11: A Definir - GERENTE DE PROJETOS SR | B11: =IFERROR(VLOOKUP(tbEquipe[[#This Row],[Nome]],tbFOPAG[[Nome]:[Cargo]],2,0),"<Selecionar Nome>") -> GERENTE DE PROJETOS SR | C11: Direto | D11: 10 | E11: =176*tbEquipe[[#This Row],[Alocação]] -> 23.466667 | F11: 0.13333333 | G11: =IFERROR((VLOOKUP(tbEquipe[[#This Row],[Nome]],tbFOPAG[[Nome]:[Custo Total]],3,0)*tbEquipe[[#This Row],[Alocação]]*IF(OR(tbEquipe[[#This Row],[Mês]]>Configuração!$D$7,tbEquipe[[#This Row],[Mês]]=Configuração!$D$7),(1+Configuração!$D$4),1))*IF(OR(tbEquipe[[#This Row],[Mês]]>Configuração!$D$8,tbEquipe[[#This Row],[Mês]]=Configuração!$D$8),(1+Configuração!$D$4),1)+(IF(tbEquipe[[#This Row],[Mês]]=(Configuração!$D$7-1),Configuração!$D$11*tbEquipe[[#This Row],[Alocação]],0))+(IF(tbEquipe[[#This Row],[Mês]]=(Configuração!$D$9),Configuração!$D$12*tbEquipe[[#This Row],[Alocação]],0)),0) -> 6284.7258
A12: A Definir - GERENTE DE PROJETOS SR | B12: =IFERROR(VLOOKUP(tbEquipe[[#This Row],[Nome]],tbFOPAG[[Nome]:[Cargo]],2,0),"<Selecionar Nome>") -> GERENTE DE PROJETOS SR | C12: Direto | D12: 11 | E12: =176*tbEquipe[[#This Row],[Alocação]] -> 23.466667 | F12: 0.13333333 | G12: =IFERROR((VLOOKUP(tbEquipe[[#This Row],[Nome]],tbFOPAG[[Nome]:[Custo Total]],3,0)*tbEquipe[[#This Row],[Alocação]]*IF(OR(tbEquipe[[#This Row],[Mês]]>Configuração!$D$7,tbEquipe[[#This Row],[Mês]]=Configuração!$D$7),(1+Configuração!$D$4),1))*IF(OR(tbEquipe[[#This Row],[Mês]]>Configuração!$D$8,tbEquipe[[#This Row],[Mês]]=Configuração!$D$8),(1+Configuração!$D$4),1)+(IF(tbEquipe[[#This Row],[Mês]]=(Configuração!$D$7-1),Configuração!$D$11*tbEquipe[[#This Row],[Alocação]],0))+(IF(tbEquipe[[#This Row],[Mês]]=(Configuração!$D$9),Configuração!$D$12*tbEquipe[[#This Row],[Alocação]],0)),0) -> 6284.7258
A13: A Definir - GERENTE DE PROJETOS SR | B13: =IFERROR(VLOOKUP(tbEquipe[[#This Row],[Nome]],tbFOPAG[[Nome]:[Cargo]],2,0),"<Selecionar Nome>") -> GERENTE DE PROJETOS SR | C13: Direto | D13: 12 | E13: =176*tbEquipe[[#This Row],[Alocação]] -> 23.466667 | F13: 0.13333333 | G13: =IFERROR((VLOOKUP(tbEquipe[[#This Row],[Nome]],tbFOPAG[[Nome]:[Custo Total]],3,0)*tbEquipe[[#This Row],[Alocação]]*IF(OR(tbEquipe[[#This Row],[Mês]]>Configuração!$D$7,tbEquipe[[#This Row],[Mês]]=Configuração!$D$7),(1+Configuração!$D$4),1))*IF(OR(tbEquipe[[#This Row],[Mês]]>Configuração!$D$8,tbEquipe[[#This Row],[Mês]]=Configuração!$D$8),(1+Configuração!$D$4),1)+(IF(tbEquipe[[#This Row],[Mês]]=(Configuração!$D$7-1),Configuração!$D$11*tbEquipe[[#This Row],[Alocação]],0))+(IF(tbEquipe[[#This Row],[Mês]]=(Configuração!$D$9),Configuração!$D$12*tbEquipe[[#This Row],[Alocação]],0)),0) -> 6284.7258
A14: A Definir - GERENTE DE PROJETOS SR | B14: =IFERROR(VLOOKUP(tbEquipe[[#This Row],[Nome]],tbFOPAG[[Nome]:[Cargo]],2,0),"<Selecionar Nome>") -> GERENTE DE PROJETOS SR | C14: Direto | D14: 13 | E14: =176*tbEquipe[[#This Row],[Alocação]] -> 8.8 | F14: 0.05 | G14: =IFERROR((VLOOKUP(tbEquipe[[#This Row],[Nome]],tbFOPAG[[Nome]:[Custo Total]],3,0)*tbEquipe[[#This Row],[Alocação]]*IF(OR(tbEquipe[[#This Row],[Mês]]>Configuração!$D$7,tbEquipe[[#This Row],[Mês]]=Configuração!$D$7),(1+Configuração!$D$4),1))*IF(OR(tbEquipe[[#This Row],[Mês]]>Configuração!$D$8,tbEquipe[[#This Row],[Mês]]=Configuração!$D$8),(1+Configuração!$D$4),1)+(IF(tbEquipe[[#This Row],[Mês]]=(Configuração!$D$7-1),Configuração!$D$11*tbEquipe[[#This Row],[Alocação]],0))+(IF(tbEquipe[[#This Row],[Mês]]=(Configuração!$D$9),Configuração!$D$12*tbEquipe[[#This Row],[Alocação]],0)),0) -> 2356.7722
A15: A Definir - GERENTE DE PROJETOS SR | B15: =IFERROR(VLOOKUP(tbEquipe[[#This Row],[Nome]],tbFOPAG[[Nome]:[Cargo]],2,0),"<Selecionar Nome>") -> GERENTE DE PROJETOS SR | C15: Direto | D15: 14 | E15: =176*tbEquipe[[#This Row],[Alocação]] -> 8.8 | F15: 0.05 | G15: =IFERROR((VLOOKUP(tbEquipe[[#This Row],[Nome]],tbFOPAG[[Nome]:[Custo Total]],3,0)*tbEquipe[[#This Row],[Alocação]]*IF(OR(tbEquipe[[#This Row],[Mês]]>Configuração!$D$7,tbEquipe[[#This Row],[Mês]]=Configuração!$D$7),(1+Configuração!$D$4),1))*IF(OR(tbEquipe[[#This Row],[Mês]]>Configuração!$D$8,tbEquipe[[#This Row],[Mês]]=Configuração!$D$8),(1+Configuração!$D$4),1)+(IF(tbEquipe[[#This Row],[Mês]]=(Configuração!$D$7-1),Configuração!$D$11*tbEquipe[[#This Row],[Alocação]],0))+(IF(tbEquipe[[#This Row],[Mês]]=(Configuração!$D$9),Configuração!$D$12*tbEquipe[[#This Row],[Alocação]],0)),0) -> 2498.1785
A16: A Definir - GERENTE DE PROJETOS SR | B16: =IFERROR(VLOOKUP(tbEquipe[[#This Row],[Nome]],tbFOPAG[[Nome]:[Cargo]],2,0),"<Selecionar Nome>") -> GERENTE DE PROJETOS SR | C16: Direto | D16: 15 | E16: =176*tbEquipe[[#This Row],[Alocação]] -> 8.8 | F16: 0.05 | G16: =IFERROR((VLOOKUP(tbEquipe[[#This Row],[Nome]],tbFOPAG[[Nome]:[Custo Total]],3,0)*tbEquipe[[#This Row],[Alocação]]*IF(OR(tbEquipe[[#This Row],[Mês]]>Configuração!$D$7,tbEquipe[[#This Row],[Mês]]=Configuração!$D$7),(1+Configuração!$D$4),1))*IF(OR(tbEquipe[[#This Row],[Mês]]>Configuração!$D$8,tbEquipe[[#This Row],[Mês]]=Configuração!$D$8),(1+Configuração!$D$4),1)+(IF(tbEquipe[[#This Row],[Mês]]=(Configuração!$D$7-1),Configuração!$D$11*tbEquipe[[#This Row],[Alocação]],0))+(IF(tbEquipe[[#This Row],[Mês]]=(Configuração!$D$9),Configuração!$D$12*tbEquipe[[#This Row],[Alocação]],0)),0) -> 2498.1785 | I16: =SUM(G2:G16) -> 82460.767
A17: A Definir - LÍDER DE PROJETOS | B17: =IFERROR(VLOOKUP(tbEquipe[[#This Row],[Nome]],tbFOPAG[[Nome]:[Cargo]],2,0),"<Selecionar Nome>") -> LÍDER DE PROJETOS | C17: Direto | D17: 1 | E17: =176*tbEquipe[[#This Row],[Alocação]] -> 23.466667 | F17: 0.13333333 | G17: =IFERROR((VLOOKUP(tbEquipe[[#This Row],[Nome]],tbFOPAG[[Nome]:[Custo Total]],3,0)*tbEquipe[[#This Row],[Alocação]]*IF(OR(tbEquipe[[#This Row],[Mês]]>Configuração!$D$7,tbEquipe[[#This Row],[Mês]]=Configuração!$D$7),(1+Configuração!$D$4),1))*IF(OR(tbEquipe[[#This Row],[Mês]]>Configuração!$D$8,tbEquipe[[#This Row],[Mês]]=Configuração!$D$8),(1+Configuração!$D$4),1)+(IF(tbEquipe[[#This Row],[Mês]]=(Configuração!$D$7-1),Configuração!$D$11*tbEquipe[[#This Row],[Alocação]],0))+(IF(tbEquipe[[#This Row],[Mês]]=(Configuração!$D$9),Configuração!$D$12*tbEquipe[[#This Row],[Alocação]],0)),0) -> 3175.427
A18: A Definir - LÍDER DE PROJETOS | B18: =IFERROR(VLOOKUP(tbEquipe[[#This Row],[Nome]],tbFOPAG[[Nome]:[Cargo]],2,0),"<Selecionar Nome>") -> LÍDER DE PROJETOS | C18: Direto | D18: 2 | E18: =176*tbEquipe[[#This Row],[Alocação]] -> 23.466667 | F18: 0.13333333 | G18: =IFERROR((VLOOKUP(tbEquipe[[#This Row],[Nome]],tbFOPAG[[Nome]:[Custo Total]],3,0)*tbEquipe[[#This Row],[Alocação]]*IF(OR(tbEquipe[[#This Row],[Mês]]>Configuração!$D$7,tbEquipe[[#This Row],[Mês]]=Configuração!$D$7),(1+Configuração!$D$4),1))*IF(OR(tbEquipe[[#This Row],[Mês]]>Configuração!$D$8,tbEquipe[[#This Row],[Mês]]=Configuração!$D$8),(1+Configuração!$D$4),1)+(IF(tbEquipe[[#This Row],[Mês]]=(Configuração!$D$7-1),Configuração!$D$11*tbEquipe[[#This Row],[Alocação]],0))+(IF(tbEquipe[[#This Row],[Mês]]=(Configuração!$D$9),Configuração!$D$12*tbEquipe[[#This Row],[Alocação]],0)),0) -> 3316.4859
A19: A Definir - LÍDER DE PROJETOS | B19: =IFERROR(VLOOKUP(tbEquipe[[#This Row],[Nome]],tbFOPAG[[Nome]:[Cargo]],2,0),"<Selecionar Nome>") -> LÍDER DE PROJETOS | C19: Direto | D19: 3 | E19: =176*tbEquipe[[#This Row],[Alocação]] -> 23.466667 | F19: 0.13333333 | G19: =IFERROR((VLOOKUP(tbEquipe[[#This Row],[Nome]],tbFOPAG[[Nome]:[Custo Total]],3,0)*tbEquipe[[#This Row],[Alocação]]*IF(OR(tbEquipe[[#This Row],[Mês]]>Configuração!$D$7,tbEquipe[[#This Row],[Mês]]=Configuração!$D$7),(1+Configuração!$D$4),1))*IF(OR(tbEquipe[[#This Row],[Mês]]>Configuração!$D$8,tbEquipe[[#This Row],[Mês]]=Configuração!$D$8),(1+Configuração!$D$4),1)+(IF(tbEquipe[[#This Row],[Mês]]=(Configuração!$D$7-1),Configuração!$D$11*tbEquipe[[#This Row],[Alocação]],0))+(IF(tbEquipe[[#This Row],[Mês]]=(Configuração!$D$9),Configuração!$D$12*tbEquipe[[#This Row],[Alocação]],0)),0) -> 3316.4859
A20: A Definir - LÍDER DE PROJETOS | B20: =IFERROR(VLOOKUP(tbEquipe[[#This Row],[Nome]],tbFOPAG[[Nome]:[Cargo]],2,0),"<Selecionar Nome>") -> LÍDER DE PROJETOS | C20: Direto | D20: 4 | E20: =176*tbEquipe[[#This Row],[Alocação]] -> 23.466667 | F20: 0.13333333 | G20: =IFERROR((VLOOKUP(tbEquipe[[#This Row],[Nome]],tbFOPAG[[Nome]:[Custo Total]],3,0)*tbEquipe[[#This Row],[Alocação]]*IF(OR(tbEquipe[[#This Row],[Mês]]>Configuração!$D$7,tbEquipe[[#This Row],[Mês]]=Configuração!$D$7),(1+Configuração!$D$4),1))*IF(OR(tbEquipe[[#This Row],[Mês]]>Configuração!$D$8,tbEquipe[[#This Row],[Mês]]=Configuração!$D$8),(1+Configuração!$D$4),1)+(IF(tbEquipe[[#This Row],[Mês]]=(Configuração!$D$7-1),Configuração!$D$11*tbEquipe[[#This Row],[Alocação]],0))+(IF(tbEquipe[[#This Row],[Mês]]=(Configuração!$D$9),Configuração!$D$12*tbEquipe[[#This Row],[Alocação]],0)),0) -> 3316.4859
A21: A Definir - LÍDER DE PROJETOS | B21: =IFERROR(VLOOKUP(tbEquipe[[#This Row],[Nome]],tbFOPAG[[Nome]:[Cargo]],2,0),"<Selecionar Nome>") -> LÍDER DE PROJETOS | C21: Direto | D21: 5 | E21: =176*tbEquipe[[#This Row],[Alocação]] -> 23.466667 | F21: 0.13333333 | G21: =IFERROR((VLOOKUP(tbEquipe[[#This Row],[Nome]],tbFOPAG[[Nome]:[Custo Total]],3,0)*tbEquipe[[#This Row],[Alocação]]*IF(OR(tbEquipe[[#This Row],[Mês]]>Configuração!$D$7,tbEquipe[[#This Row],[Mês]]=Configuração!$D$7),(1+Configuração!$D$4),1))*IF(OR(tbEquipe[[#This Row],[Mês]]>Configuração!$D$8,tbEquipe[[#This Row],[Mês]]=Configuração!$D$8),(1+Configuração!$D$4),1)+(IF(tbEquipe[[#This Row],[Mês]]=(Configuração!$D$7-1),Configuração!$D$11*tbEquipe[[#This Row],[Alocação]],0))+(IF(tbEquipe[[#This Row],[Mês]]=(Configuração!$D$9),Configuração!$D$12*tbEquipe[[#This Row],[Alocação]],0)),0) -> 3316.4859
A22: A Definir - LÍDER DE PROJETOS | B22: =IFERROR(VLOOKUP(tbEquipe[[#This Row],[Nome]],tbFOPAG[[Nome]:[Cargo]],2,0),"<Selecionar Nome>") -> LÍDER DE PROJETOS | C22: Direto | D22: 6 | E22: =176*tbEquipe[[#This Row],[Alocação]] -> 23.466667 | F22: 0.13333333 | G22: =IFERROR((VLOOKUP(tbEquipe[[#This Row],[Nome]],tbFOPAG[[Nome]:[Custo Total]],3,0)*tbEquipe[[#This Row],[Alocação]]*IF(OR(tbEquipe[[#This Row],[Mês]]>Configuração!$D$7,tbEquipe[[#This Row],[Mês]]=Configuração!$D$7),(1+Configuração!$D$4),1))*IF(OR(tbEquipe[[#This Row],[Mês]]>Configuração!$D$8,tbEquipe[[#This Row],[Mês]]=Configuração!$D$8),(1+Configuração!$D$4),1)+(IF(tbEquipe[[#This Row],[Mês]]=(Configuração!$D$7-1),Configuração!$D$11*tbEquipe[[#This Row],[Alocação]],0))+(IF(tbEquipe[[#This Row],[Mês]]=(Configuração!$D$9),Configuração!$D$12*tbEquipe[[#This Row],[Alocação]],0)),0) -> 3316.4859
A23: A Definir - LÍDER DE PROJETOS | B23: =IFERROR(VLOOKUP(tbEquipe[[#This Row],[Nome]],tbFOPAG[[Nome]:[Cargo]],2,0),"<Selecionar Nome>") -> LÍDER DE PROJETOS | C23: Direto | D23: 7 | E23: =176*tbEquipe[[#This Row],[Alocação]] -> 23.466667 | F23: 0.13333333 | G23: =IFERROR((VLOOKUP(tbEquipe[[#This Row],[Nome]],tbFOPAG[[Nome]:[Custo Total]],3,0)*tbEquipe[[#This Row],[Alocação]]*IF(OR(tbEquipe[[#This Row],[Mês]]>Configuração!$D$7,tbEquipe[[#This Row],[Mês]]=Configuração!$D$7),(1+Configuração!$D$4),1))*IF(OR(tbEquipe[[#This Row],[Mês]]>Configuração!$D$8,tbEquipe[[#This Row],[Mês]]=Configuração!$D$8),(1+Configuração!$D$4),1)+(IF(tbEquipe[[#This Row],[Mês]]=(Configuração!$D$7-1),Configuração!$D$11*tbEquipe[[#This Row],[Alocação]],0))+(IF(tbEquipe[[#This Row],[Mês]]=(Configuração!$D$9),Configuração!$D$12*tbEquipe[[#This Row],[Alocação]],0)),0) -> 3316.4859
A24: A Definir - LÍDER DE PROJETOS | B24: =IFERROR(VLOOKUP(tbEquipe[[#This Row],[Nome]],tbFOPAG[[Nome]:[Cargo]],2,0),"<Selecionar Nome>") -> LÍDER DE PROJETOS | C24: Direto | D24: 8 | E24: =176*tbEquipe[[#This Row],[Alocação]] -> 23.466667 | F24: 0.13333333 | G24: =IFERROR((VLOOKUP(tbEquipe[[#This Row],[Nome]],tbFOPAG[[Nome]:[Custo Total]],3,0)*tbEquipe[[#This Row],[Alocação]]*IF(OR(tbEquipe[[#This Row],[Mês]]>Configuração!$D$7,tbEquipe[[#This Row],[Mês]]=Configuração!$D$7),(1+Configuração!$D$4),1))*IF(OR(tbEquipe[[#This Row],[Mês]]>Configuração!$D$8,tbEquipe[[#This Row],[Mês]]=Configuração!$D$8),(1+Configuração!$D$4),1)+(IF(tbEquipe[[#This Row],[Mês]]=(Configuração!$D$7-1),Configuração!$D$11*tbEquipe[[#This Row],[Alocação]],0))+(IF(tbEquipe[[#This Row],[Mês]]=(Configuração!$D$9),Configuração!$D$12*tbEquipe[[#This Row],[Alocação]],0)),0) -> 3316.4859 | I24: =SUM(G17:G24) -> 26390.829 | J24: =SUM(F17:F24) -> 1.0666667 | K24: =J24/12 -> 0.088888889 | M24: 1.6 | N24: 0.13333333
A25: A Definir - LÍDER DE PROJETOS | B25: =IFERROR(VLOOKUP(tbEquipe[[#This Row],[Nome]],tbFOPAG[[Nome]:[Cargo]],2,0),"<Selecionar Nome>") -> LÍDER DE PROJETOS | C25: Direto | D25: 9 | E25: =176*tbEquipe[[#This Row],[Alocação]] -> 23.466667 | F25: 0.13333333 | G25: =IFERROR((VLOOKUP(tbEquipe[[#This Row],[Nome]],tbFOPAG[[Nome]:[Custo Total]],3,0)*tbEquipe[[#This Row],[Alocação]]*IF(OR(tbEquipe[[#This Row],[Mês]]>Configuração!$D$7,tbEquipe[[#This Row],[Mês]]=Configuração!$D$7),(1+Configuração!$D$4),1))*IF(OR(tbEquipe[[#This Row],[Mês]]>Configuração!$D$8,tbEquipe[[#This Row],[Mês]]=Configuração!$D$8),(1+Configuração!$D$4),1)+(IF(tbEquipe[[#This Row],[Mês]]=(Configuração!$D$7-1),Configuração!$D$11*tbEquipe[[#This Row],[Alocação]],0))+(IF(tbEquipe[[#This Row],[Mês]]=(Configuração!$D$9),Configuração!$D$12*tbEquipe[[#This Row],[Alocação]],0)),0) -> 3316.4859
A26: A Definir - LÍDER DE PROJETOS | B26: =IFERROR(VLOOKUP(tbEquipe[[#This Row],[Nome]],tbFOPAG[[Nome]:[Cargo]],2,0),"<Selecionar Nome>") -> LÍDER DE PROJETOS | C26: Direto | D26: 10 | E26: =176*tbEquipe[[#This Row],[Alocação]] -> 23.466667 | F26: 0.13333333 | G26: =IFERROR((VLOOKUP(tbEquipe[[#This Row],[Nome]],tbFOPAG[[Nome]:[Custo Total]],3,0)*tbEquipe[[#This Row],[Alocação]]*IF(OR(tbEquipe[[#This Row],[Mês]]>Configuração!$D$7,tbEquipe[[#This Row],[Mês]]=Configuração!$D$7),(1+Configuração!$D$4),1))*IF(OR(tbEquipe[[#This Row],[Mês]]>Configuração!$D$8,tbEquipe[[#This Row],[Mês]]=Configuração!$D$8),(1+Configuração!$D$4),1)+(IF(tbEquipe[[#This Row],[Mês]]=(Configuração!$D$7-1),Configuração!$D$11*tbEquipe[[#This Row],[Alocação]],0))+(IF(tbEquipe[[#This Row],[Mês]]=(Configuração!$D$9),Configuração!$D$12*tbEquipe[[#This Row],[Alocação]],0)),0) -> 3316.4859
A27: A Definir - LÍDER DE PROJETOS | B27: =IFERROR(VLOOKUP(tbEquipe[[#This Row],[Nome]],tbFOPAG[[Nome]:[Cargo]],2,0),"<Selecionar Nome>") -> LÍDER DE PROJETOS | C27: Direto | D27: 11 | E27: =176*tbEquipe[[#This Row],[Alocação]] -> 23.466667 | F27: 0.13333333 | G27: =IFERROR((VLOOKUP(tbEquipe[[#This Row],[Nome]],tbFOPAG[[Nome]:[Custo Total]],3,0)*tbEquipe[[#This Row],[Alocação]]*IF(OR(tbEquipe[[#This Row],[Mês]]>Configuração!$D$7,tbEquipe[[#This Row],[Mês]]=Configuração!$D$7),(1+Configuração!$D$4),1))*IF(OR(tbEquipe[[#This Row],[Mês]]>Configuração!$D$8,tbEquipe[[#This Row],[Mês]]=Configuração!$D$8),(1+Configuração!$D$4),1)+(IF(tbEquipe[[#This Row],[Mês]]=(Configuração!$D$7-1),Configuração!$D$11*tbEquipe[[#This Row],[Alocação]],0))+(IF(tbEquipe[[#This Row],[Mês]]=(Configuração!$D$9),Configuração!$D$12*tbEquipe[[#This Row],[Alocação]],0)),0) -> 3316.4859
A28: A Definir - LÍDER DE PROJETOS | B28: =IFERROR(VLOOKUP(tbEquipe[[#This Row],[Nome]],tbFOPAG[[Nome]:[Cargo]],2,0),"<Selecionar Nome>") -> LÍDER DE PROJETOS | C28: Direto | D28: 12 | E28: =176*tbEquipe[[#This Row],[Alocação]] -> 23.466667 | F28: 0.13333333 | G28: =IFERROR((VLOOKUP(tbEquipe[[#This Row],[Nome]],tbFOPAG[[Nome]:[Custo Total]],3,0)*tbEquipe[[#This Row],[Alocação]]*IF(OR(tbEquipe[[#This Row],[Mês]]>Configuração!$D$7,tbEquipe[[#This Row],[Mês]]=Configuração!$D$7),(1+Configuração!$D$4),1))*IF(OR(tbEquipe[[#This Row],[Mês]]>Configuração!$D$8,tbEquipe[[#This Row],[Mês]]=Configuração!$D$8),(1+Configuração!$D$4),1)+(IF(tbEquipe[[#This Row],[Mês]]=(Configuração!$D$7-1),Configuração!$D$11*tbEquipe[[#This Row],[Alocação]],0))+(IF(tbEquipe[[#This Row],[Mês]]=(Configuração!$D$9),Configuração!$D$12*tbEquipe[[#This Row],[Alocação]],0)),0) -> 3316.4859
A29: A Definir - LÍDER DE PROJETOS | B29: =IFERROR(VLOOKUP(tbEquipe[[#This Row],[Nome]],tbFOPAG[[Nome]:[Cargo]],2,0),"<Selecionar Nome>") -> LÍDER DE PROJETOS | C29: Direto | D29: 13 | E29: =176*tbEquipe[[#This Row],[Alocação]] -> 8.8 | F29: 0.05 | G29: =IFERROR((VLOOKUP(tbEquipe[[#This Row],[Nome]],tbFOPAG[[Nome]:[Custo Total]],3,0)*tbEquipe[[#This Row],[Alocação]]*IF(OR(tbEquipe[[#This Row],[Mês]]>Configuração!$D$7,tbEquipe[[#This Row],[Mês]]=Configuração!$D$7),(1+Configuração!$D$4),1))*IF(OR(tbEquipe[[#This Row],[Mês]]>Configuração!$D$8,tbEquipe[[#This Row],[Mês]]=Configuração!$D$8),(1+Configuração!$D$4),1)+(IF(tbEquipe[[#This Row],[Mês]]=(Configuração!$D$7-1),Configuração!$D$11*tbEquipe[[#This Row],[Alocação]],0))+(IF(tbEquipe[[#This Row],[Mês]]=(Configuração!$D$9),Configuração!$D$12*tbEquipe[[#This Row],[Alocação]],0)),0) -> 1243.6822
A30: A Definir - LÍDER DE PROJETOS | B30: =IFERROR(VLOOKUP(tbEquipe[[#This Row],[Nome]],tbFOPAG[[Nome]:[Cargo]],2,0),"<Selecionar Nome>") -> LÍDER DE PROJETOS | C30: Direto | D30: 14 | E30: =176*tbEquipe[[#This Row],[Alocação]] -> 8.8 | F30: 0.05 | G30: =IFERROR((VLOOKUP(tbEquipe[[#This Row],[Nome]],tbFOPAG[[Nome]:[Custo Total]],3,0)*tbEquipe[[#This Row],[Alocação]]*IF(OR(tbEquipe[[#This Row],[Mês]]>Configuração!$D$7,tbEquipe[[#This Row],[Mês]]=Configuração!$D$7),(1+Configuração!$D$4),1))*IF(OR(tbEquipe[[#This Row],[Mês]]>Configuração!$D$8,tbEquipe[[#This Row],[Mês]]=Configuração!$D$8),(1+Configuração!$D$4),1)+(IF(tbEquipe[[#This Row],[Mês]]=(Configuração!$D$7-1),Configuração!$D$11*tbEquipe[[#This Row],[Alocação]],0))+(IF(tbEquipe[[#This Row],[Mês]]=(Configuração!$D$9),Configuração!$D$12*tbEquipe[[#This Row],[Alocação]],0)),0) -> 1318.3032
A31: A Definir - LÍDER DE PROJETOS | B31: =IFERROR(VLOOKUP(tbEquipe[[#This Row],[Nome]],tbFOPAG[[Nome]:[Cargo]],2,0),"<Selecionar Nome>") -> LÍDER DE PROJETOS | C31: Direto | D31: 15 | E31: =176*tbEquipe[[#This Row],[Alocação]] -> 8.8 | F31: 0.05 | G31: =IFERROR((VLOOKUP(tbEquipe[[#This Row],[Nome]],tbFOPAG[[Nome]:[Custo Total]],3,0)*tbEquipe[[#This Row],[Alocação]]*IF(OR(tbEquipe[[#This Row],[Mês]]>Configuração!$D$7,tbEquipe[[#This Row],[Mês]]=Configuração!$D$7),(1+Configuração!$D$4),1))*IF(OR(tbEquipe[[#This Row],[Mês]]>Configuração!$D$8,tbEquipe[[#This Row],[Mês]]=Configuração!$D$8),(1+Configuração!$D$4),1)+(IF(tbEquipe[[#This Row],[Mês]]=(Configuração!$D$7-1),Configuração!$D$11*tbEquipe[[#This Row],[Alocação]],0))+(IF(tbEquipe[[#This Row],[Mês]]=(Configuração!$D$9),Configuração!$D$12*tbEquipe[[#This Row],[Alocação]],0)),0) -> 1318.3032 | I31: =SUM(G17:G31) -> 43537.061
A32: A Definir - ANALISTA DE NEGOCIOS SR | B32: =IFERROR(VLOOKUP(tbEquipe[[#This Row],[Nome]],tbFOPAG[[Nome]:[Cargo]],2,0),"<Selecionar Nome>") -> ANALISTA DE NEGOCIOS SR | C32: Direto | D32: 1 | E32: =176*tbEquipe[[#This Row],[Alocação]] -> 38.72 | F32: 0.22 | G32: =IFERROR((VLOOKUP(tbEquipe[[#This Row],[Nome]],tbFOPAG[[Nome]:[Custo Total]],3,0)*tbEquipe[[#This Row],[Alocação]]*IF(OR(tbEquipe[[#This Row],[Mês]]>Configuração!$D$7,tbEquipe[[#This Row],[Mês]]=Configuração!$D$7),(1+Configuração!$D$4),1))*IF(OR(tbEquipe[[#This Row],[Mês]]>Configuração!$D$8,tbEquipe[[#This Row],[Mês]]=Configuração!$D$8),(1+Configuração!$D$4),1)+(IF(tbEquipe[[#This Row],[Mês]]=(Configuração!$D$7-1),Configuração!$D$11*tbEquipe[[#This Row],[Alocação]],0))+(IF(tbEquipe[[#This Row],[Mês]]=(Configuração!$D$9),Configuração!$D$12*tbEquipe[[#This Row],[Alocação]],0)),0) -> 3863.9108
A33: A Definir - ANALISTA DE NEGOCIOS SR | B33: =IFERROR(VLOOKUP(tbEquipe[[#This Row],[Nome]],tbFOPAG[[Nome]:[Cargo]],2,0),"<Selecionar Nome>") -> ANALISTA DE NEGOCIOS SR | C33: Direto | D33: 2 | E33: =176*tbEquipe[[#This Row],[Alocação]] -> 38.72 | F33: 0.22 | G33: =IFERROR((VLOOKUP(tbEquipe[[#This Row],[Nome]],tbFOPAG[[Nome]:[Custo Total]],3,0)*tbEquipe[[#This Row],[Alocação]]*IF(OR(tbEquipe[[#This Row],[Mês]]>Configuração!$D$7,tbEquipe[[#This Row],[Mês]]=Configuração!$D$7),(1+Configuração!$D$4),1))*IF(OR(tbEquipe[[#This Row],[Mês]]>Configuração!$D$8,tbEquipe[[#This Row],[Mês]]=Configuração!$D$8),(1+Configuração!$D$4),1)+(IF(tbEquipe[[#This Row],[Mês]]=(Configuração!$D$7-1),Configuração!$D$11*tbEquipe[[#This Row],[Alocação]],0))+(IF(tbEquipe[[#This Row],[Mês]]=(Configuração!$D$9),Configuração!$D$12*tbEquipe[[#This Row],[Alocação]],0)),0) -> 4014.1254
A34: A Definir - ANALISTA DE NEGOCIOS SR | B34: =IFERROR(VLOOKUP(tbEquipe[[#This Row],[Nome]],tbFOPAG[[Nome]:[Cargo]],2,0),"<Selecionar Nome>") -> ANALISTA DE NEGOCIOS SR | C34: Direto | D34: 3 | E34: =176*tbEquipe[[#This Row],[Alocação]] -> 38.72 | F34: 0.22 | G34: =IFERROR((VLOOKUP(tbEquipe[[#This Row],[Nome]],tbFOPAG[[Nome]:[Custo Total]],3,0)*tbEquipe[[#This Row],[Alocação]]*IF(OR(tbEquipe[[#This Row],[Mês]]>Configuração!$D$7,tbEquipe[[#This Row],[Mês]]=Configuração!$D$7),(1+Configuração!$D$4),1))*IF(OR(tbEquipe[[#This Row],[Mês]]>Configuração!$D$8,tbEquipe[[#This Row],[Mês]]=Configuração!$D$8),(1+Configuração!$D$4),1)+(IF(tbEquipe[[#This Row],[Mês]]=(Configuração!$D$7-1),Configuração!$D$11*tbEquipe[[#This Row],[Alocação]],0))+(IF(tbEquipe[[#This Row],[Mês]]=(Configuração!$D$9),Configuração!$D$12*tbEquipe[[#This Row],[Alocação]],0)),0) -> 4014.1254
A35: A Definir - ANALISTA DE NEGOCIOS SR | B35: =IFERROR(VLOOKUP(tbEquipe[[#This Row],[Nome]],tbFOPAG[[Nome]:[Cargo]],2,0),"<Selecionar Nome>") -> ANALISTA DE NEGOCIOS SR | C35: Direto | D35: 4 | E35: =176*tbEquipe[[#This Row],[Alocação]] -> 38.72 | F35: 0.22 | G35: =IFERROR((VLOOKUP(tbEquipe[[#This Row],[Nome]],tbFOPAG[[Nome]:[Custo Total]],3,0)*tbEquipe[[#This Row],[Alocação]]*IF(OR(tbEquipe[[#This Row],[Mês]]>Configuração!$D$7,tbEquipe[[#This Row],[Mês]]=Configuração!$D$7),(1+Configuração!$D$4),1))*IF(OR(tbEquipe[[#This Row],[Mês]]>Configuração!$D$8,tbEquipe[[#This Row],[Mês]]=Configuração!$D$8),(1+Configuração!$D$4),1)+(IF(tbEquipe[[#This Row],[Mês]]=(Configuração!$D$7-1),Configuração!$D$11*tbEquipe[[#This Row],[Alocação]],0))+(IF(tbEquipe[[#This Row],[Mês]]=(Configuração!$D$9),Configuração!$D$12*tbEquipe[[#This Row],[Alocação]],0)),0) -> 4014.1254
A36: A Definir - ANALISTA DE NEGOCIOS SR | B36: =IFERROR(VLOOKUP(tbEquipe[[#This Row],[Nome]],tbFOPAG[[Nome]:[Cargo]],2,0),"<Selecionar Nome>") -> ANALISTA DE NEGOCIOS SR | C36: Direto | D36: 5 | E36: =176*tbEquipe[[#This Row],[Alocação]] -> 38.72 | F36: 0.22 | G36: =IFERROR((VLOOKUP(tbEquipe[[#This Row],[Nome]],tbFOPAG[[Nome]:[Custo Total]],3,0)*tbEquipe[[#This Row],[Alocação]]*IF(OR(tbEquipe[[#This Row],[Mês]]>Configuração!$D$7,tbEquipe[[#This Row],[Mês]]=Configuração!$D$7),(1+Configuração!$D$4),1))*IF(OR(tbEquipe[[#This Row],[Mês]]>Configuração!$D$8,tbEquipe[[#This Row],[Mês]]=Configuração!$D$8),(1+Configuração!$D$4),1)+(IF(tbEquipe[[#This Row],[Mês]]=(Configuração!$D$7-1),Configuração!$D$11*tbEquipe[[#This Row],[Alocação]],0))+(IF(tbEquipe[[#This Row],[Mês]]=(Configuração!$D$9),Configuração!$D$12*tbEquipe[[#This Row],[Alocação]],0)),0) -> 4014.1254
A37: A Definir - ANALISTA DE NEGOCIOS SR | B37: =IFERROR(VLOOKUP(tbEquipe[[#This Row],[Nome]],tbFOPAG[[Nome]:[Cargo]],2,0),"<Selecionar Nome>") -> ANALISTA DE NEGOCIOS SR | C37: Direto | D37: 6 | E37: =176*tbEquipe[[#This Row],[Alocação]] -> 38.72 | F37: 0.22 | G37: =IFERROR((VLOOKUP(tbEquipe[[#This Row],[Nome]],tbFOPAG[[Nome]:[Custo Total]],3,0)*tbEquipe[[#This Row],[Alocação]]*IF(OR(tbEquipe[[#This Row],[Mês]]>Configuração!$D$7,tbEquipe[[#This Row],[Mês]]=Configuração!$D$7),(1+Configuração!$D$4),1))*IF(OR(tbEquipe[[#This Row],[Mês]]>Configuração!$D$8,tbEquipe[[#This Row],[Mês]]=Configuração!$D$8),(1+Configuração!$D$4),1)+(IF(tbEquipe[[#This Row],[Mês]]=(Configuração!$D$7-1),Configuração!$D$11*tbEquipe[[#This Row],[Alocação]],0))+(IF(tbEquipe[[#This Row],[Mês]]=(Configuração!$D$9),Configuração!$D$12*tbEquipe[[#This Row],[Alocação]],0)),0) -> 4014.1254
A38: A Definir - ANALISTA DE NEGOCIOS SR | B38: =IFERROR(VLOOKUP(tbEquipe[[#This Row],[Nome]],tbFOPAG[[Nome]:[Cargo]],2,0),"<Selecionar Nome>") -> ANALISTA DE NEGOCIOS SR | C38: Direto | D38: 7 | E38: =176*tbEquipe[[#This Row],[Alocação]] -> 38.72 | F38: 0.22 | G38: =IFERROR((VLOOKUP(tbEquipe[[#This Row],[Nome]],tbFOPAG[[Nome]:[Custo Total]],3,0)*tbEquipe[[#This Row],[Alocação]]*IF(OR(tbEquipe[[#This Row],[Mês]]>Configuração!$D$7,tbEquipe[[#This Row],[Mês]]=Configuração!$D$7),(1+Configuração!$D$4),1))*IF(OR(tbEquipe[[#This Row],[Mês]]>Configuração!$D$8,tbEquipe[[#This Row],[Mês]]=Configuração!$D$8),(1+Configuração!$D$4),1)+(IF(tbEquipe[[#This Row],[Mês]]=(Configuração!$D$7-1),Configuração!$D$11*tbEquipe[[#This Row],[Alocação]],0))+(IF(tbEquipe[[#This Row],[Mês]]=(Configuração!$D$9),Configuração!$D$12*tbEquipe[[#This Row],[Alocação]],0)),0) -> 4014.1254
A39: A Definir - ANALISTA DE NEGOCIOS SR | B39: =IFERROR(VLOOKUP(tbEquipe[[#This Row],[Nome]],tbFOPAG[[Nome]:[Cargo]],2,0),"<Selecionar Nome>") -> ANALISTA DE NEGOCIOS SR | C39: Direto | D39: 8 | E39: =176*tbEquipe[[#This Row],[Alocação]] -> 38.72 | F39: 0.22 | G39: =IFERROR((VLOOKUP(tbEquipe[[#This Row],[Nome]],tbFOPAG[[Nome]:[Custo Total]],3,0)*tbEquipe[[#This Row],[Alocação]]*IF(OR(tbEquipe[[#This Row],[Mês]]>Configuração!$D$7,tbEquipe[[#This Row],[Mês]]=Configuração!$D$7),(1+Configuração!$D$4),1))*IF(OR(tbEquipe[[#This Row],[Mês]]>Configuração!$D$8,tbEquipe[[#This Row],[Mês]]=Configuração!$D$8),(1+Configuração!$D$4),1)+(IF(tbEquipe[[#This Row],[Mês]]=(Configuração!$D$7-1),Configuração!$D$11*tbEquipe[[#This Row],[Alocação]],0))+(IF(tbEquipe[[#This Row],[Mês]]=(Configuração!$D$9),Configuração!$D$12*tbEquipe[[#This Row],[Alocação]],0)),0) -> 4014.1254 | I39: =SUM(G32:G39) -> 31962.789 | J39: =SUM(F32:F39) -> 1.76 | K39: =J39/12 -> 0.14666667 | M39: 2.64 | N39: 0.22
A40: A Definir - ANALISTA DE NEGOCIOS SR | B40: =IFERROR(VLOOKUP(tbEquipe[[#This Row],[Nome]],tbFOPAG[[Nome]:[Cargo]],2,0),"<Selecionar Nome>") -> ANALISTA DE NEGOCIOS SR | C40: Direto | D40: 9 | E40: =176*tbEquipe[[#This Row],[Alocação]] -> 38.72 | F40: 0.22 | G40: =IFERROR((VLOOKUP(tbEquipe[[#This Row],[Nome]],tbFOPAG[[Nome]:[Custo Total]],3,0)*tbEquipe[[#This Row],[Alocação]]*IF(OR(tbEquipe[[#This Row],[Mês]]>Configuração!$D$7,tbEquipe[[#This Row],[Mês]]=Configuração!$D$7),(1+Configuração!$D$4),1))*IF(OR(tbEquipe[[#This Row],[Mês]]>Configuração!$D$8,tbEquipe[[#This Row],[Mês]]=Configuração!$D$8),(1+Configuração!$D$4),1)+(IF(tbEquipe[[#This Row],[Mês]]=(Configuração!$D$7-1),Configuração!$D$11*tbEquipe[[#This Row],[Alocação]],0))+(IF(tbEquipe[[#This Row],[Mês]]=(Configuração!$D$9),Configuração!$D$12*tbEquipe[[#This Row],[Alocação]],0)),0) -> 4014.1254
A41: A Definir - ANALISTA DE NEGOCIOS SR | B41: =IFERROR(VLOOKUP(tbEquipe[[#This Row],[Nome]],tbFOPAG[[Nome]:[Cargo]],2,0),"<Selecionar Nome>") -> ANALISTA DE NEGOCIOS SR | C41: Direto | D41: 10 | E41: =176*tbEquipe[[#This Row],[Alocação]] -> 38.72 | F41: 0.22 | G41: =IFERROR((VLOOKUP(tbEquipe[[#This Row],[Nome]],tbFOPAG[[Nome]:[Custo Total]],3,0)*tbEquipe[[#This Row],[Alocação]]*IF(OR(tbEquipe[[#This Row],[Mês]]>Configuração!$D$7,tbEquipe[[#This Row],[Mês]]=Configuração!$D$7),(1+Configuração!$D$4),1))*IF(OR(tbEquipe[[#This Row],[Mês]]>Configuração!$D$8,tbEquipe[[#This Row],[Mês]]=Configuração!$D$8),(1+Configuração!$D$4),1)+(IF(tbEquipe[[#This Row],[Mês]]=(Configuração!$D$7-1),Configuração!$D$11*tbEquipe[[#This Row],[Alocação]],0))+(IF(tbEquipe[[#This Row],[Mês]]=(Configuração!$D$9),Configuração!$D$12*tbEquipe[[#This Row],[Alocação]],0)),0) -> 4014.1254
A42: A Definir - ANALISTA DE NEGOCIOS SR | B42: =IFERROR(VLOOKUP(tbEquipe[[#This Row],[Nome]],tbFOPAG[[Nome]:[Cargo]],2,0),"<Selecionar Nome>") -> ANALISTA DE NEGOCIOS SR | C42: Direto | D42: 11 | E42: =176*tbEquipe[[#This Row],[Alocação]] -> 38.72 | F42: 0.22 | G42: =IFERROR((VLOOKUP(tbEquipe[[#This Row],[Nome]],tbFOPAG[[Nome]:[Custo Total]],3,0)*tbEquipe[[#This Row],[Alocação]]*IF(OR(tbEquipe[[#This Row],[Mês]]>Configuração!$D$7,tbEquipe[[#This Row],[Mês]]=Configuração!$D$7),(1+Configuração!$D$4),1))*IF(OR(tbEquipe[[#This Row],[Mês]]>Configuração!$D$8,tbEquipe[[#This Row],[Mês]]=Configuração!$D$8),(1+Configuração!$D$4),1)+(IF(tbEquipe[[#This Row],[Mês]]=(Configuração!$D$7-1),Configuração!$D$11*tbEquipe[[#This Row],[Alocação]],0))+(IF(tbEquipe[[#This Row],[Mês]]=(Configuração!$D$9),Configuração!$D$12*tbEquipe[[#This Row],[Alocação]],0)),0) -> 4014.1254
A43: A Definir - ANALISTA DE NEGOCIOS SR | B43: =IFERROR(VLOOKUP(tbEquipe[[#This Row],[Nome]],tbFOPAG[[Nome]:[Cargo]],2,0),"<Selecionar Nome>") -> ANALISTA DE NEGOCIOS SR | C43: Direto | D43: 12 | E43: =176*tbEquipe[[#This Row],[Alocação]] -> 38.72 | F43: 0.22 | G43: =IFERROR((VLOOKUP(tbEquipe[[#This Row],[Nome]],tbFOPAG[[Nome]:[Custo Total]],3,0)*tbEquipe[[#This Row],[Alocação]]*IF(OR(tbEquipe[[#This Row],[Mês]]>Configuração!$D$7,tbEquipe[[#This Row],[Mês]]=Configuração!$D$7),(1+Configuração!$D$4),1))*IF(OR(tbEquipe[[#This Row],[Mês]]>Configuração!$D$8,tbEquipe[[#This Row],[Mês]]=Configuração!$D$8),(1+Configuração!$D$4),1)+(IF(tbEquipe[[#This Row],[Mês]]=(Configuração!$D$7-1),Configuração!$D$11*tbEquipe[[#This Row],[Alocação]],0))+(IF(tbEquipe[[#This Row],[Mês]]=(Configuração!$D$9),Configuração!$D$12*tbEquipe[[#This Row],[Alocação]],0)),0) -> 4014.1254
A44: A Definir - ANALISTA DE NEGOCIOS SR | B44: =IFERROR(VLOOKUP(tbEquipe[[#This Row],[Nome]],tbFOPAG[[Nome]:[Cargo]],2,0),"<Selecionar Nome>") -> ANALISTA DE NEGOCIOS SR | C44: Direto | D44: 13 | E44: =176*tbEquipe[[#This Row],[Alocação]] -> 17.6 | F44: 0.1 | G44: =IFERROR((VLOOKUP(tbEquipe[[#This Row],[Nome]],tbFOPAG[[Nome]:[Custo Total]],3,0)*tbEquipe[[#This Row],[Alocação]]*IF(OR(tbEquipe[[#This Row],[Mês]]>Configuração!$D$7,tbEquipe[[#This Row],[Mês]]=Configuração!$D$7),(1+Configuração!$D$4),1))*IF(OR(tbEquipe[[#This Row],[Mês]]>Configuração!$D$8,tbEquipe[[#This Row],[Mês]]=Configuração!$D$8),(1+Configuração!$D$4),1)+(IF(tbEquipe[[#This Row],[Mês]]=(Configuração!$D$7-1),Configuração!$D$11*tbEquipe[[#This Row],[Alocação]],0))+(IF(tbEquipe[[#This Row],[Mês]]=(Configuração!$D$9),Configuração!$D$12*tbEquipe[[#This Row],[Alocação]],0)),0) -> 1824.6025
A45: A Definir - ANALISTA DE NEGOCIOS SR | B45: =IFERROR(VLOOKUP(tbEquipe[[#This Row],[Nome]],tbFOPAG[[Nome]:[Cargo]],2,0),"<Selecionar Nome>") -> ANALISTA DE NEGOCIOS SR | C45: Direto | D45: 14 | E45: =176*tbEquipe[[#This Row],[Alocação]] -> 17.6 | F45: 0.1 | G45: =IFERROR((VLOOKUP(tbEquipe[[#This Row],[Nome]],tbFOPAG[[Nome]:[Custo Total]],3,0)*tbEquipe[[#This Row],[Alocação]]*IF(OR(tbEquipe[[#This Row],[Mês]]>Configuração!$D$7,tbEquipe[[#This Row],[Mês]]=Configuração!$D$7),(1+Configuração!$D$4),1))*IF(OR(tbEquipe[[#This Row],[Mês]]>Configuração!$D$8,tbEquipe[[#This Row],[Mês]]=Configuração!$D$8),(1+Configuração!$D$4),1)+(IF(tbEquipe[[#This Row],[Mês]]=(Configuração!$D$7-1),Configuração!$D$11*tbEquipe[[#This Row],[Alocação]],0))+(IF(tbEquipe[[#This Row],[Mês]]=(Configuração!$D$9),Configuração!$D$12*tbEquipe[[#This Row],[Alocação]],0)),0) -> 1934.0786
A46: A Definir - ANALISTA DE NEGOCIOS SR | B46: =IFERROR(VLOOKUP(tbEquipe[[#This Row],[Nome]],tbFOPAG[[Nome]:[Cargo]],2,0),"<Selecionar Nome>") -> ANALISTA DE NEGOCIOS SR | C46: Direto | D46: 15 | E46: =176*tbEquipe[[#This Row],[Alocação]] -> 17.6 | F46: 0.1 | G46: =IFERROR((VLOOKUP(tbEquipe[[#This Row],[Nome]],tbFOPAG[[Nome]:[Custo Total]],3,0)*tbEquipe[[#This Row],[Alocação]]*IF(OR(tbEquipe[[#This Row],[Mês]]>Configuração!$D$7,tbEquipe[[#This Row],[Mês]]=Configuração!$D$7),(1+Configuração!$D$4),1))*IF(OR(tbEquipe[[#This Row],[Mês]]>Configuração!$D$8,tbEquipe[[#This Row],[Mês]]=Configuração!$D$8),(1+Configuração!$D$4),1)+(IF(tbEquipe[[#This Row],[Mês]]=(Configuração!$D$7-1),Configuração!$D$11*tbEquipe[[#This Row],[Alocação]],0))+(IF(tbEquipe[[#This Row],[Mês]]=(Configuração!$D$9),Configuração!$D$12*tbEquipe[[#This Row],[Alocação]],0)),0) -> 1934.0786 | I46: =SUM(G32:G46) -> 53712.05
A47: A Definir - ESPECIALISTA EM DEVOPS | B47: =IFERROR(VLOOKUP(tbEquipe[[#This Row],[Nome]],tbFOPAG[[Nome]:[Cargo]],2,0),"<Selecionar Nome>") -> ESPECIALISTA EM DEVOPS | C47: Direto | D47: 1 | E47: =176*tbEquipe[[#This Row],[Alocação]] -> 11.733333 | F47: 0.066666667 | G47: =IFERROR((VLOOKUP(tbEquipe[[#This Row],[Nome]],tbFOPAG[[Nome]:[Custo Total]],3,0)*tbEquipe[[#This Row],[Alocação]]*IF(OR(tbEquipe[[#This Row],[Mês]]>Configuração!$D$7,tbEquipe[[#This Row],[Mês]]=Configuração!$D$7),(1+Configuração!$D$4),1))*IF(OR(tbEquipe[[#This Row],[Mês]]>Configuração!$D$8,tbEquipe[[#This Row],[Mês]]=Configuração!$D$8),(1+Configuração!$D$4),1)+(IF(tbEquipe[[#This Row],[Mês]]=(Configuração!$D$7-1),Configuração!$D$11*tbEquipe[[#This Row],[Alocação]],0))+(IF(tbEquipe[[#This Row],[Mês]]=(Configuração!$D$9),Configuração!$D$12*tbEquipe[[#This Row],[Alocação]],0)),0) -> 2273.4693
A48: A Definir - ESPECIALISTA EM DEVOPS | B48: =IFERROR(VLOOKUP(tbEquipe[[#This Row],[Nome]],tbFOPAG[[Nome]:[Cargo]],2,0),"<Selecionar Nome>") -> ESPECIALISTA EM DEVOPS | C48: Direto | D48: 2 | E48: =176*tbEquipe[[#This Row],[Alocação]] -> 11.733333 | F48: 0.066666667 | G48: =IFERROR((VLOOKUP(tbEquipe[[#This Row],[Nome]],tbFOPAG[[Nome]:[Custo Total]],3,0)*tbEquipe[[#This Row],[Alocação]]*IF(OR(tbEquipe[[#This Row],[Mês]]>Configuração!$D$7,tbEquipe[[#This Row],[Mês]]=Configuração!$D$7),(1+Configuração!$D$4),1))*IF(OR(tbEquipe[[#This Row],[Mês]]>Configuração!$D$8,tbEquipe[[#This Row],[Mês]]=Configuração!$D$8),(1+Configuração!$D$4),1)+(IF(tbEquipe[[#This Row],[Mês]]=(Configuração!$D$7-1),Configuração!$D$11*tbEquipe[[#This Row],[Alocação]],0))+(IF(tbEquipe[[#This Row],[Mês]]=(Configuração!$D$9),Configuração!$D$12*tbEquipe[[#This Row],[Alocação]],0)),0) -> 2385.1442
A49: A Definir - ESPECIALISTA EM DEVOPS | B49: =IFERROR(VLOOKUP(tbEquipe[[#This Row],[Nome]],tbFOPAG[[Nome]:[Cargo]],2,0),"<Selecionar Nome>") -> ESPECIALISTA EM DEVOPS | C49: Direto | D49: 3 | E49: =176*tbEquipe[[#This Row],[Alocação]] -> 11.733333 | F49: 0.066666667 | G49: =IFERROR((VLOOKUP(tbEquipe[[#This Row],[Nome]],tbFOPAG[[Nome]:[Custo Total]],3,0)*tbEquipe[[#This Row],[Alocação]]*IF(OR(tbEquipe[[#This Row],[Mês]]>Configuração!$D$7,tbEquipe[[#This Row],[Mês]]=Configuração!$D$7),(1+Configuração!$D$4),1))*IF(OR(tbEquipe[[#This Row],[Mês]]>Configuração!$D$8,tbEquipe[[#This Row],[Mês]]=Configuração!$D$8),(1+Configuração!$D$4),1)+(IF(tbEquipe[[#This Row],[Mês]]=(Configuração!$D$7-1),Configuração!$D$11*tbEquipe[[#This Row],[Alocação]],0))+(IF(tbEquipe[[#This Row],[Mês]]=(Configuração!$D$9),Configuração!$D$12*tbEquipe[[#This Row],[Alocação]],0)),0) -> 2385.1442
A50: A Definir - ESPECIALISTA EM DEVOPS | B50: =IFERROR(VLOOKUP(tbEquipe[[#This Row],[Nome]],tbFOPAG[[Nome]:[Cargo]],2,0),"<Selecionar Nome>") -> ESPECIALISTA EM DEVOPS | C50: Direto | D50: 4 | E50: =176*tbEquipe[[#This Row],[Alocação]] -> 11.733333 | F50: 0.066666667 | G50: =IFERROR((VLOOKUP(tbEquipe[[#This Row],[Nome]],tbFOPAG[[Nome]:[Custo Total]],3,0)*tbEquipe[[#This Row],[Alocação]]*IF(OR(tbEquipe[[#This Row],[Mês]]>Configuração!$D$7,tbEquipe[[#This Row],[Mês]]=Configuração!$D$7),(1+Configuração!$D$4),1))*IF(OR(tbEquipe[[#This Row],[Mês]]>Configuração!$D$8,tbEquipe[[#This Row],[Mês]]=Configuração!$D$8),(1+Configuração!$D$4),1)+(IF(tbEquipe[[#This Row],[Mês]]=(Configuração!$D$7-1),Configuração!$D$11*tbEquipe[[#This Row],[Alocação]],0))+(IF(tbEquipe[[#This Row],[Mês]]=(Configuração!$D$9),Configuração!$D$12*tbEquipe[[#This Row],[Alocação]],0)),0) -> 2385.1442
A51: A Definir - ESPECIALISTA EM DEVOPS | B51: =IFERROR(VLOOKUP(tbEquipe[[#This Row],[Nome]],tbFOPAG[[Nome]:[Cargo]],2,0),"<Selecionar Nome>") -> ESPECIALISTA EM DEVOPS | C51: Direto | D51: 5 | E51: =176*tbEquipe[[#This Row],[Alocação]] -> 11.733333 | F51: 0.066666667 | G51: =IFERROR((VLOOKUP(tbEquipe[[#This Row],[Nome]],tbFOPAG[[Nome]:[Custo Total]],3,0)*tbEquipe[[#This Row],[Alocação]]*IF(OR(tbEquipe[[#This Row],[Mês]]>Configuração!$D$7,tbEquipe[[#This Row],[Mês]]=Configuração!$D$7),(1+Configuração!$D$4),1))*IF(OR(tbEquipe[[#This Row],[Mês]]>Configuração!$D$8,tbEquipe[[#This Row],[Mês]]=Configuração!$D$8),(1+Configuração!$D$4),1)+(IF(tbEquipe[[#This Row],[Mês]]=(Configuração!$D$7-1),Configuração!$D$11*tbEquipe[[#This Row],[Alocação]],0))+(IF(tbEquipe[[#This Row],[Mês]]=(Configuração!$D$9),Configuração!$D$12*tbEquipe[[#This Row],[Alocação]],0)),0) -> 2385.1442
A52: A Definir - ESPECIALISTA EM DEVOPS | B52: =IFERROR(VLOOKUP(tbEquipe[[#This Row],[Nome]],tbFOPAG[[Nome]:[Cargo]],2,0),"<Selecionar Nome>") -> ESPECIALISTA EM DEVOPS | C52: Direto | D52: 6 | E52: =176*tbEquipe[[#This Row],[Alocação]] -> 11.733333 | F52: 0.066666667 | G52: =IFERROR((VLOOKUP(tbEquipe[[#This Row],[Nome]],tbFOPAG[[Nome]:[Custo Total]],3,0)*tbEquipe[[#This Row],[Alocação]]*IF(OR(tbEquipe[[#This Row],[Mês]]>Configuração!$D$7,tbEquipe[[#This Row],[Mês]]=Configuração!$D$7),(1+Configuração!$D$4),1))*IF(OR(tbEquipe[[#This Row],[Mês]]>Configuração!$D$8,tbEquipe[[#This Row],[Mês]]=Configuração!$D$8),(1+Configuração!$D$4),1)+(IF(tbEquipe[[#This Row],[Mês]]=(Configuração!$D$7-1),Configuração!$D$11*tbEquipe[[#This Row],[Alocação]],0))+(IF(tbEquipe[[#This Row],[Mês]]=(Configuração!$D$9),Configuração!$D$12*tbEquipe[[#This Row],[Alocação]],0)),0) -> 2385.1442
A53: A Definir - ESPECIALISTA EM DEVOPS | B53: =IFERROR(VLOOKUP(tbEquipe[[#This Row],[Nome]],tbFOPAG[[Nome]:[Cargo]],2,0),"<Selecionar Nome>") -> ESPECIALISTA EM DEVOPS | C53: Direto | D53: 7 | E53: =176*tbEquipe[[#This Row],[Alocação]] -> 11.733333 | F53: 0.066666667 | G53: =IFERROR((VLOOKUP(tbEquipe[[#This Row],[Nome]],tbFOPAG[[Nome]:[Custo Total]],3,0)*tbEquipe[[#This Row],[Alocação]]*IF(OR(tbEquipe[[#This Row],[Mês]]>Configuração!$D$7,tbEquipe[[#This Row],[Mês]]=Configuração!$D$7),(1+Configuração!$D$4),1))*IF(OR(tbEquipe[[#This Row],[Mês]]>Configuração!$D$8,tbEquipe[[#This Row],[Mês]]=Configuração!$D$8),(1+Configuração!$D$4),1)+(IF(tbEquipe[[#This Row],[Mês]]=(Configuração!$D$7-1),Configuração!$D$11*tbEquipe[[#This Row],[Alocação]],0))+(IF(tbEquipe[[#This Row],[Mês]]=(Configuração!$D$9),Configuração!$D$12*tbEquipe[[#This Row],[Alocação]],0)),0) -> 2385.1442
A54: A Definir - ESPECIALISTA EM DEVOPS | B54: =IFERROR(VLOOKUP(tbEquipe[[#This Row],[Nome]],tbFOPAG[[Nome]:[Cargo]],2,0),"<Selecionar Nome>") -> ESPECIALISTA EM DEVOPS | C54: Direto | D54: 8 | E54: =176*tbEquipe[[#This Row],[Alocação]] -> 11.733333 | F54: 0.066666667 | G54: =IFERROR((VLOOKUP(tbEquipe[[#This Row],[Nome]],tbFOPAG[[Nome]:[Custo Total]],3,0)*tbEquipe[[#This Row],[Alocação]]*IF(OR(tbEquipe[[#This Row],[Mês]]>Configuração!$D$7,tbEquipe[[#This Row],[Mês]]=Configuração!$D$7),(1+Configuração!$D$4),1))*IF(OR(tbEquipe[[#This Row],[Mês]]>Configuração!$D$8,tbEquipe[[#This Row],[Mês]]=Configuração!$D$8),(1+Configuração!$D$4),1)+(IF(tbEquipe[[#This Row],[Mês]]=(Configuração!$D$7-1),Configuração!$D$11*tbEquipe[[#This Row],[Alocação]],0))+(IF(tbEquipe[[#This Row],[Mês]]=(Configuração!$D$9),Configuração!$D$12*tbEquipe[[#This Row],[Alocação]],0)),0) -> 2385.1442 | I54: =SUM(G47:G54) -> 18969.478 | J54: =SUM(F47:F54) -> 0.53333333 | K54: =J54/12 -> 0.044444444 | M54: 0.8 | N54: 0.066666667
A55: A Definir - ESPECIALISTA EM DEVOPS | B55: =IFERROR(VLOOKUP(tbEquipe[[#This Row],[Nome]],tbFOPAG[[Nome]:[Cargo]],2,0),"<Selecionar Nome>") -> ESPECIALISTA EM DEVOPS | C55: Direto | D55: 9 | E55: =176*tbEquipe[[#This Row],[Alocação]] -> 11.733333 | F55: 0.066666667 | G55: =IFERROR((VLOOKUP(tbEquipe[[#This Row],[Nome]],tbFOPAG[[Nome]:[Custo Total]],3,0)*tbEquipe[[#This Row],[Alocação]]*IF(OR(tbEquipe[[#This Row],[Mês]]>Configuração!$D$7,tbEquipe[[#This Row],[Mês]]=Configuração!$D$7),(1+Configuração!$D$4),1))*IF(OR(tbEquipe[[#This Row],[Mês]]>Configuração!$D$8,tbEquipe[[#This Row],[Mês]]=Configuração!$D$8),(1+Configuração!$D$4),1)+(IF(tbEquipe[[#This Row],[Mês]]=(Configuração!$D$7-1),Configuração!$D$11*tbEquipe[[#This Row],[Alocação]],0))+(IF(tbEquipe[[#This Row],[Mês]]=(Configuração!$D$9),Configuração!$D$12*tbEquipe[[#This Row],[Alocação]],0)),0) -> 2385.1442
A56: A Definir - ESPECIALISTA EM DEVOPS | B56: =IFERROR(VLOOKUP(tbEquipe[[#This Row],[Nome]],tbFOPAG[[Nome]:[Cargo]],2,0),"<Selecionar Nome>") -> ESPECIALISTA EM DEVOPS | C56: Direto | D56: 10 | E56: =176*tbEquipe[[#This Row],[Alocação]] -> 11.733333 | F56: 0.066666667 | G56: =IFERROR((VLOOKUP(tbEquipe[[#This Row],[Nome]],tbFOPAG[[Nome]:[Custo Total]],3,0)*tbEquipe[[#This Row],[Alocação]]*IF(OR(tbEquipe[[#This Row],[Mês]]>Configuração!$D$7,tbEquipe[[#This Row],[Mês]]=Configuração!$D$7),(1+Configuração!$D$4),1))*IF(OR(tbEquipe[[#This Row],[Mês]]>Configuração!$D$8,tbEquipe[[#This Row],[Mês]]=Configuração!$D$8),(1+Configuração!$D$4),1)+(IF(tbEquipe[[#This Row],[Mês]]=(Configuração!$D$7-1),Configuração!$D$11*tbEquipe[[#This Row],[Alocação]],0))+(IF(tbEquipe[[#This Row],[Mês]]=(Configuração!$D$9),Configuração!$D$12*tbEquipe[[#This Row],[Alocação]],0)),0) -> 2385.1442
A57: A Definir - ESPECIALISTA EM DEVOPS | B57: =IFERROR(VLOOKUP(tbEquipe[[#This Row],[Nome]],tbFOPAG[[Nome]:[Cargo]],2,0),"<Selecionar Nome>") -> ESPECIALISTA EM DEVOPS | C57: Direto | D57: 11 | E57: =176*tbEquipe[[#This Row],[Alocação]] -> 11.733333 | F57: 0.066666667 | G57: =IFERROR((VLOOKUP(tbEquipe[[#This Row],[Nome]],tbFOPAG[[Nome]:[Custo Total]],3,0)*tbEquipe[[#This Row],[Alocação]]*IF(OR(tbEquipe[[#This Row],[Mês]]>Configuração!$D$7,tbEquipe[[#This Row],[Mês]]=Configuração!$D$7),(1+Configuração!$D$4),1))*IF(OR(tbEquipe[[#This Row],[Mês]]>Configuração!$D$8,tbEquipe[[#This Row],[Mês]]=Configuração!$D$8),(1+Configuração!$D$4),1)+(IF(tbEquipe[[#This Row],[Mês]]=(Configuração!$D$7-1),Configuração!$D$11*tbEquipe[[#This Row],[Alocação]],0))+(IF(tbEquipe[[#This Row],[Mês]]=(Configuração!$D$9),Configuração!$D$12*tbEquipe[[#This Row],[Alocação]],0)),0) -> 2385.1442
A58: A Definir - ESPECIALISTA EM DEVOPS | B58: =IFERROR(VLOOKUP(tbEquipe[[#This Row],[Nome]],tbFOPAG[[Nome]:[Cargo]],2,0),"<Selecionar Nome>") -> ESPECIALISTA EM DEVOPS | C58: Direto | D58: 12 | E58: =176*tbEquipe[[#This Row],[Alocação]] -> 11.733333 | F58: 0.066666667 | G58: =IFERROR((VLOOKUP(tbEquipe[[#This Row],[Nome]],tbFOPAG[[Nome]:[Custo Total]],3,0)*tbEquipe[[#This Row],[Alocação]]*IF(OR(tbEquipe[[#This Row],[Mês]]>Configuração!$D$7,tbEquipe[[#This Row],[Mês]]=Configuração!$D$7),(1+Configuração!$D$4),1))*IF(OR(tbEquipe[[#This Row],[Mês]]>Configuração!$D$8,tbEquipe[[#This Row],[Mês]]=Configuração!$D$8),(1+Configuração!$D$4),1)+(IF(tbEquipe[[#This Row],[Mês]]=(Configuração!$D$7-1),Configuração!$D$11*tbEquipe[[#This Row],[Alocação]],0))+(IF(tbEquipe[[#This Row],[Mês]]=(Configuração!$D$9),Configuração!$D$12*tbEquipe[[#This Row],[Alocação]],0)),0) -> 2385.1442
A59: A Definir - ESPECIALISTA EM DEVOPS | B59: =IFERROR(VLOOKUP(tbEquipe[[#This Row],[Nome]],tbFOPAG[[Nome]:[Cargo]],2,0),"<Selecionar Nome>") -> ESPECIALISTA EM DEVOPS | C59: Direto | D59: 13 | E59: =176*tbEquipe[[#This Row],[Alocação]] -> 0 | G59: =IFERROR((VLOOKUP(tbEquipe[[#This Row],[Nome]],tbFOPAG[[Nome]:[Custo Total]],3,0)*tbEquipe[[#This Row],[Alocação]]*IF(OR(tbEquipe[[#This Row],[Mês]]>Configuração!$D$7,tbEquipe[[#This Row],[Mês]]=Configuração!$D$7),(1+Configuração!$D$4),1))*IF(OR(tbEquipe[[#This Row],[Mês]]>Configuração!$D$8,tbEquipe[[#This Row],[Mês]]=Configuração!$D$8),(1+Configuração!$D$4),1)+(IF(tbEquipe[[#This Row],[Mês]]=(Configuração!$D$7-1),Configuração!$D$11*tbEquipe[[#This Row],[Alocação]],0))+(IF(tbEquipe[[#This Row],[Mês]]=(Configuração!$D$9),Configuração!$D$12*tbEquipe[[#This Row],[Alocação]],0)),0) -> 0
A60: A Definir - ESPECIALISTA EM DEVOPS | B60: =IFERROR(VLOOKUP(tbEquipe[[#This Row],[Nome]],tbFOPAG[[Nome]:[Cargo]],2,0),"<Selecionar Nome>") -> ESPECIALISTA EM DEVOPS | C60: Direto | D60: 14 | E60: =176*tbEquipe[[#This Row],[Alocação]] -> 0 | G60: =IFERROR((VLOOKUP(tbEquipe[[#This Row],[Nome]],tbFOPAG[[Nome]:[Custo Total]],3,0)*tbEquipe[[#This Row],[Alocação]]*IF(OR(tbEquipe[[#This Row],[Mês]]>Configuração!$D$7,tbEquipe[[#This Row],[Mês]]=Configuração!$D$7),(1+Configuração!$D$4),1))*IF(OR(tbEquipe[[#This Row],[Mês]]>Configuração!$D$8,tbEquipe[[#This Row],[Mês]]=Configuração!$D$8),(1+Configuração!$D$4),1)+(IF(tbEquipe[[#This Row],[Mês]]=(Configuração!$D$7-1),Configuração!$D$11*tbEquipe[[#This Row],[Alocação]],0))+(IF(tbEquipe[[#This Row],[Mês]]=(Configuração!$D$9),Configuração!$D$12*tbEquipe[[#This Row],[Alocação]],0)),0) -> 0
A61: A Definir - ESPECIALISTA EM DEVOPS | B61: =IFERROR(VLOOKUP(tbEquipe[[#This Row],[Nome]],tbFOPAG[[Nome]:[Cargo]],2,0),"<Selecionar Nome>") -> ESPECIALISTA EM DEVOPS | C61: Direto | D61: 15 | E61: =176*tbEquipe[[#This Row],[Alocação]] -> 0 | G61: =IFERROR((VLOOKUP(tbEquipe[[#This Row],[Nome]],tbFOPAG[[Nome]:[Custo Total]],3,0)*tbEquipe[[#This Row],[Alocação]]*IF(OR(tbEquipe[[#This Row],[Mês]]>Configuração!$D$7,tbEquipe[[#This Row],[Mês]]=Configuração!$D$7),(1+Configuração!$D$4),1))*IF(OR(tbEquipe[[#This Row],[Mês]]>Configuração!$D$8,tbEquipe[[#This Row],[Mês]]=Configuração!$D$8),(1+Configuração!$D$4),1)+(IF(tbEquipe[[#This Row],[Mês]]=(Configuração!$D$7-1),Configuração!$D$11*tbEquipe[[#This Row],[Alocação]],0))+(IF(tbEquipe[[#This Row],[Mês]]=(Configuração!$D$9),Configuração!$D$12*tbEquipe[[#This Row],[Alocação]],0)),0) -> 0 | I61: =SUM(G47:G61) -> 28510.055
A62: A definir - ANALISTA DE AUTOMAÇÃO PL | B62: =IFERROR(VLOOKUP(tbEquipe[[#This Row],[Nome]],tbFOPAG[[Nome]:[Cargo]],2,0),"<Selecionar Nome>") -> ANALISTA DE AUTOMAÇÃO PL | C62: Direto | D62: 1 | E62: =176*tbEquipe[[#This Row],[Alocação]] -> 117.33333 | F62: 0.66666667 | G62: =IFERROR((VLOOKUP(tbEquipe[[#This Row],[Nome]],tbFOPAG[[Nome]:[Custo Total]],3,0)*tbEquipe[[#This Row],[Alocação]]*IF(OR(tbEquipe[[#This Row],[Mês]]>Configuração!$D$7,tbEquipe[[#This Row],[Mês]]=Configuração!$D$7),(1+Configuração!$D$4),1))*IF(OR(tbEquipe[[#This Row],[Mês]]>Configuração!$D$8,tbEquipe[[#This Row],[Mês]]=Configuração!$D$8),(1+Configuração!$D$4),1)+(IF(tbEquipe[[#This Row],[Mês]]=(Configuração!$D$7-1),Configuração!$D$11*tbEquipe[[#This Row],[Alocação]],0))+(IF(tbEquipe[[#This Row],[Mês]]=(Configuração!$D$9),Configuração!$D$12*tbEquipe[[#This Row],[Alocação]],0)),0) -> 10783.286
A63: A definir - ANALISTA DE AUTOMAÇÃO PL | B63: =IFERROR(VLOOKUP(tbEquipe[[#This Row],[Nome]],tbFOPAG[[Nome]:[Cargo]],2,0),"<Selecionar Nome>") -> ANALISTA DE AUTOMAÇÃO PL | C63: Direto | D63: 2 | E63: =176*tbEquipe[[#This Row],[Alocação]] -> 117.33333 | F63: 0.66666667 | G63: =IFERROR((VLOOKUP(tbEquipe[[#This Row],[Nome]],tbFOPAG[[Nome]:[Custo Total]],3,0)*tbEquipe[[#This Row],[Alocação]]*IF(OR(tbEquipe[[#This Row],[Mês]]>Configuração!$D$7,tbEquipe[[#This Row],[Mês]]=Configuração!$D$7),(1+Configuração!$D$4),1))*IF(OR(tbEquipe[[#This Row],[Mês]]>Configuração!$D$8,tbEquipe[[#This Row],[Mês]]=Configuração!$D$8),(1+Configuração!$D$4),1)+(IF(tbEquipe[[#This Row],[Mês]]=(Configuração!$D$7-1),Configuração!$D$11*tbEquipe[[#This Row],[Alocação]],0))+(IF(tbEquipe[[#This Row],[Mês]]=(Configuração!$D$9),Configuração!$D$12*tbEquipe[[#This Row],[Alocação]],0)),0) -> 11182.95
A64: A definir - ANALISTA DE AUTOMAÇÃO PL | B64: =IFERROR(VLOOKUP(tbEquipe[[#This Row],[Nome]],tbFOPAG[[Nome]:[Cargo]],2,0),"<Selecionar Nome>") -> ANALISTA DE AUTOMAÇÃO PL | C64: Direto | D64: 3 | E64: =176*tbEquipe[[#This Row],[Alocação]] -> 117.33333 | F64: 0.66666667 | G64: =IFERROR((VLOOKUP(tbEquipe[[#This Row],[Nome]],tbFOPAG[[Nome]:[Custo Total]],3,0)*tbEquipe[[#This Row],[Alocação]]*IF(OR(tbEquipe[[#This Row],[Mês]]>Configuração!$D$7,tbEquipe[[#This Row],[Mês]]=Configuração!$D$7),(1+Configuração!$D$4),1))*IF(OR(tbEquipe[[#This Row],[Mês]]>Configuração!$D$8,tbEquipe[[#This Row],[Mês]]=Configuração!$D$8),(1+Configuração!$D$4),1)+(IF(tbEquipe[[#This Row],[Mês]]=(Configuração!$D$7-1),Configuração!$D$11*tbEquipe[[#This Row],[Alocação]],0))+(IF(tbEquipe[[#This Row],[Mês]]=(Configuração!$D$9),Configuração!$D$12*tbEquipe[[#This Row],[Alocação]],0)),0) -> 11182.95
A65: A definir - ANALISTA DE AUTOMAÇÃO PL | B65: =IFERROR(VLOOKUP(tbEquipe[[#This Row],[Nome]],tbFOPAG[[Nome]:[Cargo]],2,0),"<Selecionar Nome>") -> ANALISTA DE AUTOMAÇÃO PL | C65: Direto | D65: 4 | E65: =176*tbEquipe[[#This Row],[Alocação]] -> 117.33333 | F65: 0.66666667 | G65: =IFERROR((VLOOKUP(tbEquipe[[#This Row],[Nome]],tbFOPAG[[Nome]:[Custo Total]],3,0)*tbEquipe[[#This Row],[Alocação]]*IF(OR(tbEquipe[[#This Row],[Mês]]>Configuração!$D$7,tbEquipe[[#This Row],[Mês]]=Configuração!$D$7),(1+Configuração!$D$4),1))*IF(OR(tbEquipe[[#This Row],[Mês]]>Configuração!$D$8,tbEquipe[[#This Row],[Mês]]=Configuração!$D$8),(1+Configuração!$D$4),1)+(IF(tbEquipe[[#This Row],[Mês]]=(Configuração!$D$7-1),Configuração!$D$11*tbEquipe[[#This Row],[Alocação]],0))+(IF(tbEquipe[[#This Row],[Mês]]=(Configuração!$D$9),Configuração!$D$12*tbEquipe[[#This Row],[Alocação]],0)),0) -> 11182.95
A66: A definir - ANALISTA DE AUTOMAÇÃO PL | B66: =IFERROR(VLOOKUP(tbEquipe[[#This Row],[Nome]],tbFOPAG[[Nome]:[Cargo]],2,0),"<Selecionar Nome>") -> ANALISTA DE AUTOMAÇÃO PL | C66: Direto | D66: 5 | E66: =176*tbEquipe[[#This Row],[Alocação]] -> 117.33333 | F66: 0.66666667 | G66: =IFERROR((VLOOKUP(tbEquipe[[#This Row],[Nome]],tbFOPAG[[Nome]:[Custo Total]],3,0)*tbEquipe[[#This Row],[Alocação]]*IF(OR(tbEquipe[[#This Row],[Mês]]>Configuração!$D$7,tbEquipe[[#This Row],[Mês]]=Configuração!$D$7),(1+Configuração!$D$4),1))*IF(OR(tbEquipe[[#This Row],[Mês]]>Configuração!$D$8,tbEquipe[[#This Row],[Mês]]=Configuração!$D$8),(1+Configuração!$D$4),1)+(IF(tbEquipe[[#This Row],[Mês]]=(Configuração!$D$7-1),Configuração!$D$11*tbEquipe[[#This Row],[Alocação]],0))+(IF(tbEquipe[[#This Row],[Mês]]=(Configuração!$D$9),Configuração!$D$12*tbEquipe[[#This Row],[Alocação]],0)),0) -> 11182.95
A67: A definir - ANALISTA DE AUTOMAÇÃO PL | B67: =IFERROR(VLOOKUP(tbEquipe[[#This Row],[Nome]],tbFOPAG[[Nome]:[Cargo]],2,0),"<Selecionar Nome>") -> ANALISTA DE AUTOMAÇÃO PL | C67: Direto | D67: 6 | E67: =176*tbEquipe[[#This Row],[Alocação]] -> 117.33333 | F67: 0.66666667 | G67: =IFERROR((VLOOKUP(tbEquipe[[#This Row],[Nome]],tbFOPAG[[Nome]:[Custo Total]],3,0)*tbEquipe[[#This Row],[Alocação]]*IF(OR(tbEquipe[[#This Row],[Mês]]>Configuração!$D$7,tbEquipe[[#This Row],[Mês]]=Configuração!$D$7),(1+Configuração!$D$4),1))*IF(OR(tbEquipe[[#This Row],[Mês]]>Configuração!$D$8,tbEquipe[[#This Row],[Mês]]=Configuração!$D$8),(1+Configuração!$D$4),1)+(IF(tbEquipe[[#This Row],[Mês]]=(Configuração!$D$7-1),Configuração!$D$11*tbEquipe[[#This Row],[Alocação]],0))+(IF(tbEquipe[[#This Row],[Mês]]=(Configuração!$D$9),Configuração!$D$12*tbEquipe[[#This Row],[Alocação]],0)),0) -> 11182.95
A68: A definir - ANALISTA DE AUTOMAÇÃO PL | B68: =IFERROR(VLOOKUP(tbEquipe[[#This Row],[Nome]],tbFOPAG[[Nome]:[Cargo]],2,0),"<Selecionar Nome>") -> ANALISTA DE AUTOMAÇÃO PL | C68: Direto | D68: 7 | E68: =176*tbEquipe[[#This Row],[Alocação]] -> 117.33333 | F68: 0.66666667 | G68: =IFERROR((VLOOKUP(tbEquipe[[#This Row],[Nome]],tbFOPAG[[Nome]:[Custo Total]],3,0)*tbEquipe[[#This Row],[Alocação]]*IF(OR(tbEquipe[[#This Row],[Mês]]>Configuração!$D$7,tbEquipe[[#This Row],[Mês]]=Configuração!$D$7),(1+Configuração!$D$4),1))*IF(OR(tbEquipe[[#This Row],[Mês]]>Configuração!$D$8,tbEquipe[[#This Row],[Mês]]=Configuração!$D$8),(1+Configuração!$D$4),1)+(IF(tbEquipe[[#This Row],[Mês]]=(Configuração!$D$7-1),Configuração!$D$11*tbEquipe[[#This Row],[Alocação]],0))+(IF(tbEquipe[[#This Row],[Mês]]=(Configuração!$D$9),Configuração!$D$12*tbEquipe[[#This Row],[Alocação]],0)),0) -> 11182.95
A69: A definir - ANALISTA DE AUTOMAÇÃO PL | B69: =IFERROR(VLOOKUP(tbEquipe[[#This Row],[Nome]],tbFOPAG[[Nome]:[Cargo]],2,0),"<Selecionar Nome>") -> ANALISTA DE AUTOMAÇÃO PL | C69: Direto | D69: 8 | E69: =176*tbEquipe[[#This Row],[Alocação]] -> 117.33333 | F69: 0.66666667 | G69: =IFERROR((VLOOKUP(tbEquipe[[#This Row],[Nome]],tbFOPAG[[Nome]:[Custo Total]],3,0)*tbEquipe[[#This Row],[Alocação]]*IF(OR(tbEquipe[[#This Row],[Mês]]>Configuração!$D$7,tbEquipe[[#This Row],[Mês]]=Configuração!$D$7),(1+Configuração!$D$4),1))*IF(OR(tbEquipe[[#This Row],[Mês]]>Configuração!$D$8,tbEquipe[[#This Row],[Mês]]=Configuração!$D$8),(1+Configuração!$D$4),1)+(IF(tbEquipe[[#This Row],[Mês]]=(Configuração!$D$7-1),Configuração!$D$11*tbEquipe[[#This Row],[Alocação]],0))+(IF(tbEquipe[[#This Row],[Mês]]=(Configuração!$D$9),Configuração!$D$12*tbEquipe[[#This Row],[Alocação]],0)),0) -> 11182.95 | I69: =SUM(G62:G69) -> 89063.938 | J69: =SUM(F62:F69) -> 5.3333333 | K69: =J69/12 -> 0.44444444 | M69: 8 | N69: 0.66666667
A70: A definir - ANALISTA DE AUTOMAÇÃO PL | B70: =IFERROR(VLOOKUP(tbEquipe[[#This Row],[Nome]],tbFOPAG[[Nome]:[Cargo]],2,0),"<Selecionar Nome>") -> ANALISTA DE AUTOMAÇÃO PL | C70: Direto | D70: 9 | E70: =176*tbEquipe[[#This Row],[Alocação]] -> 117.33333 | F70: 0.66666667 | G70: =IFERROR((VLOOKUP(tbEquipe[[#This Row],[Nome]],tbFOPAG[[Nome]:[Custo Total]],3,0)*tbEquipe[[#This Row],[Alocação]]*IF(OR(tbEquipe[[#This Row],[Mês]]>Configuração!$D$7,tbEquipe[[#This Row],[Mês]]=Configuração!$D$7),(1+Configuração!$D$4),1))*IF(OR(tbEquipe[[#This Row],[Mês]]>Configuração!$D$8,tbEquipe[[#This Row],[Mês]]=Configuração!$D$8),(1+Configuração!$D$4),1)+(IF(tbEquipe[[#This Row],[Mês]]=(Configuração!$D$7-1),Configuração!$D$11*tbEquipe[[#This Row],[Alocação]],0))+(IF(tbEquipe[[#This Row],[Mês]]=(Configuração!$D$9),Configuração!$D$12*tbEquipe[[#This Row],[Alocação]],0)),0) -> 11182.95
A71: A definir - ANALISTA DE AUTOMAÇÃO PL | B71: =IFERROR(VLOOKUP(tbEquipe[[#This Row],[Nome]],tbFOPAG[[Nome]:[Cargo]],2,0),"<Selecionar Nome>") -> ANALISTA DE AUTOMAÇÃO PL | C71: Direto | D71: 10 | E71: =176*tbEquipe[[#This Row],[Alocação]] -> 117.33333 | F71: 0.66666667 | G71: =IFERROR((VLOOKUP(tbEquipe[[#This Row],[Nome]],tbFOPAG[[Nome]:[Custo Total]],3,0)*tbEquipe[[#This Row],[Alocação]]*IF(OR(tbEquipe[[#This Row],[Mês]]>Configuração!$D$7,tbEquipe[[#This Row],[Mês]]=Configuração!$D$7),(1+Configuração!$D$4),1))*IF(OR(tbEquipe[[#This Row],[Mês]]>Configuração!$D$8,tbEquipe[[#This Row],[Mês]]=Configuração!$D$8),(1+Configuração!$D$4),1)+(IF(tbEquipe[[#This Row],[Mês]]=(Configuração!$D$7-1),Configuração!$D$11*tbEquipe[[#This Row],[Alocação]],0))+(IF(tbEquipe[[#This Row],[Mês]]=(Configuração!$D$9),Configuração!$D$12*tbEquipe[[#This Row],[Alocação]],0)),0) -> 11182.95
A72: A definir - ANALISTA DE AUTOMAÇÃO PL | B72: =IFERROR(VLOOKUP(tbEquipe[[#This Row],[Nome]],tbFOPAG[[Nome]:[Cargo]],2,0),"<Selecionar Nome>") -> ANALISTA DE AUTOMAÇÃO PL | C72: Direto | D72: 11 | E72: =176*tbEquipe[[#This Row],[Alocação]] -> 117.33333 | F72: 0.66666667 | G72: =IFERROR((VLOOKUP(tbEquipe[[#This Row],[Nome]],tbFOPAG[[Nome]:[Custo Total]],3,0)*tbEquipe[[#This Row],[Alocação]]*IF(OR(tbEquipe[[#This Row],[Mês]]>Configuração!$D$7,tbEquipe[[#This Row],[Mês]]=Configuração!$D$7),(1+Configuração!$D$4),1))*IF(OR(tbEquipe[[#This Row],[Mês]]>Configuração!$D$8,tbEquipe[[#This Row],[Mês]]=Configuração!$D$8),(1+Configuração!$D$4),1)+(IF(tbEquipe[[#This Row],[Mês]]=(Configuração!$D$7-1),Configuração!$D$11*tbEquipe[[#This Row],[Alocação]],0))+(IF(tbEquipe[[#This Row],[Mês]]=(Configuração!$D$9),Configuração!$D$12*tbEquipe[[#This Row],[Alocação]],0)),0) -> 11182.95
A73: A definir - ANALISTA DE AUTOMAÇÃO PL | B73: =IFERROR(VLOOKUP(tbEquipe[[#This Row],[Nome]],tbFOPAG[[Nome]:[Cargo]],2,0),"<Selecionar Nome>") -> ANALISTA DE AUTOMAÇÃO PL | C73: Direto | D73: 12 | E73: =176*tbEquipe[[#This Row],[Alocação]] -> 117.33333 | F73: 0.66666667 | G73: =IFERROR((VLOOKUP(tbEquipe[[#This Row],[Nome]],tbFOPAG[[Nome]:[Custo Total]],3,0)*tbEquipe[[#This Row],[Alocação]]*IF(OR(tbEquipe[[#This Row],[Mês]]>Configuração!$D$7,tbEquipe[[#This Row],[Mês]]=Configuração!$D$7),(1+Configuração!$D$4),1))*IF(OR(tbEquipe[[#This Row],[Mês]]>Configuração!$D$8,tbEquipe[[#This Row],[Mês]]=Configuração!$D$8),(1+Configuração!$D$4),1)+(IF(tbEquipe[[#This Row],[Mês]]=(Configuração!$D$7-1),Configuração!$D$11*tbEquipe[[#This Row],[Alocação]],0))+(IF(tbEquipe[[#This Row],[Mês]]=(Configuração!$D$9),Configuração!$D$12*tbEquipe[[#This Row],[Alocação]],0)),0) -> 11182.95 | I73: =SUM(G62:G73) -> 133795.74 | J73: HW | M73: HW
A74: A Definir - DESIGNER UX/UI JR | B74: =IFERROR(VLOOKUP(tbEquipe[[#This Row],[Nome]],tbFOPAG[[Nome]:[Cargo]],2,0),"<Selecionar Nome>") -> DESIGNER UX/UI JR | C74: Direto | D74: 1 | E74: =176*tbEquipe[[#This Row],[Alocação]] -> 38.72 | F74: 0.22 | G74: =IFERROR((VLOOKUP(tbEquipe[[#This Row],[Nome]],tbFOPAG[[Nome]:[Custo Total]],3,0)*tbEquipe[[#This Row],[Alocação]]*IF(OR(tbEquipe[[#This Row],[Mês]]>Configuração!$D$7,tbEquipe[[#This Row],[Mês]]=Configuração!$D$7),(1+Configuração!$D$4),1))*IF(OR(tbEquipe[[#This Row],[Mês]]>Configuração!$D$8,tbEquipe[[#This Row],[Mês]]=Configuração!$D$8),(1+Configuração!$D$4),1)+(IF(tbEquipe[[#This Row],[Mês]]=(Configuração!$D$7-1),Configuração!$D$11*tbEquipe[[#This Row],[Alocação]],0))+(IF(tbEquipe[[#This Row],[Mês]]=(Configuração!$D$9),Configuração!$D$12*tbEquipe[[#This Row],[Alocação]],0)),0) -> 2091.7644
A75: A Definir - DESIGNER UX/UI JR | B75: =IFERROR(VLOOKUP(tbEquipe[[#This Row],[Nome]],tbFOPAG[[Nome]:[Cargo]],2,0),"<Selecionar Nome>") -> DESIGNER UX/UI JR | C75: Direto | D75: 2 | E75: =176*tbEquipe[[#This Row],[Alocação]] -> 38.72 | F75: 0.22 | G75: =IFERROR((VLOOKUP(tbEquipe[[#This Row],[Nome]],tbFOPAG[[Nome]:[Custo Total]],3,0)*tbEquipe[[#This Row],[Alocação]]*IF(OR(tbEquipe[[#This Row],[Mês]]>Configuração!$D$7,tbEquipe[[#This Row],[Mês]]=Configuração!$D$7),(1+Configuração!$D$4),1))*IF(OR(tbEquipe[[#This Row],[Mês]]>Configuração!$D$8,tbEquipe[[#This Row],[Mês]]=Configuração!$D$8),(1+Configuração!$D$4),1)+(IF(tbEquipe[[#This Row],[Mês]]=(Configuração!$D$7-1),Configuração!$D$11*tbEquipe[[#This Row],[Alocação]],0))+(IF(tbEquipe[[#This Row],[Mês]]=(Configuração!$D$9),Configuração!$D$12*tbEquipe[[#This Row],[Alocação]],0)),0) -> 2135.6503
A76: A Definir - DESIGNER UX/UI JR | B76: =IFERROR(VLOOKUP(tbEquipe[[#This Row],[Nome]],tbFOPAG[[Nome]:[Cargo]],2,0),"<Selecionar Nome>") -> DESIGNER UX/UI JR | C76: Direto | D76: 3 | E76: =176*tbEquipe[[#This Row],[Alocação]] -> 38.72 | F76: 0.22 | G76: =IFERROR((VLOOKUP(tbEquipe[[#This Row],[Nome]],tbFOPAG[[Nome]:[Custo Total]],3,0)*tbEquipe[[#This Row],[Alocação]]*IF(OR(tbEquipe[[#This Row],[Mês]]>Configuração!$D$7,tbEquipe[[#This Row],[Mês]]=Configuração!$D$7),(1+Configuração!$D$4),1))*IF(OR(tbEquipe[[#This Row],[Mês]]>Configuração!$D$8,tbEquipe[[#This Row],[Mês]]=Configuração!$D$8),(1+Configuração!$D$4),1)+(IF(tbEquipe[[#This Row],[Mês]]=(Configuração!$D$7-1),Configuração!$D$11*tbEquipe[[#This Row],[Alocação]],0))+(IF(tbEquipe[[#This Row],[Mês]]=(Configuração!$D$9),Configuração!$D$12*tbEquipe[[#This Row],[Alocação]],0)),0) -> 2135.6503
A77: A Definir - DESIGNER UX/UI JR | B77: =IFERROR(VLOOKUP(tbEquipe[[#This Row],[Nome]],tbFOPAG[[Nome]:[Cargo]],2,0),"<Selecionar Nome>") -> DESIGNER UX/UI JR | C77: Direto | D77: 4 | E77: =176*tbEquipe[[#This Row],[Alocação]] -> 38.72 | F77: 0.22 | G77: =IFERROR((VLOOKUP(tbEquipe[[#This Row],[Nome]],tbFOPAG[[Nome]:[Custo Total]],3,0)*tbEquipe[[#This Row],[Alocação]]*IF(OR(tbEquipe[[#This Row],[Mês]]>Configuração!$D$7,tbEquipe[[#This Row],[Mês]]=Configuração!$D$7),(1+Configuração!$D$4),1))*IF(OR(tbEquipe[[#This Row],[Mês]]>Configuração!$D$8,tbEquipe[[#This Row],[Mês]]=Configuração!$D$8),(1+Configuração!$D$4),1)+(IF(tbEquipe[[#This Row],[Mês]]=(Configuração!$D$7-1),Configuração!$D$11*tbEquipe[[#This Row],[Alocação]],0))+(IF(tbEquipe[[#This Row],[Mês]]=(Configuração!$D$9),Configuração!$D$12*tbEquipe[[#This Row],[Alocação]],0)),0) -> 2135.6503
A78: A Definir - DESIGNER UX/UI JR | B78: =IFERROR(VLOOKUP(tbEquipe[[#This Row],[Nome]],tbFOPAG[[Nome]:[Cargo]],2,0),"<Selecionar Nome>") -> DESIGNER UX/UI JR | C78: Direto | D78: 5 | E78: =176*tbEquipe[[#This Row],[Alocação]] -> 38.72 | F78: 0.22 | G78: =IFERROR((VLOOKUP(tbEquipe[[#This Row],[Nome]],tbFOPAG[[Nome]:[Custo Total]],3,0)*tbEquipe[[#This Row],[Alocação]]*IF(OR(tbEquipe[[#This Row],[Mês]]>Configuração!$D$7,tbEquipe[[#This Row],[Mês]]=Configuração!$D$7),(1+Configuração!$D$4),1))*IF(OR(tbEquipe[[#This Row],[Mês]]>Configuração!$D$8,tbEquipe[[#This Row],[Mês]]=Configuração!$D$8),(1+Configuração!$D$4),1)+(IF(tbEquipe[[#This Row],[Mês]]=(Configuração!$D$7-1),Configuração!$D$11*tbEquipe[[#This Row],[Alocação]],0))+(IF(tbEquipe[[#This Row],[Mês]]=(Configuração!$D$9),Configuração!$D$12*tbEquipe[[#This Row],[Alocação]],0)),0) -> 2135.6503
A79: A Definir - DESIGNER UX/UI JR | B79: =IFERROR(VLOOKUP(tbEquipe[[#This Row],[Nome]],tbFOPAG[[Nome]:[Cargo]],2,0),"<Selecionar Nome>") -> DESIGNER UX/UI JR | C79: Direto | D79: 6 | E79: =176*tbEquipe[[#This Row],[Alocação]] -> 38.72 | F79: 0.22 | G79: =IFERROR((VLOOKUP(tbEquipe[[#This Row],[Nome]],tbFOPAG[[Nome]:[Custo Total]],3,0)*tbEquipe[[#This Row],[Alocação]]*IF(OR(tbEquipe[[#This Row],[Mês]]>Configuração!$D$7,tbEquipe[[#This Row],[Mês]]=Configuração!$D$7),(1+Configuração!$D$4),1))*IF(OR(tbEquipe[[#This Row],[Mês]]>Configuração!$D$8,tbEquipe[[#This Row],[Mês]]=Configuração!$D$8),(1+Configuração!$D$4),1)+(IF(tbEquipe[[#This Row],[Mês]]=(Configuração!$D$7-1),Configuração!$D$11*tbEquipe[[#This Row],[Alocação]],0))+(IF(tbEquipe[[#This Row],[Mês]]=(Configuração!$D$9),Configuração!$D$12*tbEquipe[[#This Row],[Alocação]],0)),0) -> 2135.6503
A80: A Definir - DESIGNER UX/UI JR | B80: =IFERROR(VLOOKUP(tbEquipe[[#This Row],[Nome]],tbFOPAG[[Nome]:[Cargo]],2,0),"<Selecionar Nome>") -> DESIGNER UX/UI JR | C80: Direto | D80: 7 | E80: =176*tbEquipe[[#This Row],[Alocação]] -> 38.72 | F80: 0.22 | G80: =IFERROR((VLOOKUP(tbEquipe[[#This Row],[Nome]],tbFOPAG[[Nome]:[Custo Total]],3,0)*tbEquipe[[#This Row],[Alocação]]*IF(OR(tbEquipe[[#This Row],[Mês]]>Configuração!$D$7,tbEquipe[[#This Row],[Mês]]=Configuração!$D$7),(1+Configuração!$D$4),1))*IF(OR(tbEquipe[[#This Row],[Mês]]>Configuração!$D$8,tbEquipe[[#This Row],[Mês]]=Configuração!$D$8),(1+Configuração!$D$4),1)+(IF(tbEquipe[[#This Row],[Mês]]=(Configuração!$D$7-1),Configuração!$D$11*tbEquipe[[#This Row],[Alocação]],0))+(IF(tbEquipe[[#This Row],[Mês]]=(Configuração!$D$9),Configuração!$D$12*tbEquipe[[#This Row],[Alocação]],0)),0) -> 2135.6503
A81: A Definir - DESIGNER UX/UI JR | B81: =IFERROR(VLOOKUP(tbEquipe[[#This Row],[Nome]],tbFOPAG[[Nome]:[Cargo]],2,0),"<Selecionar Nome>") -> DESIGNER UX/UI JR | C81: Direto | D81: 8 | E81: =176*tbEquipe[[#This Row],[Alocação]] -> 38.72 | F81: 0.22 | G81: =IFERROR((VLOOKUP(tbEquipe[[#This Row],[Nome]],tbFOPAG[[Nome]:[Custo Total]],3,0)*tbEquipe[[#This Row],[Alocação]]*IF(OR(tbEquipe[[#This Row],[Mês]]>Configuração!$D$7,tbEquipe[[#This Row],[Mês]]=Configuração!$D$7),(1+Configuração!$D$4),1))*IF(OR(tbEquipe[[#This Row],[Mês]]>Configuração!$D$8,tbEquipe[[#This Row],[Mês]]=Configuração!$D$8),(1+Configuração!$D$4),1)+(IF(tbEquipe[[#This Row],[Mês]]=(Configuração!$D$7-1),Configuração!$D$11*tbEquipe[[#This Row],[Alocação]],0))+(IF(tbEquipe[[#This Row],[Mês]]=(Configuração!$D$9),Configuração!$D$12*tbEquipe[[#This Row],[Alocação]],0)),0) -> 2135.6503 | I81: =SUM(G74:G81) -> 17041.316 | J81: =SUM(F74:F81) -> 1.76 | K81: =J81/12 -> 0.14666667 | M81: 2.64 | N81: 0.22
A82: A Definir - DESIGNER UX/UI JR | B82: =IFERROR(VLOOKUP(tbEquipe[[#This Row],[Nome]],tbFOPAG[[Nome]:[Cargo]],2,0),"<Selecionar Nome>") -> DESIGNER UX/UI JR | C82: Direto | D82: 9 | E82: =176*tbEquipe[[#This Row],[Alocação]] -> 38.72 | F82: 0.22 | G82: =IFERROR((VLOOKUP(tbEquipe[[#This Row],[Nome]],tbFOPAG[[Nome]:[Custo Total]],3,0)*tbEquipe[[#This Row],[Alocação]]*IF(OR(tbEquipe[[#This Row],[Mês]]>Configuração!$D$7,tbEquipe[[#This Row],[Mês]]=Configuração!$D$7),(1+Configuração!$D$4),1))*IF(OR(tbEquipe[[#This Row],[Mês]]>Configuração!$D$8,tbEquipe[[#This Row],[Mês]]=Configuração!$D$8),(1+Configuração!$D$4),1)+(IF(tbEquipe[[#This Row],[Mês]]=(Configuração!$D$7-1),Configuração!$D$11*tbEquipe[[#This Row],[Alocação]],0))+(IF(tbEquipe[[#This Row],[Mês]]=(Configuração!$D$9),Configuração!$D$12*tbEquipe[[#This Row],[Alocação]],0)),0) -> 2135.6503
A83: A Definir - DESIGNER UX/UI JR | B83: =IFERROR(VLOOKUP(tbEquipe[[#This Row],[Nome]],tbFOPAG[[Nome]:[Cargo]],2,0),"<Selecionar Nome>") -> DESIGNER UX/UI JR | C83: Direto | D83: 10 | E83: =176*tbEquipe[[#This Row],[Alocação]] -> 38.72 | F83: 0.22 | G83: =IFERROR((VLOOKUP(tbEquipe[[#This Row],[Nome]],tbFOPAG[[Nome]:[Custo Total]],3,0)*tbEquipe[[#This Row],[Alocação]]*IF(OR(tbEquipe[[#This Row],[Mês]]>Configuração!$D$7,tbEquipe[[#This Row],[Mês]]=Configuração!$D$7),(1+Configuração!$D$4),1))*IF(OR(tbEquipe[[#This Row],[Mês]]>Configuração!$D$8,tbEquipe[[#This Row],[Mês]]=Configuração!$D$8),(1+Configuração!$D$4),1)+(IF(tbEquipe[[#This Row],[Mês]]=(Configuração!$D$7-1),Configuração!$D$11*tbEquipe[[#This Row],[Alocação]],0))+(IF(tbEquipe[[#This Row],[Mês]]=(Configuração!$D$9),Configuração!$D$12*tbEquipe[[#This Row],[Alocação]],0)),0) -> 2135.6503
A84: A Definir - DESIGNER UX/UI JR | B84: =IFERROR(VLOOKUP(tbEquipe[[#This Row],[Nome]],tbFOPAG[[Nome]:[Cargo]],2,0),"<Selecionar Nome>") -> DESIGNER UX/UI JR | C84: Direto | D84: 11 | E84: =176*tbEquipe[[#This Row],[Alocação]] -> 38.72 | F84: 0.22 | G84: =IFERROR((VLOOKUP(tbEquipe[[#This Row],[Nome]],tbFOPAG[[Nome]:[Custo Total]],3,0)*tbEquipe[[#This Row],[Alocação]]*IF(OR(tbEquipe[[#This Row],[Mês]]>Configuração!$D$7,tbEquipe[[#This Row],[Mês]]=Configuração!$D$7),(1+Configuração!$D$4),1))*IF(OR(tbEquipe[[#This Row],[Mês]]>Configuração!$D$8,tbEquipe[[#This Row],[Mês]]=Configuração!$D$8),(1+Configuração!$D$4),1)+(IF(tbEquipe[[#This Row],[Mês]]=(Configuração!$D$7-1),Configuração!$D$11*tbEquipe[[#This Row],[Alocação]],0))+(IF(tbEquipe[[#This Row],[Mês]]=(Configuração!$D$9),Configuração!$D$12*tbEquipe[[#This Row],[Alocação]],0)),0) -> 2135.6503
A85: A Definir - DESIGNER UX/UI JR | B85: =IFERROR(VLOOKUP(tbEquipe[[#This Row],[Nome]],tbFOPAG[[Nome]:[Cargo]],2,0),"<Selecionar Nome>") -> DESIGNER UX/UI JR | C85: Direto | D85: 12 | E85: =176*tbEquipe[[#This Row],[Alocação]] -> 38.72 | F85: 0.22 | G85: =IFERROR((VLOOKUP(tbEquipe[[#This Row],[Nome]],tbFOPAG[[Nome]:[Custo Total]],3,0)*tbEquipe[[#This Row],[Alocação]]*IF(OR(tbEquipe[[#This Row],[Mês]]>Configuração!$D$7,tbEquipe[[#This Row],[Mês]]=Configuração!$D$7),(1+Configuração!$D$4),1))*IF(OR(tbEquipe[[#This Row],[Mês]]>Configuração!$D$8,tbEquipe[[#This Row],[Mês]]=Configuração!$D$8),(1+Configuração!$D$4),1)+(IF(tbEquipe[[#This Row],[Mês]]=(Configuração!$D$7-1),Configuração!$D$11*tbEquipe[[#This Row],[Alocação]],0))+(IF(tbEquipe[[#This Row],[Mês]]=(Configuração!$D$9),Configuração!$D$12*tbEquipe[[#This Row],[Alocação]],0)),0) -> 2135.6503
A86: A Definir - DESIGNER UX/UI JR | B86: =IFERROR(VLOOKUP(tbEquipe[[#This Row],[Nome]],tbFOPAG[[Nome]:[Cargo]],2,0),"<Selecionar Nome>") -> DESIGNER UX/UI JR | C86: Direto | D86: 13 | E86: =176*tbEquipe[[#This Row],[Alocação]] -> 0 | G86: =IFERROR((VLOOKUP(tbEquipe[[#This Row],[Nome]],tbFOPAG[[Nome]:[Custo Total]],3,0)*tbEquipe[[#This Row],[Alocação]]*IF(OR(tbEquipe[[#This Row],[Mês]]>Configuração!$D$7,tbEquipe[[#This Row],[Mês]]=Configuração!$D$7),(1+Configuração!$D$4),1))*IF(OR(tbEquipe[[#This Row],[Mês]]>Configuração!$D$8,tbEquipe[[#This Row],[Mês]]=Configuração!$D$8),(1+Configuração!$D$4),1)+(IF(tbEquipe[[#This Row],[Mês]]=(Configuração!$D$7-1),Configuração!$D$11*tbEquipe[[#This Row],[Alocação]],0))+(IF(tbEquipe[[#This Row],[Mês]]=(Configuração!$D$9),Configuração!$D$12*tbEquipe[[#This Row],[Alocação]],0)),0) -> 0
A87: A Definir - DESIGNER UX/UI JR | B87: =IFERROR(VLOOKUP(tbEquipe[[#This Row],[Nome]],tbFOPAG[[Nome]:[Cargo]],2,0),"<Selecionar Nome>") -> DESIGNER UX/UI JR | C87: Direto | D87: 14 | E87: =176*tbEquipe[[#This Row],[Alocação]] -> 0 | G87: =IFERROR((VLOOKUP(tbEquipe[[#This Row],[Nome]],tbFOPAG[[Nome]:[Custo Total]],3,0)*tbEquipe[[#This Row],[Alocação]]*IF(OR(tbEquipe[[#This Row],[Mês]]>Configuração!$D$7,tbEquipe[[#This Row],[Mês]]=Configuração!$D$7),(1+Configuração!$D$4),1))*IF(OR(tbEquipe[[#This Row],[Mês]]>Configuração!$D$8,tbEquipe[[#This Row],[Mês]]=Configuração!$D$8),(1+Configuração!$D$4),1)+(IF(tbEquipe[[#This Row],[Mês]]=(Configuração!$D$7-1),Configuração!$D$11*tbEquipe[[#This Row],[Alocação]],0))+(IF(tbEquipe[[#This Row],[Mês]]=(Configuração!$D$9),Configuração!$D$12*tbEquipe[[#This Row],[Alocação]],0)),0) -> 0
A88: A Definir - DESIGNER UX/UI JR | B88: =IFERROR(VLOOKUP(tbEquipe[[#This Row],[Nome]],tbFOPAG[[Nome]:[Cargo]],2,0),"<Selecionar Nome>") -> DESIGNER UX/UI JR | C88: Direto | D88: 15 | E88: =176*tbEquipe[[#This Row],[Alocação]] -> 0 | G88: =IFERROR((VLOOKUP(tbEquipe[[#This Row],[Nome]],tbFOPAG[[Nome]:[Custo Total]],3,0)*tbEquipe[[#This Row],[Alocação]]*IF(OR(tbEquipe[[#This Row],[Mês]]>Configuração!$D$7,tbEquipe[[#This Row],[Mês]]=Configuração!$D$7),(1+Configuração!$D$4),1))*IF(OR(tbEquipe[[#This Row],[Mês]]>Configuração!$D$8,tbEquipe[[#This Row],[Mês]]=Configuração!$D$8),(1+Configuração!$D$4),1)+(IF(tbEquipe[[#This Row],[Mês]]=(Configuração!$D$7-1),Configuração!$D$11*tbEquipe[[#This Row],[Alocação]],0))+(IF(tbEquipe[[#This Row],[Mês]]=(Configuração!$D$9),Configuração!$D$12*tbEquipe[[#This Row],[Alocação]],0)),0) -> 0 | I88: =SUM(G74:G88) -> 25583.917
A89: A Definir - DBA JR | B89: =IFERROR(VLOOKUP(tbEquipe[[#This Row],[Nome]],tbFOPAG[[Nome]:[Cargo]],2,0),"<Selecionar Nome>") -> DBA JR | C89: Direto | D89: 1 | E89: =176*tbEquipe[[#This Row],[Alocação]] -> 23.466667 | F89: 0.13333333 | G89: =IFERROR((VLOOKUP(tbEquipe[[#This Row],[Nome]],tbFOPAG[[Nome]:[Custo Total]],3,0)*tbEquipe[[#This Row],[Alocação]]*IF(OR(tbEquipe[[#This Row],[Mês]]>Configuração!$D$7,tbEquipe[[#This Row],[Mês]]=Configuração!$D$7),(1+Configuração!$D$4),1))*IF(OR(tbEquipe[[#This Row],[Mês]]>Configuração!$D$8,tbEquipe[[#This Row],[Mês]]=Configuração!$D$8),(1+Configuração!$D$4),1)+(IF(tbEquipe[[#This Row],[Mês]]=(Configuração!$D$7-1),Configuração!$D$11*tbEquipe[[#This Row],[Alocação]],0))+(IF(tbEquipe[[#This Row],[Mês]]=(Configuração!$D$9),Configuração!$D$12*tbEquipe[[#This Row],[Alocação]],0)),0) -> 1104.7613
A90: A Definir - DBA JR | B90: =IFERROR(VLOOKUP(tbEquipe[[#This Row],[Nome]],tbFOPAG[[Nome]:[Cargo]],2,0),"<Selecionar Nome>") -> DBA JR | C90: Direto | D90: 2 | E90: =176*tbEquipe[[#This Row],[Alocação]] -> 23.466667 | F90: 0.13333333 | G90: =IFERROR((VLOOKUP(tbEquipe[[#This Row],[Nome]],tbFOPAG[[Nome]:[Custo Total]],3,0)*tbEquipe[[#This Row],[Alocação]]*IF(OR(tbEquipe[[#This Row],[Mês]]>Configuração!$D$7,tbEquipe[[#This Row],[Mês]]=Configuração!$D$7),(1+Configuração!$D$4),1))*IF(OR(tbEquipe[[#This Row],[Mês]]>Configuração!$D$8,tbEquipe[[#This Row],[Mês]]=Configuração!$D$8),(1+Configuração!$D$4),1)+(IF(tbEquipe[[#This Row],[Mês]]=(Configuração!$D$7-1),Configuração!$D$11*tbEquipe[[#This Row],[Alocação]],0))+(IF(tbEquipe[[#This Row],[Mês]]=(Configuração!$D$9),Configuração!$D$12*tbEquipe[[#This Row],[Alocação]],0)),0) -> 1121.5803
A91: A Definir - DBA JR | B91: =IFERROR(VLOOKUP(tbEquipe[[#This Row],[Nome]],tbFOPAG[[Nome]:[Cargo]],2,0),"<Selecionar Nome>") -> DBA JR | C91: Direto | D91: 3 | E91: =176*tbEquipe[[#This Row],[Alocação]] -> 23.466667 | F91: 0.13333333 | G91: =IFERROR((VLOOKUP(tbEquipe[[#This Row],[Nome]],tbFOPAG[[Nome]:[Custo Total]],3,0)*tbEquipe[[#This Row],[Alocação]]*IF(OR(tbEquipe[[#This Row],[Mês]]>Configuração!$D$7,tbEquipe[[#This Row],[Mês]]=Configuração!$D$7),(1+Configuração!$D$4),1))*IF(OR(tbEquipe[[#This Row],[Mês]]>Configuração!$D$8,tbEquipe[[#This Row],[Mês]]=Configuração!$D$8),(1+Configuração!$D$4),1)+(IF(tbEquipe[[#This Row],[Mês]]=(Configuração!$D$7-1),Configuração!$D$11*tbEquipe[[#This Row],[Alocação]],0))+(IF(tbEquipe[[#This Row],[Mês]]=(Configuração!$D$9),Configuração!$D$12*tbEquipe[[#This Row],[Alocação]],0)),0) -> 1121.5803
A92: A Definir - DBA JR | B92: =IFERROR(VLOOKUP(tbEquipe[[#This Row],[Nome]],tbFOPAG[[Nome]:[Cargo]],2,0),"<Selecionar Nome>") -> DBA JR | C92: Direto | D92: 4 | E92: =176*tbEquipe[[#This Row],[Alocação]] -> 23.466667 | F92: 0.13333333 | G92: =IFERROR((VLOOKUP(tbEquipe[[#This Row],[Nome]],tbFOPAG[[Nome]:[Custo Total]],3,0)*tbEquipe[[#This Row],[Alocação]]*IF(OR(tbEquipe[[#This Row],[Mês]]>Configuração!$D$7,tbEquipe[[#This Row],[Mês]]=Configuração!$D$7),(1+Configuração!$D$4),1))*IF(OR(tbEquipe[[#This Row],[Mês]]>Configuração!$D$8,tbEquipe[[#This Row],[Mês]]=Configuração!$D$8),(1+Configuração!$D$4),1)+(IF(tbEquipe[[#This Row],[Mês]]=(Configuração!$D$7-1),Configuração!$D$11*tbEquipe[[#This Row],[Alocação]],0))+(IF(tbEquipe[[#This Row],[Mês]]=(Configuração!$D$9),Configuração!$D$12*tbEquipe[[#This Row],[Alocação]],0)),0) -> 1121.5803
A93: A Definir - DBA JR | B93: =IFERROR(VLOOKUP(tbEquipe[[#This Row],[Nome]],tbFOPAG[[Nome]:[Cargo]],2,0),"<Selecionar Nome>") -> DBA JR | C93: Direto | D93: 5 | E93: =176*tbEquipe[[#This Row],[Alocação]] -> 23.466667 | F93: 0.13333333 | G93: =IFERROR((VLOOKUP(tbEquipe[[#This Row],[Nome]],tbFOPAG[[Nome]:[Custo Total]],3,0)*tbEquipe[[#This Row],[Alocação]]*IF(OR(tbEquipe[[#This Row],[Mês]]>Configuração!$D$7,tbEquipe[[#This Row],[Mês]]=Configuração!$D$7),(1+Configuração!$D$4),1))*IF(OR(tbEquipe[[#This Row],[Mês]]>Configuração!$D$8,tbEquipe[[#This Row],[Mês]]=Configuração!$D$8),(1+Configuração!$D$4),1)+(IF(tbEquipe[[#This Row],[Mês]]=(Configuração!$D$7-1),Configuração!$D$11*tbEquipe[[#This Row],[Alocação]],0))+(IF(tbEquipe[[#This Row],[Mês]]=(Configuração!$D$9),Configuração!$D$12*tbEquipe[[#This Row],[Alocação]],0)),0) -> 1121.5803
A94: A Definir - DBA JR | B94: =IFERROR(VLOOKUP(tbEquipe[[#This Row],[Nome]],tbFOPAG[[Nome]:[Cargo]],2,0),"<Selecionar Nome>") -> DBA JR | C94: Direto | D94: 6 | E94: =176*tbEquipe[[#This Row],[Alocação]] -> 23.466667 | F94: 0.13333333 | G94: =IFERROR((VLOOKUP(tbEquipe[[#This Row],[Nome]],tbFOPAG[[Nome]:[Custo Total]],3,0)*tbEquipe[[#This Row],[Alocação]]*IF(OR(tbEquipe[[#This Row],[Mês]]>Configuração!$D$7,tbEquipe[[#This Row],[Mês]]=Configuração!$D$7),(1+Configuração!$D$4),1))*IF(OR(tbEquipe[[#This Row],[Mês]]>Configuração!$D$8,tbEquipe[[#This Row],[Mês]]=Configuração!$D$8),(1+Configuração!$D$4),1)+(IF(tbEquipe[[#This Row],[Mês]]=(Configuração!$D$7-1),Configuração!$D$11*tbEquipe[[#This Row],[Alocação]],0))+(IF(tbEquipe[[#This Row],[Mês]]=(Configuração!$D$9),Configuração!$D$12*tbEquipe[[#This Row],[Alocação]],0)),0) -> 1121.5803
A95: A Definir - DBA JR | B95: =IFERROR(VLOOKUP(tbEquipe[[#This Row],[Nome]],tbFOPAG[[Nome]:[Cargo]],2,0),"<Selecionar Nome>") -> DBA JR | C95: Direto | D95: 7 | E95: =176*tbEquipe[[#This Row],[Alocação]] -> 23.466667 | F95: 0.13333333 | G95: =IFERROR((VLOOKUP(tbEquipe[[#This Row],[Nome]],tbFOPAG[[Nome]:[Custo Total]],3,0)*tbEquipe[[#This Row],[Alocação]]*IF(OR(tbEquipe[[#This Row],[Mês]]>Configuração!$D$7,tbEquipe[[#This Row],[Mês]]=Configuração!$D$7),(1+Configuração!$D$4),1))*IF(OR(tbEquipe[[#This Row],[Mês]]>Configuração!$D$8,tbEquipe[[#This Row],[Mês]]=Configuração!$D$8),(1+Configuração!$D$4),1)+(IF(tbEquipe[[#This Row],[Mês]]=(Configuração!$D$7-1),Configuração!$D$11*tbEquipe[[#This Row],[Alocação]],0))+(IF(tbEquipe[[#This Row],[Mês]]=(Configuração!$D$9),Configuração!$D$12*tbEquipe[[#This Row],[Alocação]],0)),0) -> 1121.5803
A96: A Definir - DBA JR | B96: =IFERROR(VLOOKUP(tbEquipe[[#This Row],[Nome]],tbFOPAG[[Nome]:[Cargo]],2,0),"<Selecionar Nome>") -> DBA JR | C96: Direto | D96: 8 | E96: =176*tbEquipe[[#This Row],[Alocação]] -> 23.466667 | F96: 0.13333333 | G96: =IFERROR((VLOOKUP(tbEquipe[[#This Row],[Nome]],tbFOPAG[[Nome]:[Custo Total]],3,0)*tbEquipe[[#This Row],[Alocação]]*IF(OR(tbEquipe[[#This Row],[Mês]]>Configuração!$D$7,tbEquipe[[#This Row],[Mês]]=Configuração!$D$7),(1+Configuração!$D$4),1))*IF(OR(tbEquipe[[#This Row],[Mês]]>Configuração!$D$8,tbEquipe[[#This Row],[Mês]]=Configuração!$D$8),(1+Configuração!$D$4),1)+(IF(tbEquipe[[#This Row],[Mês]]=(Configuração!$D$7-1),Configuração!$D$11*tbEquipe[[#This Row],[Alocação]],0))+(IF(tbEquipe[[#This Row],[Mês]]=(Configuração!$D$9),Configuração!$D$12*tbEquipe[[#This Row],[Alocação]],0)),0) -> 1121.5803 | I96: =SUM(G89:G96) -> 8955.8238 | J96: =SUM(F89:F96) -> 1.0666667 | K96: =J96/12 -> 0.088888889 | M96: 1.6 | N96: 0.13333333
A97: A Definir - DBA JR | B97: =IFERROR(VLOOKUP(tbEquipe[[#This Row],[Nome]],tbFOPAG[[Nome]:[Cargo]],2,0),"<Selecionar Nome>") -> DBA JR | C97: Direto | D97: 9 | E97: =176*tbEquipe[[#This Row],[Alocação]] -> 23.466667 | F97: 0.13333333 | G97: =IFERROR((VLOOKUP(tbEquipe[[#This Row],[Nome]],tbFOPAG[[Nome]:[Custo Total]],3,0)*tbEquipe[[#This Row],[Alocação]]*IF(OR(tbEquipe[[#This Row],[Mês]]>Configuração!$D$7,tbEquipe[[#This Row],[Mês]]=Configuração!$D$7),(1+Configuração!$D$4),1))*IF(OR(tbEquipe[[#This Row],[Mês]]>Configuração!$D$8,tbEquipe[[#This Row],[Mês]]=Configuração!$D$8),(1+Configuração!$D$4),1)+(IF(tbEquipe[[#This Row],[Mês]]=(Configuração!$D$7-1),Configuração!$D$11*tbEquipe[[#This Row],[Alocação]],0))+(IF(tbEquipe[[#This Row],[Mês]]=(Configuração!$D$9),Configuração!$D$12*tbEquipe[[#This Row],[Alocação]],0)),0) -> 1121.5803
A98: A Definir - DBA JR | B98: =IFERROR(VLOOKUP(tbEquipe[[#This Row],[Nome]],tbFOPAG[[Nome]:[Cargo]],2,0),"<Selecionar Nome>") -> DBA JR | C98: Direto | D98: 10 | E98: =176*tbEquipe[[#This Row],[Alocação]] -> 23.466667 | F98: 0.13333333 | G98: =IFERROR((VLOOKUP(tbEquipe[[#This Row],[Nome]],tbFOPAG[[Nome]:[Custo Total]],3,0)*tbEquipe[[#This Row],[Alocação]]*IF(OR(tbEquipe[[#This Row],[Mês]]>Configuração!$D$7,tbEquipe[[#This Row],[Mês]]=Configuração!$D$7),(1+Configuração!$D$4),1))*IF(OR(tbEquipe[[#This Row],[Mês]]>Configuração!$D$8,tbEquipe[[#This Row],[Mês]]=Configuração!$D$8),(1+Configuração!$D$4),1)+(IF(tbEquipe[[#This Row],[Mês]]=(Configuração!$D$7-1),Configuração!$D$11*tbEquipe[[#This Row],[Alocação]],0))+(IF(tbEquipe[[#This Row],[Mês]]=(Configuração!$D$9),Configuração!$D$12*tbEquipe[[#This Row],[Alocação]],0)),0) -> 1121.5803
A99: A Definir - DBA JR | B99: =IFERROR(VLOOKUP(tbEquipe[[#This Row],[Nome]],tbFOPAG[[Nome]:[Cargo]],2,0),"<Selecionar Nome>") -> DBA JR | C99: Direto | D99: 11 | E99: =176*tbEquipe[[#This Row],[Alocação]] -> 23.466667 | F99: 0.13333333 | G99: =IFERROR((VLOOKUP(tbEquipe[[#This Row],[Nome]],tbFOPAG[[Nome]:[Custo Total]],3,0)*tbEquipe[[#This Row],[Alocação]]*IF(OR(tbEquipe[[#This Row],[Mês]]>Configuração!$D$7,tbEquipe[[#This Row],[Mês]]=Configuração!$D$7),(1+Configuração!$D$4),1))*IF(OR(tbEquipe[[#This Row],[Mês]]>Configuração!$D$8,tbEquipe[[#This Row],[Mês]]=Configuração!$D$8),(1+Configuração!$D$4),1)+(IF(tbEquipe[[#This Row],[Mês]]=(Configuração!$D$7-1),Configuração!$D$11*tbEquipe[[#This Row],[Alocação]],0))+(IF(tbEquipe[[#This Row],[Mês]]=(Configuração!$D$9),Configuração!$D$12*tbEquipe[[#This Row],[Alocação]],0)),0) -> 1121.5803
A100: A Definir - DBA JR | B100: =IFERROR(VLOOKUP(tbEquipe[[#This Row],[Nome]],tbFOPAG[[Nome]:[Cargo]],2,0),"<Selecionar Nome>") -> DBA JR | C100: Direto | D100: 12 | E100: =176*tbEquipe[[#This Row],[Alocação]] -> 23.466667 | F100: 0.13333333 | G100: =IFERROR((VLOOKUP(tbEquipe[[#This Row],[Nome]],tbFOPAG[[Nome]:[Custo Total]],3,0)*tbEquipe[[#This Row],[Alocação]]*IF(OR(tbEquipe[[#This Row],[Mês]]>Configuração!$D$7,tbEquipe[[#This Row],[Mês]]=Configuração!$D$7),(1+Configuração!$D$4),1))*IF(OR(tbEquipe[[#This Row],[Mês]]>Configuração!$D$8,tbEquipe[[#This Row],[Mês]]=Configuração!$D$8),(1+Configuração!$D$4),1)+(IF(tbEquipe[[#This Row],[Mês]]=(Configuração!$D$7-1),Configuração!$D$11*tbEquipe[[#This Row],[Alocação]],0))+(IF(tbEquipe[[#This Row],[Mês]]=(Configuração!$D$9),Configuração!$D$12*tbEquipe[[#This Row],[Alocação]],0)),0) -> 1121.5803
...

Sheet Rubrica
A1: Rubrica | B1: Descrição | C1: Justificativa | D1: Mês | E1: Quantidade | F1: Custo Unitário | G1: Frete | H1: Custo Total | I1: Observações | J1: Coluna1
A2: Máquinas e Equipamentos | D2: 1 | E2: 1 | F2: =SERVICO!N10-F8+tbRubrica[[#This Row],[Coluna1]] -> 340084.8 | H2: =E2*F2 -> 340084.8 | J2: 250000
A3: Material de Consumo | D3: 2 | E3: 1 | F3: =SERVICO!N15 -> 720254.41 | H3: =E3*F3 -> 720254.41
A4: Serviço Técnico de Terceiros | D4: 3 | E4: 1 | F4: =SERVICO!N14-250000 -> 390226.14 | H4: =E4*F4 -> 390226.14 | J4: -250000
A5: Outros correlatos | D5: 1 | E5: 1 | F5: 100000 | H5: =E5*F5 -> 100000 | I5: Valor pendente de projetos anteriores
A6: Serviço Técnico de Terceiros | H6: =E6*F6 -> 0
A7: Outros correlatos | B7: SYSMAQ | D7: 1 | E7: 1 | H7: =E7*F7 -> 0 | I7: Valor reduzido na rubrica de Serviço de terceiros
A8: Outros correlatos | B8: SYSMAQ | D8: 2 | E8: 1 | F8: 150000 | H8: =E8*F8 -> 150000 | I8: Valor reduzido na rubrica de Serviço de terceiros
H11: =E11*F11 -> 0
H12: =E12*F12 -> 0
H13: =E13*F13 -> 0
H14: =E14*F14 -> 0
H15: =E15*F15 -> 0
H16: =E16*F16 -> 0
H17: =E17*F17 -> 0
H18: =E18*F18 -> 0
H19: =E19*F19 -> 0
H20: =E20*F20 -> 0
H21: =E21*F21 -> 0
H22: =E22*F22 -> 0
... H658: =E658*F658 -> 0
H659: =SUBTOTAL(109,tbRubrica[Custo Total]) -> 1700565.4

Sheet RHI
A1: Nome | B1: Cargo | C1: Custo | D1: 1 | E1: %Aloc1 | F1: 2 | G1: %Aloc2 | H1: 3 | I1: %Aloc3 | J1: 4 | K1: %Aloc4 | L1: 5 | M1: %Aloc5 | N1: 6 | O1: %Aloc6 | P1: 7 | Q1: %Aloc7 | R1: 8 | S1: %Aloc8 | T1: 9 | U1: %Aloc9 | V1: 10 | W1: %Aloc10 | X1: 11 | Y1: %Aloc11 | Z1: 12 | AA1: %Aloc12 | AB1: 13 | AC1: %Aloc13 | AD1: 14 | AE1: %Aloc14 | AF1: 15 | AG1: %Aloc15 | AH1: 16 | AI1: %Aloc16 | AJ1: 17 | AK1: %Aloc17 | AL1: 18 | AM1: %Aloc18 | AN1: 19 | AO1: %Aloc19 | AP1: 20 | AQ1: %Aloc20 | AR1: 21 | AS1: %Aloc21 | AT1: 22 | AU1: %Aloc22 | AV1: 23 | AW1: %Aloc23
A2: LIRIAN CORREA DA SILVA | B2: =_xlfn.XLOOKUP($A2,DBFolha!$A:$A,DBFolha!$B:$B) -> COORDENADOR DE REGULAMENTAÇÃO DE P&D | C2: =_xlfn.XLOOKUP($A2,DBFolha!$A:$A,DBFolha!$C:$C) -> 16879 | D2: =(tbRHI[[#This Row],[Custo]]/SUM(tbRHI[Custo]))*SUMIFS(tbEquipe[Custo],tbEquipe[Mês],D$1)*Configuração!$D$10 -> 1748.405 | E2: =tbRHI[[#This Row],[1]]/tbRHI[[#This Row],[Custo]] -> 0.10358463 | F2: =(tbRHI[[#This Row],[Custo]]/SUM(tbRHI[Custo]))*SUMIFS(tbEquipe[Custo],tbEquipe[Mês],F$1)*Configuração!$D$10 -> 1809.5672 | G2: =tbRHI[[#This Row],[2]]/tbRHI[[#This Row],[Custo]] -> 0.1072082 | H2: =(tbRHI[[#This Row],[Custo]]/SUM(tbRHI[Custo]))*SUMIFS(tbEquipe[Custo],tbEquipe[Mês],H$1)*Configuração!$D$10 -> 1809.5672 | I2: =tbRHI[[#This Row],[3]]/tbRHI[[#This Row],[Custo]] -> 0.1072082 | J2: =(tbRHI[[#This Row],[Custo]]/SUM(tbRHI[Custo]))*SUMIFS(tbEquipe[Custo],tbEquipe[Mês],J$1)*Configuração!$D$10 -> 1809.5672 | K2: =tbRHI[[#This Row],[4]]/tbRHI[[#This Row],[Custo]] -> 0.1072082 | L2: =(tbRHI[[#This Row],[Custo]]/SUM(tbRHI[Custo]))*SUMIFS(tbEquipe[Custo],tbEquipe[Mês],L$1)*Configuração!$D$10 -> 1809.5672 | M2: =tbRHI[[#This Row],[5]]/tbRHI[[#This Row],[Custo]] -> 0.1072082 | N2: =(tbRHI[[#This Row],[Custo]]/SUM(tbRHI[Custo]))*SUMIFS(tbEquipe[Custo],tbEquipe[Mês],N$1)*Configuração!$D$10 -> 1809.5672 | O2: =tbRHI[[#This Row],[6]]/tbRHI[[#This Row],[Custo]] -> 0.1072082 | P2: =(tbRHI[[#This Row],[Custo]]/SUM(tbRHI[Custo]))*SUMIFS(tbEquipe[Custo],tbEquipe[Mês],P$1)*Configuração!$D$10 -> 1809.5672 | Q2: =tbRHI[[#This Row],[7]]/tbRHI[[#This Row],[Custo]] -> 0.1072082 | R2: =(tbRHI[[#This Row],[Custo]]/SUM(tbRHI[Custo]))*SUMIFS(tbEquipe[Custo],tbEquipe[Mês],R$1)*Configuração!$D$10 -> 1809.5672 | S2: =tbRHI[[#This Row],[8]]/tbRHI[[#This Row],[Custo]] -> 0.1072082 | T2: =(tbRHI[[#This Row],[Custo]]/SUM(tbRHI[Custo]))*SUMIFS(tbEquipe[Custo],tbEquipe[Mês],T$1)*Configuração!$D$10 -> 1809.5672 | U2: =tbRHI[[#This Row],[9]]/tbRHI[[#This Row],[Custo]] -> 0.1072082 | V2: =(tbRHI[[#This Row],[Custo]]/SUM(tbRHI[Custo]))*SUMIFS(tbEquipe[Custo],tbEquipe[Mês],V$1)*Configuração!$D$10 -> 1809.5672 | W2: =tbRHI[[#This Row],[10]]/tbRHI[[#This Row],[Custo]] -> 0.1072082 | X2: =(tbRHI[[#This Row],[Custo]]/SUM(tbRHI[Custo]))*SUMIFS(tbEquipe[Custo],tbEquipe[Mês],X$1)*Configuração!$D$10 -> 1809.5672 | Y2: =tbRHI[[#This Row],[11]]/tbRHI[[#This Row],[Custo]] -> 0.1072082 | Z2: =(tbRHI[[#This Row],[Custo]]/SUM(tbRHI[Custo]))*SUMIFS(tbEquipe[Custo],tbEquipe[Mês],Z$1)*Configuração!$D$10 -> 1809.5672 | AA2: =tbRHI[[#This Row],[12]]/tbRHI[[#This Row],[Custo]] -> 0.1072082 | AB2: =(tbRHI[[#This Row],[Custo]]/SUM(tbRHI[Custo]))*SUMIFS(tbEquipe[Custo],tbEquipe[Mês],AB$1)*Configuração!$D$10 -> 141.38139 | AC2: =tbRHI[[#This Row],[13]]/tbRHI[[#This Row],[Custo]] -> 0.0083761709 | AD2: =(tbRHI[[#This Row],[Custo]]/SUM(tbRHI[Custo]))*SUMIFS(tbEquipe[Custo],tbEquipe[Mês],AD$1)*Configuração!$D$10 -> 149.86427 | AE2: =tbRHI[[#This Row],[14]]/tbRHI[[#This Row],[Custo]] -> 0.0088787412 | AF2: =(tbRHI[[#This Row],[Custo]]/SUM(tbRHI[Custo]))*SUMIFS(tbEquipe[Custo],tbEquipe[Mês],AF$1)*Configuração!$D$10 -> 149.86427 | AG2: =tbRHI[[#This Row],[15]]/tbRHI[[#This Row],[Custo]] -> 0.0088787412 | AH2: =(tbRHI[[#This Row],[Custo]]/SUM(tbRHI[Custo]))*SUMIFS(tbEquipe[Custo],tbEquipe[Mês],AH$1)*Configuração!$D$10 -> 0 | AI2: =tbRHI[[#This Row],[16]]/tbRHI[[#This Row],[Custo]] -> 0 | AJ2: =(tbRHI[[#This Row],[Custo]]/SUM(tbRHI[Custo]))*SUMIFS(tbEquipe[Custo],tbEquipe[Mês],AJ$1)*Configuração!$D$10 -> 0 | AK2: =tbRHI[[#This Row],[17]]/tbRHI[[#This Row],[Custo]] -> 0 | AL2: =(tbRHI[[#This Row],[Custo]]/SUM(tbRHI[Custo]))*SUMIFS(tbEquipe[Custo],tbEquipe[Mês],AL$1)*Configuração!$D$10 -> 0 | AM2: =tbRHI[[#This Row],[18]]/tbRHI[[#This Row],[Custo]] -> 0 | AN2: =(tbRHI[[#This Row],[Custo]]/SUM(tbRHI[Custo]))*SUMIFS(tbEquipe[Custo],tbEquipe[Mês],AN$1)*Configuração!$D$10 -> 0 | AO2: =tbRHI[[#This Row],[19]]/tbRHI[[#This Row],[Custo]] -> 0 | AP2: =(tbRHI[[#This Row],[Custo]]/SUM(tbRHI[Custo]))*SUMIFS(tbEquipe[Custo],tbEquipe[Mês],AP$1)*Configuração!$D$10 -> 0 | AQ2: =tbRHI[[#This Row],[20]]/tbRHI[[#This Row],[Custo]] -> 0 | AR2: =(tbRHI[[#This Row],[Custo]]/SUM(tbRHI[Custo]))*SUMIFS(tbEquipe[Custo],tbEquipe[Mês],AR$1)*Configuração!$D$10 -> 0 | AS2: =tbRHI[[#This Row],[21]]/tbRHI[[#This Row],[Custo]] -> 0 | AT2: =(tbRHI[[#This Row],[Custo]]/SUM(tbRHI[Custo]))*SUMIFS(tbEquipe[Custo],tbEquipe[Mês],AT$1)*Configuração!$D$10 -> 0 | AU2: =tbRHI[[#This Row],[22]]/tbRHI[[#This Row],[Custo]] -> 0 | AV2: =(tbRHI[[#This Row],[Custo]]/SUM(tbRHI[Custo]))*SUMIFS(tbEquipe[Custo],tbEquipe[Mês],AV$1)*Configuração!$D$10 -> 0 | AW2: =tbRHI[[#This Row],[23]]/tbRHI[[#This Row],[Custo]] -> 0
A3: ALESSANDRA DUARTE SILVA | B3: =_xlfn.XLOOKUP($A3,DBFolha!$A:$A,DBFolha!$B:$B) -> DIRETOR PD&I E NEGÓCIOS | C3: =_xlfn.XLOOKUP($A3,DBFolha!$A:$A,DBFolha!$C:$C) -> 35000 | D3: =(tbRHI[[#This Row],[Custo]]/SUM(tbRHI[Custo]))*SUMIFS(tbEquipe[Custo],tbEquipe[Mês],D$1)*Configuração!$D$10 -> 3625.4622 | E3: =tbRHI[[#This Row],[1]]/tbRHI[[#This Row],[Custo]] -> 0.10358463 | F3: =(tbRHI[[#This Row],[Custo]]/SUM(tbRHI[Custo]))*SUMIFS(tbEquipe[Custo],tbEquipe[Mês],F$1)*Configuração!$D$10 -> 3752.2869 | G3: =tbRHI[[#This Row],[2]]/tbRHI[[#This Row],[Custo]] -> 0.1072082 | H3: =(tbRHI[[#This Row],[Custo]]/SUM(tbRHI[Custo]))*SUMIFS(tbEquipe[Custo],tbEquipe[Mês],H$1)*Configuração!$D$10 -> 3752.2869 | I3: =tbRHI[[#This Row],[3]]/tbRHI[[#This Row],[Custo]] -> 0.1072082 | J3: =(tbRHI[[#This Row],[Custo]]/SUM(tbRHI[Custo]))*SUMIFS(tbEquipe[Custo],tbEquipe[Mês],J$1)*Configuração!$D$10 -> 3752.2869 | K3: =tbRHI[[#This Row],[4]]/tbRHI[[#This Row],[Custo]] -> 0.1072082 | L3: =(tbRHI[[#This Row],[Custo]]/SUM(tbRHI[Custo]))*SUMIFS(tbEquipe[Custo],tbEquipe[Mês],L$1)*Configuração!$D$10 -> 3752.2869 | M3: =tbRHI[[#This Row],[5]]/tbRHI[[#This Row],[Custo]] -> 0.1072082 | N3: =(tbRHI[[#This Row],[Custo]]/SUM(tbRHI[Custo]))*SUMIFS(tbEquipe[Custo],tbEquipe[Mês],N$1)*Configuração!$D$10 -> 3752.2869 | O3: =tbRHI[[#This Row],[6]]/tbRHI[[#This Row],[Custo]] -> 0.1072082 | P3: =(tbRHI[[#This Row],[Custo]]/SUM(tbRHI[Custo]))*SUMIFS(tbEquipe[Custo],tbEquipe[Mês],P$1)*Configuração!$D$10 -> 3752.2869 | Q3: =tbRHI[[#This Row],[7]]/tbRHI[[#This Row],[Custo]] -> 0.1072082 | R3: =(tbRHI[[#This Row],[Custo]]/SUM(tbRHI[Custo]))*SUMIFS(tbEquipe[Custo],tbEquipe[Mês],R$1)*Configuração!$D$10 -> 3752.2869 | S3: =tbRHI[[#This Row],[8]]/tbRHI[[#This Row],[Custo]] -> 0.1072082 | T3: =(tbRHI[[#This Row],[Custo]]/SUM(tbRHI[Custo]))*SUMIFS(tbEquipe[Custo],tbEquipe[Mês],T$1)*Configuração!$D$10 -> 3752.2869 | U3: =tbRHI[[#This Row],[9]]/tbRHI[[#This Row],[Custo]] -> 0.1072082 | V3: =(tbRHI[[#This Row],[Custo]]/SUM(tbRHI[Custo]))*SUMIFS(tbEquipe[Custo],tbEquipe[Mês],V$1)*Configuração!$D$10 -> 3752.2869 | W3: =tbRHI[[#This Row],[10]]/tbRHI[[#This Row],[Custo]] -> 0.1072082 | X3: =(tbRHI[[#This Row],[Custo]]/SUM(tbRHI[Custo]))*SUMIFS(tbEquipe[Custo],tbEquipe[Mês],X$1)*Configuração!$D$10 -> 3752.2869 | Y3: =tbRHI[[#This Row],[11]]/tbRHI[[#This Row],[Custo]] -> 0.1072082 | Z3: =(tbRHI[[#This Row],[Custo]]/SUM(tbRHI[Custo]))*SUMIFS(tbEquipe[Custo],tbEquipe[Mês],Z$1)*Configuração!$D$10 -> 3752.2869 | AA3: =tbRHI[[#This Row],[12]]/tbRHI[[#This Row],[Custo]] -> 0.1072082 | AB3: =(tbRHI[[#This Row],[Custo]]/SUM(tbRHI[Custo]))*SUMIFS(tbEquipe[Custo],tbEquipe[Mês],AB$1)*Configuração!$D$10 -> 293.16598 | AC3: =tbRHI[[#This Row],[13]]/tbRHI[[#This Row],[Custo]] -> 0.0083761709 | AD3: =(tbRHI[[#This Row],[Custo]]/SUM(tbRHI[Custo]))*SUMIFS(tbEquipe[Custo],tbEquipe[Mês],AD$1)*Configuração!$D$10 -> 310.75594 | AE3: =tbRHI[[#This Row],[14]]/tbRHI[[#This Row],[Custo]] -> 0.0088787412 | AF3: =(tbRHI[[#This Row],[Custo]]/SUM(tbRHI[Custo]))*SUMIFS(tbEquipe[Custo],tbEquipe[Mês],AF$1)*Configuração!$D$10 -> 310.75594 | AG3: =tbRHI[[#This Row],[15]]/tbRHI[[#This Row],[Custo]] -> 0.0088787412 | AH3: =(tbRHI[[#This Row],[Custo]]/SUM(tbRHI[Custo]))*SUMIFS(tbEquipe[Custo],tbEquipe[Mês],AH$1)*Configuração!$D$10 -> 0 | AI3: =tbRHI[[#This Row],[16]]/tbRHI[[#This Row],[Custo]] -> 0 | AJ3: =(tbRHI[[#This Row],[Custo]]/SUM(tbRHI[Custo]))*SUMIFS(tbEquipe[Custo],tbEquipe[Mês],AJ$1)*Configuração!$D$10 -> 0 | AK3: =tbRHI[[#This Row],[17]]/tbRHI[[#This Row],[Custo]] -> 0 | AL3: =(tbRHI[[#This Row],[Custo]]/SUM(tbRHI[Custo]))*SUMIFS(tbEquipe[Custo],tbEquipe[Mês],AL$1)*Configuração!$D$10 -> 0 | AM3: =tbRHI[[#This Row],[18]]/tbRHI[[#This Row],[Custo]] -> 0 | AN3: =(tbRHI[[#This Row],[Custo]]/SUM(tbRHI[Custo]))*SUMIFS(tbEquipe[Custo],tbEquipe[Mês],AN$1)*Configuração!$D$10 -> 0 | AO3: =tbRHI[[#This Row],[19]]/tbRHI[[#This Row],[Custo]] -> 0 | AP3: =(tbRHI[[#This Row],[Custo]]/SUM(tbRHI[Custo]))*SUMIFS(tbEquipe[Custo],tbEquipe[Mês],AP$1)*Configuração!$D$10 -> 0 | AQ3: =tbRHI[[#This Row],[20]]/tbRHI[[#This Row],[Custo]] -> 0 | AR3: =(tbRHI[[#This Row],[Custo]]/SUM(tbRHI[Custo]))*SUMIFS(tbEquipe[Custo],tbEquipe[Mês],AR$1)*Configuração!$D$10 -> 0 | AS3: =tbRHI[[#This Row],[21]]/tbRHI[[#This Row],[Custo]] -> 0 | AT3: =(tbRHI[[#This Row],[Custo]]/SUM(tbRHI[Custo]))*SUMIFS(tbEquipe[Custo],tbEquipe[Mês],AT$1)*Configuração!$D$10 -> 0 | AU3: =tbRHI[[#This Row],[22]]/tbRHI[[#This Row],[Custo]] -> 0 | AV3: =(tbRHI[[#This Row],[Custo]]/SUM(tbRHI[Custo]))*SUMIFS(tbEquipe[Custo],tbEquipe[Mês],AV$1)*Configuração!$D$10 -> 0 | AW3: =tbRHI[[#This Row],[23]]/tbRHI[[#This Row],[Custo]] -> 0
A4: FABIANA SALES BATISTA | B4: =_xlfn.XLOOKUP($A4,DBFolha!$A:$A,DBFolha!$B:$B) -> ANALISTA DE RH SR | C4: =_xlfn.XLOOKUP($A4,DBFolha!$A:$A,DBFolha!$C:$C) -> 13518.783 | D4: =(tbRHI[[#This Row],[Custo]]/SUM(tbRHI[Custo]))*SUMIFS(tbEquipe[Custo],tbEquipe[Mês],D$1)*Configuração!$D$10 -> 1400.3382 | E4: =tbRHI[[#This Row],[1]]/tbRHI[[#This Row],[Custo]] -> 0.10358463 | F4: =(tbRHI[[#This Row],[Custo]]/SUM(tbRHI[Custo]))*SUMIFS(tbEquipe[Custo],tbEquipe[Mês],F$1)*Configuração!$D$10 -> 1449.3243 | G4: =tbRHI[[#This Row],[2]]/tbRHI[[#This Row],[Custo]] -> 0.1072082 | H4: =(tbRHI[[#This Row],[Custo]]/SUM(tbRHI[Custo]))*SUMIFS(tbEquipe[Custo],tbEquipe[Mês],H$1)*Configuração!$D$10 -> 1449.3243 | I4: =tbRHI[[#This Row],[3]]/tbRHI[[#This Row],[Custo]] -> 0.1072082 | J4: =(tbRHI[[#This Row],[Custo]]/SUM(tbRHI[Custo]))*SUMIFS(tbEquipe[Custo],tbEquipe[Mês],J$1)*Configuração!$D$10 -> 1449.3243 | K4: =tbRHI[[#This Row],[4]]/tbRHI[[#This Row],[Custo]] -> 0.1072082 | L4: =(tbRHI[[#This Row],[Custo]]/SUM(tbRHI[Custo]))*SUMIFS(tbEquipe[Custo],tbEquipe[Mês],L$1)*Configuração!$D$10 -> 1449.3243 | M4: =tbRHI[[#This Row],[5]]/tbRHI[[#This Row],[Custo]] -> 0.1072082 | N4: =(tbRHI[[#This Row],[Custo]]/SUM(tbRHI[Custo]))*SUMIFS(tbEquipe[Custo],tbEquipe[Mês],N$1)*Configuração!$D$10 -> 1449.3243 | O4: =tbRHI[[#This Row],[6]]/tbRHI[[#This Row],[Custo]] -> 0.1072082 | P4: =(tbRHI[[#This Row],[Custo]]/SUM(tbRHI[Custo]))*SUMIFS(tbEquipe[Custo],tbEquipe[Mês],P$1)*Configuração!$D$10 -> 1449.3243 | Q4: =tbRHI[[#This Row],[7]]/tbRHI[[#This Row],[Custo]] -> 0.1072082 | R4: =(tbRHI[[#This Row],[Custo]]/SUM(tbRHI[Custo]))*SUMIFS(tbEquipe[Custo],tbEquipe[Mês],R$1)*Configuração!$D$10 -> 1449.3243 | S4: =tbRHI[[#This Row],[8]]/tbRHI[[#This Row],[Custo]] -> 0.1072082 | T4: =(tbRHI[[#This Row],[Custo]]/SUM(tbRHI[Custo]))*SUMIFS(tbEquipe[Custo],tbEquipe[Mês],T$1)*Configuração!$D$10 -> 1449.3243 | U4: =tbRHI[[#This Row],[9]]/tbRHI[[#This Row],[Custo]] -> 0.1072082 | V4: =(tbRHI[[#This Row],[Custo]]/SUM(tbRHI[Custo]))*SUMIFS(tbEquipe[Custo],tbEquipe[Mês],V$1)*Configuração!$D$10 -> 1449.3243 | W4: =tbRHI[[#This Row],[10]]/tbRHI[[#This Row],[Custo]] -> 0.1072082 | X4: =(tbRHI[[#This Row],[Custo]]/SUM(tbRHI[Custo]))*SUMIFS(tbEquipe[Custo],tbEquipe[Mês],X$1)*Configuração!$D$10 -> 1449.3243 | Y4: =tbRHI[[#This Row],[11]]/tbRHI[[#This Row],[Custo]] -> 0.1072082 | Z4: =(tbRHI[[#This Row],[Custo]]/SUM(tbRHI[Custo]))*SUMIFS(tbEquipe[Custo],tbEquipe[Mês],Z$1)*Configuração!$D$10 -> 1449.3243 | AA4: =tbRHI[[#This Row],[12]]/tbRHI[[#This Row],[Custo]] -> 0.1072082 | AB4: =(tbRHI[[#This Row],[Custo]]/SUM(tbRHI[Custo]))*SUMIFS(tbEquipe[Custo],tbEquipe[Mês],AB$1)*Configuração!$D$10 -> 113.23564 | AC4: =tbRHI[[#This Row],[13]]/tbRHI[[#This Row],[Custo]] -> 0.0083761709 | AD4: =(tbRHI[[#This Row],[Custo]]/SUM(tbRHI[Custo]))*SUMIFS(tbEquipe[Custo],tbEquipe[Mês],AD$1)*Configuração!$D$10 -> 120.02977 | AE4: =tbRHI[[#This Row],[14]]/tbRHI[[#This Row],[Custo]] -> 0.0088787412 | AF4: =(tbRHI[[#This Row],[Custo]]/SUM(tbRHI[Custo]))*SUMIFS(tbEquipe[Custo],tbEquipe[Mês],AF$1)*Configuração!$D$10 -> 120.02977 | AG4: =tbRHI[[#This Row],[15]]/tbRHI[[#This Row],[Custo]] -> 0.0088787412 | AH4: =(tbRHI[[#This Row],[Custo]]/SUM(tbRHI[Custo]))*SUMIFS(tbEquipe[Custo],tbEquipe[Mês],AH$1)*Configuração!$D$10 -> 0 | AI4: =tbRHI[[#This Row],[16]]/tbRHI[[#This Row],[Custo]] -> 0 | AJ4: =(tbRHI[[#This Row],[Custo]]/SUM(tbRHI[Custo]))*SUMIFS(tbEquipe[Custo],tbEquipe[Mês],AJ$1)*Configuração!$D$10 -> 0 | AK4: =tbRHI[[#This Row],[17]]/tbRHI[[#This Row],[Custo]] -> 0 | AL4: =(tbRHI[[#This Row],[Custo]]/SUM(tbRHI[Custo]))*SUMIFS(tbEquipe[Custo],tbEquipe[Mês],AL$1)*Configuração!$D$10 -> 0 | AM4: =tbRHI[[#This Row],[18]]/tbRHI[[#This Row],[Custo]] -> 0 | AN4: =(tbRHI[[#This Row],[Custo]]/SUM(tbRHI[Custo]))*SUMIFS(tbEquipe[Custo],tbEquipe[Mês],AN$1)*Configuração!$D$10 -> 0 | AO4: =tbRHI[[#This Row],[19]]/tbRHI[[#This Row],[Custo]] -> 0 | AP4: =(tbRHI[[#This Row],[Custo]]/SUM(tbRHI[Custo]))*SUMIFS(tbEquipe[Custo],tbEquipe[Mês],AP$1)*Configuração!$D$10 -> 0 | AQ4: =tbRHI[[#This Row],[20]]/tbRHI[[#This Row],[Custo]] -> 0 | AR4: =(tbRHI[[#This Row],[Custo]]/SUM(tbRHI[Custo]))*SUMIFS(tbEquipe[Custo],tbEquipe[Mês],AR$1)*Configuração!$D$10 -> 0 | AS4: =tbRHI[[#This Row],[21]]/tbRHI[[#This Row],[Custo]] -> 0 | AT4: =(tbRHI[[#This Row],[Custo]]/SUM(tbRHI[Custo]))*SUMIFS(tbEquipe[Custo],tbEquipe[Mês],AT$1)*Configuração!$D$10 -> 0 | AU4: =tbRHI[[#This Row],[22]]/tbRHI[[#This Row],[Custo]] -> 0 | AV4: =(tbRHI[[#This Row],[Custo]]/SUM(tbRHI[Custo]))*SUMIFS(tbEquipe[Custo],tbEquipe[Mês],AV$1)*Configuração!$D$10 -> 0 | AW4: =tbRHI[[#This Row],[23]]/tbRHI[[#This Row],[Custo]] -> 0
A5: PRISCILA BESSA DE SOUZA | B5: =_xlfn.XLOOKUP($A5,DBFolha!$A:$A,DBFolha!$B:$B) -> COORDENADOR(A) DE COMPRAS PL | C5: =_xlfn.XLOOKUP($A5,DBFolha!$A:$A,DBFolha!$C:$C) -> 19603.798 | D5: =(tbRHI[[#This Row],[Custo]]/SUM(tbRHI[Custo]))*SUMIFS(tbEquipe[Custo],tbEquipe[Mês],D$1)*Configuração!$D$10 -> 2030.6522 | E5: =tbRHI[[#This Row],[1]]/tbRHI[[#This Row],[Custo]] -> 0.10358463 | F5: =(tbRHI[[#This Row],[Custo]]/SUM(tbRHI[Custo]))*SUMIFS(tbEquipe[Custo],tbEquipe[Mês],F$1)*Configuração!$D$10 -> 2101.6878 | G5: =tbRHI[[#This Row],[2]]/tbRHI[[#This Row],[Custo]] -> 0.1072082 | H5: =(tbRHI[[#This Row],[Custo]]/SUM(tbRHI[Custo]))*SUMIFS(tbEquipe[Custo],tbEquipe[Mês],H$1)*Configuração!$D$10 -> 2101.6878 | I5: =tbRHI[[#This Row],[3]]/tbRHI[[#This Row],[Custo]] -> 0.1072082 | J5: =(tbRHI[[#This Row],[Custo]]/SUM(tbRHI[Custo]))*SUMIFS(tbEquipe[Custo],tbEquipe[Mês],J$1)*Configuração!$D$10 -> 2101.6878 | K5: =tbRHI[[#This Row],[4]]/tbRHI[[#This Row],[Custo]] -> 0.1072082 | L5: =(tbRHI[[#This Row],[Custo]]/SUM(tbRHI[Custo]))*SUMIFS(tbEquipe[Custo],tbEquipe[Mês],L$1)*Configuração!$D$10 -> 2101.6878 | M5: =tbRHI[[#This Row],[5]]/tbRHI[[#This Row],[Custo]] -> 0.1072082 | N5: =(tbRHI[[#This Row],[Custo]]/SUM(tbRHI[Custo]))*SUMIFS(tbEquipe[Custo],tbEquipe[Mês],N$1)*Configuração!$D$10 -> 2101.6878 | O5: =tbRHI[[#This Row],[6]]/tbRHI[[#This Row],[Custo]] -> 0.1072082 | P5: =(tbRHI[[#This Row],[Custo]]/SUM(tbRHI[Custo]))*SUMIFS(tbEquipe[Custo],tbEquipe[Mês],P$1)*Configuração!$D$10 -> 2101.6878 | Q5: =tbRHI[[#This Row],[7]]/tbRHI[[#This Row],[Custo]] -> 0.1072082 | R5: =(tbRHI[[#This Row],[Custo]]/SUM(tbRHI[Custo]))*SUMIFS(tbEquipe[Custo],tbEquipe[Mês],R$1)*Configuração!$D$10 -> 2101.6878 | S5: =tbRHI[[#This Row],[8]]/tbRHI[[#This Row],[Custo]] -> 0.1072082 | T5: =(tbRHI[[#This Row],[Custo]]/SUM(tbRHI[Custo]))*SUMIFS(tbEquipe[Custo],tbEquipe[Mês],T$1)*Configuração!$D$10 -> 2101.6878 | U5: =tbRHI[[#This Row],[9]]/tbRHI[[#This Row],[Custo]] -> 0.1072082 | V5: =(tbRHI[[#This Row],[Custo]]/SUM(tbRHI[Custo]))*SUMIFS(tbEquipe[Custo],tbEquipe[Mês],V$1)*Configuração!$D$10 -> 2101.6878 | W5: =tbRHI[[#This Row],[10]]/tbRHI[[#This Row],[Custo]] -> 0.1072082 | X5: =(tbRHI[[#This Row],[Custo]]/SUM(tbRHI[Custo]))*SUMIFS(tbEquipe[Custo],tbEquipe[Mês],X$1)*Configuração!$D$10 -> 2101.6878 | Y5: =tbRHI[[#This Row],[11]]/tbRHI[[#This Row],[Custo]] -> 0.1072082 | Z5: =(tbRHI[[#This Row],[Custo]]/SUM(tbRHI[Custo]))*SUMIFS(tbEquipe[Custo],tbEquipe[Mês],Z$1)*Configuração!$D$10 -> 2101.6878 | AA5: =tbRHI[[#This Row],[12]]/tbRHI[[#This Row],[Custo]] -> 0.1072082 | AB5: =(tbRHI[[#This Row],[Custo]]/SUM(tbRHI[Custo]))*SUMIFS(tbEquipe[Custo],tbEquipe[Mês],AB$1)*Configuração!$D$10 -> 164.20476 | AC5: =tbRHI[[#This Row],[13]]/tbRHI[[#This Row],[Custo]] -> 0.0083761709 | AD5: =(tbRHI[[#This Row],[Custo]]/SUM(tbRHI[Custo]))*SUMIFS(tbEquipe[Custo],tbEquipe[Mês],AD$1)*Configuração!$D$10 -> 174.05705 | AE5: =tbRHI[[#This Row],[14]]/tbRHI[[#This Row],[Custo]] -> 0.0088787412 | AF5: =(tbRHI[[#This Row],[Custo]]/SUM(tbRHI[Custo]))*SUMIFS(tbEquipe[Custo],tbEquipe[Mês],AF$1)*Configuração!$D$10 -> 174.05705 | AG5: =tbRHI[[#This Row],[15]]/tbRHI[[#This Row],[Custo]] -> 0.0088787412 | AH5: =(tbRHI[[#This Row],[Custo]]/SUM(tbRHI[Custo]))*SUMIFS(tbEquipe[Custo],tbEquipe[Mês],AH$1)*Configuração!$D$10 -> 0 | AI5: =tbRHI[[#This Row],[16]]/tbRHI[[#This Row],[Custo]] -> 0 | AJ5: =(tbRHI[[#This Row],[Custo]]/SUM(tbRHI[Custo]))*SUMIFS(tbEquipe[Custo],tbEquipe[Mês],AJ$1)*Configuração!$D$10 -> 0 | AK5: =tbRHI[[#This Row],[17]]/tbRHI[[#This Row],[Custo]] -> 0 | AL5: =(tbRHI[[#This Row],[Custo]]/SUM(tbRHI[Custo]))*SUMIFS(tbEquipe[Custo],tbEquipe[Mês],AL$1)*Configuração!$D$10 -> 0 | AM5: =tbRHI[[#This Row],[18]]/tbRHI[[#This Row],[Custo]] -> 0 | AN5: =(tbRHI[[#This Row],[Custo]]/SUM(tbRHI[Custo]))*SUMIFS(tbEquipe[Custo],tbEquipe[Mês],AN$1)*Configuração!$D$10 -> 0 | AO5: =tbRHI[[#This Row],[19]]/tbRHI[[#This Row],[Custo]] -> 0 | AP5: =(tbRHI[[#This Row],[Custo]]/SUM(tbRHI[Custo]))*SUMIFS(tbEquipe[Custo],tbEquipe[Mês],AP$1)*Configuração!$D$10 -> 0 | AQ5: =tbRHI[[#This Row],[20]]/tbRHI[[#This Row],[Custo]] -> 0 | AR5: =(tbRHI[[#This Row],[Custo]]/SUM(tbRHI[Custo]))*SUMIFS(tbEquipe[Custo],tbEquipe[Mês],AR$1)*Configuração!$D$10 -> 0 | AS5: =tbRHI[[#This Row],[21]]/tbRHI[[#This Row],[Custo]] -> 0 | AT5: =(tbRHI[[#This Row],[Custo]]/SUM(tbRHI[Custo]))*SUMIFS(tbEquipe[Custo],tbEquipe[Mês],AT$1)*Configuração!$D$10 -> 0 | AU5: =tbRHI[[#This Row],[22]]/tbRHI[[#This Row],[Custo]] -> 0 | AV5: =(tbRHI[[#This Row],[Custo]]/SUM(tbRHI[Custo]))*SUMIFS(tbEquipe[Custo],tbEquipe[Mês],AV$1)*Configuração!$D$10 -> 0 | AW5: =tbRHI[[#This Row],[23]]/tbRHI[[#This Row],[Custo]] -> 0
A6: DANIEL DO CARMO MENEZES | B6: =_xlfn.XLOOKUP($A6,DBFolha!$A:$A,DBFolha!$B:$B) -> ANALISTA DE SISTEMAS SR | C6: =_xlfn.XLOOKUP($A6,DBFolha!$A:$A,DBFolha!$C:$C) -> 21083.105 | D6: =(tbRHI[[#This Row],[Custo]]/SUM(tbRHI[Custo]))*SUMIFS(tbEquipe[Custo],tbEquipe[Mês],D$1)*Configuração!$D$10 -> 2183.8857 | E6: =tbRHI[[#This Row],[1]]/tbRHI[[#This Row],[Custo]] -> 0.10358463 | F6: =(tbRHI[[#This Row],[Custo]]/SUM(tbRHI[Custo]))*SUMIFS(tbEquipe[Custo],tbEquipe[Mês],F$1)*Configuração!$D$10 -> 2260.2817 | G6: =tbRHI[[#This Row],[2]]/tbRHI[[#This Row],[Custo]] -> 0.1072082 | H6: =(tbRHI[[#This Row],[Custo]]/SUM(tbRHI[Custo]))*SUMIFS(tbEquipe[Custo],tbEquipe[Mês],H$1)*Configuração!$D$10 -> 2260.2817 | I6: =tbRHI[[#This Row],[3]]/tbRHI[[#This Row],[Custo]] -> 0.1072082 | J6: =(tbRHI[[#This Row],[Custo]]/SUM(tbRHI[Custo]))*SUMIFS(tbEquipe[Custo],tbEquipe[Mês],J$1)*Configuração!$D$10 -> 2260.2817 | K6: =tbRHI[[#This Row],[4]]/tbRHI[[#This Row],[Custo]] -> 0.1072082 | L6: =(tbRHI[[#This Row],[Custo]]/SUM(tbRHI[Custo]))*SUMIFS(tbEquipe[Custo],tbEquipe[Mês],L$1)*Configuração!$D$10 -> 2260.2817 | M6: =tbRHI[[#This Row],[5]]/tbRHI[[#This Row],[Custo]] -> 0.1072082 | N6: =(tbRHI[[#This Row],[Custo]]/SUM(tbRHI[Custo]))*SUMIFS(tbEquipe[Custo],tbEquipe[Mês],N$1)*Configuração!$D$10 -> 2260.2817 | O6: =tbRHI[[#This Row],[6]]/tbRHI[[#This Row],[Custo]] -> 0.1072082 | P6: =(tbRHI[[#This Row],[Custo]]/SUM(tbRHI[Custo]))*SUMIFS(tbEquipe[Custo],tbEquipe[Mês],P$1)*Configuração!$D$10 -> 2260.2817 | Q6: =tbRHI[[#This Row],[7]]/tbRHI[[#This Row],[Custo]] -> 0.1072082 | R6: =(tbRHI[[#This Row],[Custo]]/SUM(tbRHI[Custo]))*SUMIFS(tbEquipe[Custo],tbEquipe[Mês],R$1)*Configuração!$D$10 -> 2260.2817 | S6: =tbRHI[[#This Row],[8]]/tbRHI[[#This Row],[Custo]] -> 0.1072082 | T6: =(tbRHI[[#This Row],[Custo]]/SUM(tbRHI[Custo]))*SUMIFS(tbEquipe[Custo],tbEquipe[Mês],T$1)*Configuração!$D$10 -> 2260.2817 | U6: =tbRHI[[#This Row],[9]]/tbRHI[[#This Row],[Custo]] -> 0.1072082 | V6: =(tbRHI[[#This Row],[Custo]]/SUM(tbRHI[Custo]))*SUMIFS(tbEquipe[Custo],tbEquipe[Mês],V$1)*Configuração!$D$10 -> 2260.2817 | W6: =tbRHI[[#This Row],[10]]/tbRHI[[#This Row],[Custo]] -> 0.1072082 | X6: =(tbRHI[[#This Row],[Custo]]/SUM(tbRHI[Custo]))*SUMIFS(tbEquipe[Custo],tbEquipe[Mês],X$1)*Configuração!$D$10 -> 2260.2817 | Y6: =tbRHI[[#This Row],[11]]/tbRHI[[#This Row],[Custo]] -> 0.1072082 | Z6: =(tbRHI[[#This Row],[Custo]]/SUM(tbRHI[Custo]))*SUMIFS(tbEquipe[Custo],tbEquipe[Mês],Z$1)*Configuração!$D$10 -> 2260.2817 | AA6: =tbRHI[[#This Row],[12]]/tbRHI[[#This Row],[Custo]] -> 0.1072082 | AB6: =(tbRHI[[#This Row],[Custo]]/SUM(tbRHI[Custo]))*SUMIFS(tbEquipe[Custo],tbEquipe[Mês],AB$1)*Configuração!$D$10 -> 176.59569 | AC6: =tbRHI[[#This Row],[13]]/tbRHI[[#This Row],[Custo]] -> 0.0083761709 | AD6: =(tbRHI[[#This Row],[Custo]]/SUM(tbRHI[Custo]))*SUMIFS(tbEquipe[Custo],tbEquipe[Mês],AD$1)*Configuração!$D$10 -> 187.19143 | AE6: =tbRHI[[#This Row],[14]]/tbRHI[[#This Row],[Custo]] -> 0.0088787412 | AF6: =(tbRHI[[#This Row],[Custo]]/SUM(tbRHI[Custo]))*SUMIFS(tbEquipe[Custo],tbEquipe[Mês],AF$1)*Configuração!$D$10 -> 187.19143 | AG6: =tbRHI[[#This Row],[15]]/tbRHI[[#This Row],[Custo]] -> 0.0088787412 | AH6: =(tbRHI[[#This Row],[Custo]]/SUM(tbRHI[Custo]))*SUMIFS(tbEquipe[Custo],tbEquipe[Mês],AH$1)*Configuração!$D$10 -> 0 | AI6: =tbRHI[[#This Row],[16]]/tbRHI[[#This Row],[Custo]] -> 0 | AJ6: =(tbRHI[[#This Row],[Custo]]/SUM(tbRHI[Custo]))*SUMIFS(tbEquipe[Custo],tbEquipe[Mês],AJ$1)*Configuração!$D$10 -> 0 | AK6: =tbRHI[[#This Row],[17]]/tbRHI[[#This Row],[Custo]] -> 0 | AL6: =(tbRHI[[#This Row],[Custo]]/SUM(tbRHI[Custo]))*SUMIFS(tbEquipe[Custo],tbEquipe[Mês],AL$1)*Configuração!$D$10 -> 0 | AM6: =tbRHI[[#This Row],[18]]/tbRHI[[#This Row],[Custo]] -> 0 | AN6: =(tbRHI[[#This Row],[Custo]]/SUM(tbRHI[Custo]))*SUMIFS(tbEquipe[Custo],tbEquipe[Mês],AN$1)*Configuração!$D$10 -> 0 | AO6: =tbRHI[[#This Row],[19]]/tbRHI[[#This Row],[Custo]] -> 0 | AP6: =(tbRHI[[#This Row],[Custo]]/SUM(tbRHI[Custo]))*SUMIFS(tbEquipe[Custo],tbEquipe[Mês],AP$1)*Configuração!$D$10 -> 0 | AQ6: =tbRHI[[#This Row],[20]]/tbRHI[[#This Row],[Custo]] -> 0 | AR6: =(tbRHI[[#This Row],[Custo]]/SUM(tbRHI[Custo]))*SUMIFS(tbEquipe[Custo],tbEquipe[Mês],AR$1)*Configuração!$D$10 -> 0 | AS6: =tbRHI[[#This Row],[21]]/tbRHI[[#This Row],[Custo]] -> 0 | AT6: =(tbRHI[[#This Row],[Custo]]/SUM(tbRHI[Custo]))*SUMIFS(tbEquipe[Custo],tbEquipe[Mês],AT$1)*Configuração!$D$10 -> 0 | AU6: =tbRHI[[#This Row],[22]]/tbRHI[[#This Row],[Custo]] -> 0 | AV6: =(tbRHI[[#This Row],[Custo]]/SUM(tbRHI[Custo]))*SUMIFS(tbEquipe[Custo],tbEquipe[Mês],AV$1)*Configuração!$D$10 -> 0 | AW6: =tbRHI[[#This Row],[23]]/tbRHI[[#This Row],[Custo]] -> 0
A7: ANDREA MEIRELES DA MOTA | B7: =_xlfn.XLOOKUP($A7,DBFolha!$A:$A,DBFolha!$B:$B) -> COORDENADOR(A) DE CONTROLADORIA | C7: =_xlfn.XLOOKUP($A7,DBFolha!$A:$A,DBFolha!$C:$C) -> 23450.8 | D7: =(tbRHI[[#This Row],[Custo]]/SUM(tbRHI[Custo]))*SUMIFS(tbEquipe[Custo],tbEquipe[Mês],D$1)*Configuração!$D$10 -> 2429.1426 | E7: =tbRHI[[#This Row],[1]]/tbRHI[[#This Row],[Custo]] -> 0.10358463 | F7: =(tbRHI[[#This Row],[Custo]]/SUM(tbRHI[Custo]))*SUMIFS(tbEquipe[Custo],tbEquipe[Mês],F$1)*Configuração!$D$10 -> 2514.118 | G7: =tbRHI[[#This Row],[2]]/tbRHI[[#This Row],[Custo]] -> 0.1072082 | H7: =(tbRHI[[#This Row],[Custo]]/SUM(tbRHI[Custo]))*SUMIFS(tbEquipe[Custo],tbEquipe[Mês],H$1)*Configuração!$D$10 -> 2514.118 | I7: =tbRHI[[#This Row],[3]]/tbRHI[[#This Row],[Custo]] -> 0.1072082 | J7: =(tbRHI[[#This Row],[Custo]]/SUM(tbRHI[Custo]))*SUMIFS(tbEquipe[Custo],tbEquipe[Mês],J$1)*Configuração!$D$10 -> 2514.118 | K7: =tbRHI[[#This Row],[4]]/tbRHI[[#This Row],[Custo]] -> 0.1072082 | L7: =(tbRHI[[#This Row],[Custo]]/SUM(tbRHI[Custo]))*SUMIFS(tbEquipe[Custo],tbEquipe[Mês],L$1)*Configuração!$D$10 -> 2514.118 | M7: =tbRHI[[#This Row],[5]]/tbRHI[[#This Row],[Custo]] -> 0.1072082 | N7: =(tbRHI[[#This Row],[Custo]]/SUM(tbRHI[Custo]))*SUMIFS(tbEquipe[Custo],tbEquipe[Mês],N$1)*Configuração!$D$10 -> 2514.118 | O7: =tbRHI[[#This Row],[6]]/tbRHI[[#This Row],[Custo]] -> 0.1072082 | P7: =(tbRHI[[#This Row],[Custo]]/SUM(tbRHI[Custo]))*SUMIFS(tbEquipe[Custo],tbEquipe[Mês],P$1)*Configuração!$D$10 -> 2514.118 | Q7: =tbRHI[[#This Row],[7]]/tbRHI[[#This Row],[Custo]] -> 0.1072082 | R7: =(tbRHI[[#This Row],[Custo]]/SUM(tbRHI[Custo]))*SUMIFS(tbEquipe[Custo],tbEquipe[Mês],R$1)*Configuração!$D$10 -> 2514.118 | S7: =tbRHI[[#This Row],[8]]/tbRHI[[#This Row],[Custo]] -> 0.1072082 | T7: =(tbRHI[[#This Row],[Custo]]/SUM(tbRHI[Custo]))*SUMIFS(tbEquipe[Custo],tbEquipe[Mês],T$1)*Configuração!$D$10 -> 2514.118 | U7: =tbRHI[[#This Row],[9]]/tbRHI[[#This Row],[Custo]] -> 0.1072082 | V7: =(tbRHI[[#This Row],[Custo]]/SUM(tbRHI[Custo]))*SUMIFS(tbEquipe[Custo],tbEquipe[Mês],V$1)*Configuração!$D$10 -> 2514.118 | W7: =tbRHI[[#This Row],[10]]/tbRHI[[#This Row],[Custo]] -> 0.1072082 | X7: =(tbRHI[[#This Row],[Custo]]/SUM(tbRHI[Custo]))*SUMIFS(tbEquipe[Custo],tbEquipe[Mês],X$1)*Configuração!$D$10 -> 2514.118 | Y7: =tbRHI[[#This Row],[11]]/tbRHI[[#This Row],[Custo]] -> 0.1072082 | Z7: =(tbRHI[[#This Row],[Custo]]/SUM(tbRHI[Custo]))*SUMIFS(tbEquipe[Custo],tbEquipe[Mês],Z$1)*Configuração!$D$10 -> 2514.118 | AA7: =tbRHI[[#This Row],[12]]/tbRHI[[#This Row],[Custo]] -> 0.1072082 | AB7: =(tbRHI[[#This Row],[Custo]]/SUM(tbRHI[Custo]))*SUMIFS(tbEquipe[Custo],tbEquipe[Mês],AB$1)*Configuração!$D$10 -> 196.42791 | AC7: =tbRHI[[#This Row],[13]]/tbRHI[[#This Row],[Custo]] -> 0.0083761709 | AD7: =(tbRHI[[#This Row],[Custo]]/SUM(tbRHI[Custo]))*SUMIFS(tbEquipe[Custo],tbEquipe[Mês],AD$1)*Configuração!$D$10 -> 208.21359 | AE7: =tbRHI[[#This Row],[14]]/tbRHI[[#This Row],[Custo]] -> 0.0088787412 | AF7: =(tbRHI[[#This Row],[Custo]]/SUM(tbRHI[Custo]))*SUMIFS(tbEquipe[Custo],tbEquipe[Mês],AF$1)*Configuração!$D$10 -> 208.21359 | AG7: =tbRHI[[#This Row],[15]]/tbRHI[[#This Row],[Custo]] -> 0.0088787412 | AH7: =(tbRHI[[#This Row],[Custo]]/SUM(tbRHI[Custo]))*SUMIFS(tbEquipe[Custo],tbEquipe[Mês],AH$1)*Configuração!$D$10 -> 0 | AI7: =tbRHI[[#This Row],[16]]/tbRHI[[#This Row],[Custo]] -> 0 | AJ7: =(tbRHI[[#This Row],[Custo]]/SUM(tbRHI[Custo]))*SUMIFS(tbEquipe[Custo],tbEquipe[Mês],AJ$1)*Configuração!$D$10 -> 0 | AK7: =tbRHI[[#This Row],[17]]/tbRHI[[#This Row],[Custo]] -> 0 | AL7: =(tbRHI[[#This Row],[Custo]]/SUM(tbRHI[Custo]))*SUMIFS(tbEquipe[Custo],tbEquipe[Mês],AL$1)*Configuração!$D$10 -> 0 | AM7: =tbRHI[[#This Row],[18]]/tbRHI[[#This Row],[Custo]] -> 0 | AN7: =(tbRHI[[#This Row],[Custo]]/SUM(tbRHI[Custo]))*SUMIFS(tbEquipe[Custo],tbEquipe[Mês],AN$1)*Configuração!$D$10 -> 0 | AO7: =tbRHI[[#This Row],[19]]/tbRHI[[#This Row],[Custo]] -> 0 | AP7: =(tbRHI[[#This Row],[Custo]]/SUM(tbRHI[Custo]))*SUMIFS(tbEquipe[Custo],tbEquipe[Mês],AP$1)*Configuração!$D$10 -> 0 | AQ7: =tbRHI[[#This Row],[20]]/tbRHI[[#This Row],[Custo]] -> 0 | AR7: =(tbRHI[[#This Row],[Custo]]/SUM(tbRHI[Custo]))*SUMIFS(tbEquipe[Custo],tbEquipe[Mês],AR$1)*Configuração!$D$10 -> 0 | AS7: =tbRHI[[#This Row],[21]]/tbRHI[[#This Row],[Custo]] -> 0 | AT7: =(tbRHI[[#This Row],[Custo]]/SUM(tbRHI[Custo]))*SUMIFS(tbEquipe[Custo],tbEquipe[Mês],AT$1)*Configuração!$D$10 -> 0 | AU7: =tbRHI[[#This Row],[22]]/tbRHI[[#This Row],[Custo]] -> 0 | AV7: =(tbRHI[[#This Row],[Custo]]/SUM(tbRHI[Custo]))*SUMIFS(tbEquipe[Custo],tbEquipe[Mês],AV$1)*Configuração!$D$10 -> 0 | AW7: =tbRHI[[#This Row],[23]]/tbRHI[[#This Row],[Custo]] -> 0
B8: =SUBTOTAL(103,tbRHI[Cargo]) -> 6 | C8: =SUBTOTAL(109,tbRHI[Custo]) -> 129535.49 | D8: =SUBTOTAL(109,tbRHI[1]) -> 13417.886 | E8: =SUBTOTAL(109,tbRHI[%Aloc1]) -> 0.62150781 | F8: =SUBTOTAL(109,tbRHI[2]) -> 13887.266 | G8: =SUBTOTAL(109,tbRHI[%Aloc2]) -> 0.64324918 | H8: =SUBTOTAL(109,tbRHI[3]) -> 13887.266 | I8: =SUBTOTAL(109,tbRHI[%Aloc3]) -> 0.64324918 | J8: =SUBTOTAL(109,tbRHI[4]) -> 13887.266 | K8: =SUBTOTAL(109,tbRHI[%Aloc4]) -> 0.64324918 | L8: =SUBTOTAL(109,tbRHI[5]) -> 13887.266 | M8: =SUBTOTAL(109,tbRHI[%Aloc5]) -> 0.64324918 | N8: =SUBTOTAL(109,tbRHI[6]) -> 13887.266 | O8: =SUBTOTAL(109,tbRHI[%Aloc6]) -> 0.64324918 | P8: =SUBTOTAL(109,tbRHI[7]) -> 13887.266 | Q8: =SUBTOTAL(109,tbRHI[%Aloc7]) -> 0.64324918 | R8: =SUBTOTAL(109,tbRHI[8]) -> 13887.266 | S8: =SUBTOTAL(109,tbRHI[%Aloc8]) -> 0.64324918 | T8: =SUBTOTAL(109,tbRHI[9]) -> 13887.266 | U8: =SUBTOTAL(109,tbRHI[%Aloc9]) -> 0.64324918 | V8: =SUBTOTAL(109,tbRHI[10]) -> 13887.266 | W8: =SUBTOTAL(109,tbRHI[%Aloc10]) -> 0.64324918 | X8: =SUBTOTAL(109,tbRHI[11]) -> 13887.266 | Y8: =SUBTOTAL(109,tbRHI[%Aloc11]) -> 0.64324918 | Z8: =SUBTOTAL(109,tbRHI[12]) -> 13887.266 | AA8: =SUBTOTAL(109,tbRHI[%Aloc12]) -> 0.64324918 | AB8: =SUBTOTAL(109,tbRHI[13]) -> 1085.0114 | AC8: =SUBTOTAL(109,tbRHI[%Aloc13]) -> 0.050257026 | AD8: =SUBTOTAL(109,tbRHI[14]) -> 1150.1121 | AE8: =SUBTOTAL(109,tbRHI[%Aloc14]) -> 0.053272447 | AF8: =SUBTOTAL(109,tbRHI[15]) -> 1150.1121 | AG8: =SUBTOTAL(109,tbRHI[%Aloc15]) -> 0.053272447 | AH8: =SUBTOTAL(109,tbRHI[16]) -> 0 | AI8: =SUBTOTAL(109,tbRHI[%Aloc16]) -> 0 | AJ8: =SUBTOTAL(109,tbRHI[17]) -> 0 | AK8: =SUBTOTAL(109,tbRHI[%Aloc17]) -> 0 | AL8: =SUBTOTAL(109,tbRHI[18]) -> 0 | AM8: =SUBTOTAL(109,tbRHI[%Aloc18]) -> 0 | AN8: =SUBTOTAL(109,tbRHI[19]) -> 0 | AO8: =SUBTOTAL(109,tbRHI[%Aloc19]) -> 0 | AP8: =SUBTOTAL(109,tbRHI[20]) -> 0 | AQ8: =SUBTOTAL(109,tbRHI[%Aloc20]) -> 0 | AR8: =SUBTOTAL(109,tbRHI[21]) -> 0 | AS8: =SUBTOTAL(109,tbRHI[%Aloc21]) -> 0 | AT8: =SUBTOTAL(109,tbRHI[22]) -> 0 | AU8: =SUBTOTAL(109,tbRHI[%Aloc22]) -> 0 | AV8: =SUBTOTAL(109,tbRHI[23]) -> 0 | AW8: =SUBTOTAL(109,tbRHI[%Aloc23]) -> 0 | AY8: =SUM(tbRHI[[#Totals],[1]]+tbRHI[[#Totals],[2]]+tbRHI[[#Totals],[3]]+tbRHI[[#Totals],[4]]+tbRHI[[#Totals],[5]]+tbRHI[[#Totals],[6]]+tbRHI[[#Totals],[7]]+tbRHI[[#Totals],[8]]+tbRHI[[#Totals],[9]]+tbRHI[[#Totals],[10]]+tbRHI[[#Totals],[11]]+tbRHI[[#Totals],[12]]) -> 166177.81

Sheet Rateio
A1: Despesa | B1: Custo Mensal | C1: Custo Rateado | D1: 1 | E1: 2 | F1: 3 | G1: 4 | H1: 5 | I1: 6 | J1: 7 | K1: 8 | L1: 9 | M1: 10 | N1: 11 | O1: 12 | P1: 13 | Q1: 14 | R1: 15 | S1: 16 | T1: 17 | U1: 18 | V1: 19 | W1: 20 | X1: 21 | Y1: 22 | Z1: 23
A2: Consumo Energia Elétrica | B2: 41000 | C2: =SUM(tbRateio[[#This Row],[1]],tbRateio[[#This Row],[2]],tbRateio[[#This Row],[3]],tbRateio[[#This Row],[4]],tbRateio[[#This Row],[5]],tbRateio[[#This Row],[6]],tbRateio[[#This Row],[7]],tbRateio[[#This Row],[8]],tbRateio[[#This Row],[9]],tbRateio[[#This Row],[10]],tbRateio[[#This Row],[11]],tbRateio[[#This Row],[12]],tbRateio[[#This Row],[13]],tbRateio[[#This Row],[14]],tbRateio[[#This Row],[15]],tbRateio[[#This Row],[16]],tbRateio[[#This Row],[17]],tbRateio[[#This Row],[18]],tbRateio[[#This Row],[19]],tbRateio[[#This Row],[20]],tbRateio[[#This Row],[21]],tbRateio[[#This Row],[22]],tbRateio[[#This Row],[23]]) -> 18244.724 | D2: =((SUMIF(tbEquipe[Mês],D$1,tbEquipe[Alocação])*Configuração!$D$14+SUM(tbRHI[%Aloc1])*Configuração!$D$15)/Configuração!$D$13)*tbRateio[[#This Row],[Custo Mensal]] -> 1496.26 | E2: =((SUMIF(tbEquipe[Mês],E$1,tbEquipe[Alocação])*Configuração!$D$14+SUM(tbRHI[%Aloc2])*Configuração!$D$15)/Configuração!$D$13)*tbRateio[[#This Row],[Custo Mensal]] -> 1502.5819 | F2: =((SUMIF(tbEquipe[Mês],F$1,tbEquipe[Alocação])*Configuração!$D$14+SUM(tbRHI[%Aloc3])*Configuração!$D$15)/Configuração!$D$13)*tbRateio[[#This Row],[Custo Mensal]] -> 1502.5819 | G2: =((SUMIF(tbEquipe[Mês],G$1,tbEquipe[Alocação])*Configuração!$D$14+SUM(tbRHI[%Aloc4])*Configuração!$D$15)/Configuração!$D$13)*tbRateio[[#This Row],[Custo Mensal]] -> 1502.5819 | H2: =((SUMIF(tbEquipe[Mês],H$1,tbEquipe[Alocação])*Configuração!$D$14+SUM(tbRHI[%Aloc5])*Configuração!$D$15)/Configuração!$D$13)*tbRateio[[#This Row],[Custo Mensal]] -> 1502.5819 | I2: =((SUMIF(tbEquipe[Mês],I$1,tbEquipe[Alocação])*Configuração!$D$14+SUM(tbRHI[%Aloc6])*Configuração!$D$15)/Configuração!$D$13)*tbRateio[[#This Row],[Custo Mensal]] -> 1502.5819 | J2: =((SUMIF(tbEquipe[Mês],J$1,tbEquipe[Alocação])*Configuração!$D$14+SUM(tbRHI[%Aloc7])*Configuração!$D$15)/Configuração!$D$13)*tbRateio[[#This Row],[Custo Mensal]] -> 1502.5819 | K2: =((SUMIF(tbEquipe[Mês],K$1,tbEquipe[Alocação])*Configuração!$D$14+SUM(tbRHI[%Aloc8])*Configuração!$D$15)/Configuração!$D$13)*tbRateio[[#This Row],[Custo Mensal]] -> 1502.5819 | L2: =((SUMIF(tbEquipe[Mês],L$1,tbEquipe[Alocação])*Configuração!$D$14+SUM(tbRHI[%Aloc9])*Configuração!$D$15)/Configuração!$D$13)*tbRateio[[#This Row],[Custo Mensal]] -> 1502.5819 | M2: =((SUMIF(tbEquipe[Mês],M$1,tbEquipe[Alocação])*Configuração!$D$14+SUM(tbRHI[%Aloc10])*Configuração!$D$15)/Configuração!$D$13)*tbRateio[[#This Row],[Custo Mensal]] -> 1502.5819 | N2: =((SUMIF(tbEquipe[Mês],N$1,tbEquipe[Alocação])*Configuração!$D$14+SUM(tbRHI[%Aloc11])*Configuração!$D$15)/Configuração!$D$13)*tbRateio[[#This Row],[Custo Mensal]] -> 1502.5819 | O2: =((SUMIF(tbEquipe[Mês],O$1,tbEquipe[Alocação])*Configuração!$D$14+SUM(tbRHI[%Aloc12])*Configuração!$D$15)/Configuração!$D$13)*tbRateio[[#This Row],[Custo Mensal]] -> 1502.5819 | P2: =((SUMIF(tbEquipe[Mês],P$1,tbEquipe[Alocação])*Configuração!$D$14+SUM(tbRHI[%Aloc13])*Configuração!$D$15)/Configuração!$D$13)*tbRateio[[#This Row],[Custo Mensal]] -> 72.769773 | Q2: =((SUMIF(tbEquipe[Mês],Q$1,tbEquipe[Alocação])*Configuração!$D$14+SUM(tbRHI[%Aloc14])*Configuração!$D$15)/Configuração!$D$13)*tbRateio[[#This Row],[Custo Mensal]] -> 73.646598 | R2: =((SUMIF(tbEquipe[Mês],R$1,tbEquipe[Alocação])*Configuração!$D$14+SUM(tbRHI[%Aloc15])*Configuração!$D$15)/Configuração!$D$13)*tbRateio[[#This Row],[Custo Mensal]] -> 73.646598 | S2: =((SUMIF(tbEquipe[Mês],S$1,tbEquipe[Alocação])*Configuração!$D$14+SUM(tbRHI[%Aloc16])*Configuração!$D$15)/Configuração!$D$13)*tbRateio[[#This Row],[Custo Mensal]] -> 0 | T2: =((SUMIF(tbEquipe[Mês],T$1,tbEquipe[Alocação])*Configuração!$D$14+SUM(tbRHI[%Aloc17])*Configuração!$D$15)/Configuração!$D$13)*tbRateio[[#This Row],[Custo Mensal]] -> 0 | U2: =((SUMIF(tbEquipe[Mês],U$1,tbEquipe[Alocação])*Configuração!$D$14+SUM(tbRHI[%Aloc18])*Configuração!$D$15)/Configuração!$D$13)*tbRateio[[#This Row],[Custo Mensal]] -> 0 | V2: =((SUMIF(tbEquipe[Mês],V$1,tbEquipe[Alocação])*Configuração!$D$14+SUM(tbRHI[%Aloc19])*Configuração!$D$15)/Configuração!$D$13)*tbRateio[[#This Row],[Custo Mensal]] -> 0 | W2: =((SUMIF(tbEquipe[Mês],W$1,tbEquipe[Alocação])*Configuração!$D$14+SUM(tbRHI[%Aloc20])*Configuração!$D$15)/Configuração!$D$13)*tbRateio[[#This Row],[Custo Mensal]] -> 0 | X2: =((SUMIF(tbEquipe[Mês],X$1,tbEquipe[Alocação])*Configuração!$D$14+SUM(tbRHI[%Aloc21])*Configuração!$D$15)/Configuração!$D$13)*tbRateio[[#This Row],[Custo Mensal]] -> 0 | Y2: =((SUMIF(tbEquipe[Mês],Y$1,tbEquipe[Alocação])*Configuração!$D$14+SUM(tbRHI[%Aloc22])*Configuração!$D$15)/Configuração!$D$13)*tbRateio[[#This Row],[Custo Mensal]] -> 0 | Z2: =((SUMIF(tbEquipe[Mês],Z$1,tbEquipe[Alocação])*Configuração!$D$14+SUM(tbRHI[%Aloc23])*Configuração!$D$15)/Configuração!$D$13)*tbRateio[[#This Row],[Custo Mensal]] -> 0
A3: Aluguel Prédio | B3: 75000 | C3: =SUM(tbRateio[[#This Row],[1]],tbRateio[[#This Row],[2]],tbRateio[[#This Row],[3]],tbRateio[[#This Row],[4]],tbRateio[[#This Row],[5]],tbRateio[[#This Row],[6]],tbRateio[[#This Row],[7]],tbRateio[[#This Row],[8]],tbRateio[[#This Row],[9]],tbRateio[[#This Row],[10]],tbRateio[[#This Row],[11]],tbRateio[[#This Row],[12]],tbRateio[[#This Row],[13]],tbRateio[[#This Row],[14]],tbRateio[[#This Row],[15]],tbRateio[[#This Row],[16]],tbRateio[[#This Row],[17]],tbRateio[[#This Row],[18]],tbRateio[[#This Row],[19]],tbRateio[[#This Row],[20]],tbRateio[[#This Row],[21]],tbRateio[[#This Row],[22]],tbRateio[[#This Row],[23]]) -> 33374.495 | D3: =((SUMIF(tbEquipe[Mês],D$1,tbEquipe[Alocação])*Configuração!$D$14+SUM(tbRHI[%Aloc1])*Configuração!$D$15)/Configuração!$D$13)*tbRateio[[#This Row],[Custo Mensal]] -> 2737.0609 | E3: =((SUMIF(tbEquipe[Mês],E$1,tbEquipe[Alocação])*Configuração!$D$14+SUM(tbRHI[%Aloc2])*Configuração!$D$15)/Configuração!$D$13)*tbRateio[[#This Row],[Custo Mensal]] -> 2748.6255 | F3: =((SUMIF(tbEquipe[Mês],F$1,tbEquipe[Alocação])*Configuração!$D$14+SUM(tbRHI[%Aloc3])*Configuração!$D$15)/Configuração!$D$13)*tbRateio[[#This Row],[Custo Mensal]] -> 2748.6255 | G3: =((SUMIF(tbEquipe[Mês],G$1,tbEquipe[Alocação])*Configuração!$D$14+SUM(tbRHI[%Aloc4])*Configuração!$D$15)/Configuração!$D$13)*tbRateio[[#This Row],[Custo Mensal]] -> 2748.6255 | H3: =((SUMIF(tbEquipe[Mês],H$1,tbEquipe[Alocação])*Configuração!$D$14+SUM(tbRHI[%Aloc5])*Configuração!$D$15)/Configuração!$D$13)*tbRateio[[#This Row],[Custo Mensal]] -> 2748.6255 | I3: =((SUMIF(tbEquipe[Mês],I$1,tbEquipe[Alocação])*Configuração!$D$14+SUM(tbRHI[%Aloc6])*Configuração!$D$15)/Configuração!$D$13)*tbRateio[[#This Row],[Custo Mensal]] -> 2748.6255 | J3: =((SUMIF(tbEquipe[Mês],J$1,tbEquipe[Alocação])*Configuração!$D$14+SUM(tbRHI[%Aloc7])*Configuração!$D$15)/Configuração!$D$13)*tbRateio[[#This Row],[Custo Mensal]] -> 2748.6255 | K3: =((SUMIF(tbEquipe[Mês],K$1,tbEquipe[Alocação])*Configuração!$D$14+SUM(tbRHI[%Aloc8])*Configuração!$D$15)/Configuração!$D$13)*tbRateio[[#This Row],[Custo Mensal]] -> 2748.6255 | L3: =((SUMIF(tbEquipe[Mês],L$1,tbEquipe[Alocação])*Configuração!$D$14+SUM(tbRHI[%Aloc9])*Configuração!$D$15)/Configuração!$D$13)*tbRateio[[#This Row],[Custo Mensal]] -> 2748.6255 | M3: =((SUMIF(tbEquipe[Mês],M$1,tbEquipe[Alocação])*Configuração!$D$14+SUM(tbRHI[%Aloc10])*Configuração!$D$15)/Configuração!$D$13)*tbRateio[[#This Row],[Custo Mensal]] -> 2748.6255 | N3: =((SUMIF(tbEquipe[Mês],N$1,tbEquipe[Alocação])*Configuração!$D$14+SUM(tbRHI[%Aloc11])*Configuração!$D$15)/Configuração!$D$13)*tbRateio[[#This Row],[Custo Mensal]] -> 2748.6255 | O3: =((SUMIF(tbEquipe[Mês],O$1,tbEquipe[Alocação])*Configuração!$D$14+SUM(tbRHI[%Aloc12])*Configuração!$D$15)/Configuração!$D$13)*tbRateio[[#This Row],[Custo Mensal]] -> 2748.6255 | P3: =((SUMIF(tbEquipe[Mês],P$1,tbEquipe[Alocação])*Configuração!$D$14+SUM(tbRHI[%Aloc13])*Configuração!$D$15)/Configuração!$D$13)*tbRateio[[#This Row],[Custo Mensal]] -> 133.11544 | Q3: =((SUMIF(tbEquipe[Mês],Q$1,tbEquipe[Alocação])*Configuração!$D$14+SUM(tbRHI[%Aloc14])*Configuração!$D$15)/Configuração!$D$13)*tbRateio[[#This Row],[Custo Mensal]] -> 134.71939 | R3: =((SUMIF(tbEquipe[Mês],R$1,tbEquipe[Alocação])*Configuração!$D$14+SUM(tbRHI[%Aloc15])*Configuração!$D$15)/Configuração!$D$13)*tbRateio[[#This Row],[Custo Mensal]] -> 134.71939 | S3: =((SUMIF(tbEquipe[Mês],S$1,tbEquipe[Alocação])*Configuração!$D$14+SUM(tbRHI[%Aloc16])*Configuração!$D$15)/Configuração!$D$13)*tbRateio[[#This Row],[Custo Mensal]] -> 0 | T3: =((SUMIF(tbEquipe[Mês],T$1,tbEquipe[Alocação])*Configuração!$D$14+SUM(tbRHI[%Aloc17])*Configuração!$D$15)/Configuração!$D$13)*tbRateio[[#This Row],[Custo Mensal]] -> 0 | U3: =((SUMIF(tbEquipe[Mês],U$1,tbEquipe[Alocação])*Configuração!$D$14+SUM(tbRHI[%Aloc18])*Configuração!$D$15)/Configuração!$D$13)*tbRateio[[#This Row],[Custo Mensal]] -> 0 | V3: =((SUMIF(tbEquipe[Mês],V$1,tbEquipe[Alocação])*Configuração!$D$14+SUM(tbRHI[%Aloc19])*Configuração!$D$15)/Configuração!$D$13)*tbRateio[[#This Row],[Custo Mensal]] -> 0 | W3: =((SUMIF(tbEquipe[Mês],W$1,tbEquipe[Alocação])*Configuração!$D$14+SUM(tbRHI[%Aloc20])*Configuração!$D$15)/Configuração!$D$13)*tbRateio[[#This Row],[Custo Mensal]] -> 0 | X3: =((SUMIF(tbEquipe[Mês],X$1,tbEquipe[Alocação])*Configuração!$D$14+SUM(tbRHI[%Aloc21])*Configuração!$D$15)/Configuração!$D$13)*tbRateio[[#This Row],[Custo Mensal]] -> 0 | Y3: =((SUMIF(tbEquipe[Mês],Y$1,tbEquipe[Alocação])*Configuração!$D$14+SUM(tbRHI[%Aloc22])*Configuração!$D$15)/Configuração!$D$13)*tbRateio[[#This Row],[Custo Mensal]] -> 0 | Z3: =((SUMIF(tbEquipe[Mês],Z$1,tbEquipe[Alocação])*Configuração!$D$14+SUM(tbRHI[%Aloc23])*Configuração!$D$15)/Configuração!$D$13)*tbRateio[[#This Row],[Custo Mensal]] -> 0
A4: Telefonia - Oi | B4: 1000 | C4: =SUM(tbRateio[[#This Row],[1]],tbRateio[[#This Row],[2]],tbRateio[[#This Row],[3]],tbRateio[[#This Row],[4]],tbRateio[[#This Row],[5]],tbRateio[[#This Row],[6]],tbRateio[[#This Row],[7]],tbRateio[[#This Row],[8]],tbRateio[[#This Row],[9]],tbRateio[[#This Row],[10]],tbRateio[[#This Row],[11]],tbRateio[[#This Row],[12]],tbRateio[[#This Row],[13]],tbRateio[[#This Row],[14]],tbRateio[[#This Row],[15]],tbRateio[[#This Row],[16]],tbRateio[[#This Row],[17]],tbRateio[[#This Row],[18]],tbRateio[[#This Row],[19]],tbRateio[[#This Row],[20]],tbRateio[[#This Row],[21]],tbRateio[[#This Row],[22]],tbRateio[[#This Row],[23]]) -> 444.99327 | D4: =((SUMIF(tbEquipe[Mês],D$1,tbEquipe[Alocação])*Configuração!$D$14+SUM(tbRHI[%Aloc1])*Configuração!$D$15)/Configuração!$D$13)*tbRateio[[#This Row],[Custo Mensal]] -> 36.494145 | E4: =((SUMIF(tbEquipe[Mês],E$1,tbEquipe[Alocação])*Configuração!$D$14+SUM(tbRHI[%Aloc2])*Configuração!$D$15)/Configuração!$D$13)*tbRateio[[#This Row],[Custo Mensal]] -> 36.648339 | F4: =((SUMIF(tbEquipe[Mês],F$1,tbEquipe[Alocação])*Configuração!$D$14+SUM(tbRHI[%Aloc3])*Configuração!$D$15)/Configuração!$D$13)*tbRateio[[#This Row],[Custo Mensal]] -> 36.648339 | G4: =((SUMIF(tbEquipe[Mês],G$1,tbEquipe[Alocação])*Configuração!$D$14+SUM(tbRHI[%Aloc4])*Configuração!$D$15)/Configuração!$D$13)*tbRateio[[#This Row],[Custo Mensal]] -> 36.648339 | H4: =((SUMIF(tbEquipe[Mês],H$1,tbEquipe[Alocação])*Configuração!$D$14+SUM(tbRHI[%Aloc5])*Configuração!$D$15)/Configuração!$D$13)*tbRateio[[#This Row],[Custo Mensal]] -> 36.648339 | I4: =((SUMIF(tbEquipe[Mês],I$1,tbEquipe[Alocação])*Configuração!$D$14+SUM(tbRHI[%Aloc6])*Configuração!$D$15)/Configuração!$D$13)*tbRateio[[#This Row],[Custo Mensal]] -> 36.648339 | J4: =((SUMIF(tbEquipe[Mês],J$1,tbEquipe[Alocação])*Configuração!$D$14+SUM(tbRHI[%Aloc7])*Configuração!$D$15)/Configuração!$D$13)*tbRateio[[#This Row],[Custo Mensal]] -> 36.648339 | K4: =((SUMIF(tbEquipe[Mês],K$1,tbEquipe[Alocação])*Configuração!$D$14+SUM(tbRHI[%Aloc8])*Configuração!$D$15)/Configuração!$D$13)*tbRateio[[#This Row],[Custo Mensal]] -> 36.648339 | L4: =((SUMIF(tbEquipe[Mês],L$1,tbEquipe[Alocação])*Configuração!$D$14+SUM(tbRHI[%Aloc9])*Configuração!$D$15)/Configuração!$D$13)*tbRateio[[#This Row],[Custo Mensal]] -> 36.648339 | M4: =((SUMIF(tbEquipe[Mês],M$1,tbEquipe[Alocação])*Configuração!$D$14+SUM(tbRHI[%Aloc10])*Configuração!$D$15)/Configuração!$D$13)*tbRateio[[#This Row],[Custo Mensal]] -> 36.648339 | N4: =((SUMIF(tbEquipe[Mês],N$1,tbEquipe[Alocação])*Configuração!$D$14+SUM(tbRHI[%Aloc11])*Configuração!$D$15)/Configuração!$D$13)*tbRateio[[#This Row],[Custo Mensal]] -> 36.648339 | O4: =((SUMIF(tbEquipe[Mês],O$1,tbEquipe[Alocação])*Configuração!$D$14+SUM(tbRHI[%Aloc12])*Configuração!$D$15)/Configuração!$D$13)*tbRateio[[#This Row],[Custo Mensal]] -> 36.648339 | P4: =((SUMIF(tbEquipe[Mês],P$1,tbEquipe[Alocação])*Configuração!$D$14+SUM(tbRHI[%Aloc13])*Configuração!$D$15)/Configuração!$D$13)*tbRateio[[#This Row],[Custo Mensal]] -> 1.7748725 | Q4: =((SUMIF(tbEquipe[Mês],Q$1,tbEquipe[Alocação])*Configuração!$D$14+SUM(tbRHI[%Aloc14])*Configuração!$D$15)/Configuração!$D$13)*tbRateio[[#This Row],[Custo Mensal]] -> 1.7962585 | R4: =((SUMIF(tbEquipe[Mês],R$1,tbEquipe[Alocação])*Configuração!$D$14+SUM(tbRHI[%Aloc15])*Configuração!$D$15)/Configuração!$D$13)*tbRateio[[#This Row],[Custo Mensal]] -> 1.7962585 | S4: =((SUMIF(tbEquipe[Mês],S$1,tbEquipe[Alocação])*Configuração!$D$14+SUM(tbRHI[%Aloc16])*Configuração!$D$15)/Configuração!$D$13)*tbRateio[[#This Row],[Custo Mensal]] -> 0 | T4: =((SUMIF(tbEquipe[Mês],T$1,tbEquipe[Alocação])*Configuração!$D$14+SUM(tbRHI[%Aloc17])*Configuração!$D$15)/Configuração!$D$13)*tbRateio[[#This Row],[Custo Mensal]] -> 0 | U4: =((SUMIF(tbEquipe[Mês],U$1,tbEquipe[Alocação])*Configuração!$D$14+SUM(tbRHI[%Aloc18])*Configuração!$D$15)/Configuração!$D$13)*tbRateio[[#This Row],[Custo Mensal]] -> 0 | V4: =((SUMIF(tbEquipe[Mês],V$1,tbEquipe[Alocação])*Configuração!$D$14+SUM(tbRHI[%Aloc19])*Configuração!$D$15)/Configuração!$D$13)*tbRateio[[#This Row],[Custo Mensal]] -> 0 | W4: =((SUMIF(tbEquipe[Mês],W$1,tbEquipe[Alocação])*Configuração!$D$14+SUM(tbRHI[%Aloc20])*Configuração!$D$15)/Configuração!$D$13)*tbRateio[[#This Row],[Custo Mensal]] -> 0 | X4: =((SUMIF(tbEquipe[Mês],X$1,tbEquipe[Alocação])*Configuração!$D$14+SUM(tbRHI[%Aloc21])*Configuração!$D$15)/Configuração!$D$13)*tbRateio[[#This Row],[Custo Mensal]] -> 0 | Y4: =((SUMIF(tbEquipe[Mês],Y$1,tbEquipe[Alocação])*Configuração!$D$14+SUM(tbRHI[%Aloc22])*Configuração!$D$15)/Configuração!$D$13)*tbRateio[[#This Row],[Custo Mensal]] -> 0 | Z4: =((SUMIF(tbEquipe[Mês],Z$1,tbEquipe[Alocação])*Configuração!$D$14+SUM(tbRHI[%Aloc23])*Configuração!$D$15)/Configuração!$D$13)*tbRateio[[#This Row],[Custo Mensal]] -> 0
A5: Internet - LogicPRO/Axxes | B5: 9000 | C5: =SUM(tbRateio[[#This Row],[1]],tbRateio[[#This Row],[2]],tbRateio[[#This Row],[3]],tbRateio[[#This Row],[4]],tbRateio[[#This Row],[5]],tbRateio[[#This Row],[6]],tbRateio[[#This Row],[7]],tbRateio[[#This Row],[8]],tbRateio[[#This Row],[9]],tbRateio[[#This Row],[10]],tbRateio[[#This Row],[11]],tbRateio[[#This Row],[12]],tbRateio[[#This Row],[13]],tbRateio[[#This Row],[14]],tbRateio[[#This Row],[15]],tbRateio[[#This Row],[16]],tbRateio[[#This Row],[17]],tbRateio[[#This Row],[18]],tbRateio[[#This Row],[19]],tbRateio[[#This Row],[20]],tbRateio[[#This Row],[21]],tbRateio[[#This Row],[22]],tbRateio[[#This Row],[23]]) -> 4004.9394 | D5: =((SUMIF(tbEquipe[Mês],D$1,tbEquipe[Alocação])*Configuração!$D$14+SUM(tbRHI[%Aloc1])*Configuração!$D$15)/Configuração!$D$13)*tbRateio[[#This Row],[Custo Mensal]] -> 328.44731 | E5: =((SUMIF(tbEquipe[Mês],E$1,tbEquipe[Alocação])*Configuração!$D$14+SUM(tbRHI[%Aloc2])*Configuração!$D$15)/Configuração!$D$13)*tbRateio[[#This Row],[Custo Mensal]] -> 329.83505 | F5: =((SUMIF(tbEquipe[Mês],F$1,tbEquipe[Alocação])*Configuração!$D$14+SUM(tbRHI[%Aloc3])*Configuração!$D$15)/Configuração!$D$13)*tbRateio[[#This Row],[Custo Mensal]] -> 329.83505 | G5: =((SUMIF(tbEquipe[Mês],G$1,tbEquipe[Alocação])*Configuração!$D$14+SUM(tbRHI[%Aloc4])*Configuração!$D$15)/Configuração!$D$13)*tbRateio[[#This Row],[Custo Mensal]] -> 329.83505 | H5: =((SUMIF(tbEquipe[Mês],H$1,tbEquipe[Alocação])*Configuração!$D$14+SUM(tbRHI[%Aloc5])*Configuração!$D$15)/Configuração!$D$13)*tbRateio[[#This Row],[Custo Mensal]] -> 329.83505 | I5: =((SUMIF(tbEquipe[Mês],I$1,tbEquipe[Alocação])*Configuração!$D$14+SUM(tbRHI[%Aloc6])*Configuração!$D$15)/Configuração!$D$13)*tbRateio[[#This Row],[Custo Mensal]] -> 329.83505 | J5: =((SUMIF(tbEquipe[Mês],J$1,tbEquipe[Alocação])*Configuração!$D$14+SUM(tbRHI[%Aloc7])*Configuração!$D$15)/Configuração!$D$13)*tbRateio[[#This Row],[Custo Mensal]] -> 329.83505 | K5: =((SUMIF(tbEquipe[Mês],K$1,tbEquipe[Alocação])*Configuração!$D$14+SUM(tbRHI[%Aloc8])*Configuração!$D$15)/Configuração!$D$13)*tbRateio[[#This Row],[Custo Mensal]] -> 329.83505 | L5: =((SUMIF(tbEquipe[Mês],L$1,tbEquipe[Alocação])*Configuração!$D$14+SUM(tbRHI[%Aloc9])*Configuração!$D$15)/Configuração!$D$13)*tbRateio[[#This Row],[Custo Mensal]] -> 329.83505 | M5: =((SUMIF(tbEquipe[Mês],M$1,tbEquipe[Alocação])*Configuração!$D$14+SUM(tbRHI[%Aloc10])*Configuração!$D$15)/Configuração!$D$13)*tbRateio[[#This Row],[Custo Mensal]] -> 329.83505 | N5: =((SUMIF(tbEquipe[Mês],N$1,tbEquipe[Alocação])*Configuração!$D$14+SUM(tbRHI[%Aloc11])*Configuração!$D$15)/Configuração!$D$13)*tbRateio[[#This Row],[Custo Mensal]] -> 329.83505 | O5: =((SUMIF(tbEquipe[Mês],O$1,tbEquipe[Alocação])*Configuração!$D$14+SUM(tbRHI[%Aloc12])*Configuração!$D$15)/Configuração!$D$13)*tbRateio[[#This Row],[Custo Mensal]] -> 329.83505 | P5: =((SUMIF(tbEquipe[Mês],P$1,tbEquipe[Alocação])*Configuração!$D$14+SUM(tbRHI[%Aloc13])*Configuração!$D$15)/Configuração!$D$13)*tbRateio[[#This Row],[Custo Mensal]] -> 15.973853 | Q5: =((SUMIF(tbEquipe[Mês],Q$1,tbEquipe[Alocação])*Configuração!$D$14+SUM(tbRHI[%Aloc14])*Configuração!$D$15)/Configuração!$D$13)*tbRateio[[#This Row],[Custo Mensal]] -> 16.166326 | R5: =((SUMIF(tbEquipe[Mês],R$1,tbEquipe[Alocação])*Configuração!$D$14+SUM(tbRHI[%Aloc15])*Configuração!$D$15)/Configuração!$D$13)*tbRateio[[#This Row],[Custo Mensal]] -> 16.166326 | S5: =((SUMIF(tbEquipe[Mês],S$1,tbEquipe[Alocação])*Configuração!$D$14+SUM(tbRHI[%Aloc16])*Configuração!$D$15)/Configuração!$D$13)*tbRateio[[#This Row],[Custo Mensal]] -> 0 | T5: =((SUMIF(tbEquipe[Mês],T$1,tbEquipe[Alocação])*Configuração!$D$14+SUM(tbRHI[%Aloc17])*Configuração!$D$15)/Configuração!$D$13)*tbRateio[[#This Row],[Custo Mensal]] -> 0 | U5: =((SUMIF(tbEquipe[Mês],U$1,tbEquipe[Alocação])*Configuração!$D$14+SUM(tbRHI[%Aloc18])*Configuração!$D$15)/Configuração!$D$13)*tbRateio[[#This Row],[Custo Mensal]] -> 0 | V5: =((SUMIF(tbEquipe[Mês],V$1,tbEquipe[Alocação])*Configuração!$D$14+SUM(tbRHI[%Aloc19])*Configuração!$D$15)/Configuração!$D$13)*tbRateio[[#This Row],[Custo Mensal]] -> 0 | W5: =((SUMIF(tbEquipe[Mês],W$1,tbEquipe[Alocação])*Configuração!$D$14+SUM(tbRHI[%Aloc20])*Configuração!$D$15)/Configuração!$D$13)*tbRateio[[#This Row],[Custo Mensal]] -> 0 | X5: =((SUMIF(tbEquipe[Mês],X$1,tbEquipe[Alocação])*Configuração!$D$14+SUM(tbRHI[%Aloc21])*Configuração!$D$15)/Configuração!$D$13)*tbRateio[[#This Row],[Custo Mensal]] -> 0 | Y5: =((SUMIF(tbEquipe[Mês],Y$1,tbEquipe[Alocação])*Configuração!$D$14+SUM(tbRHI[%Aloc22])*Configuração!$D$15)/Configuração!$D$13)*tbRateio[[#This Row],[Custo Mensal]] -> 0 | Z5: =((SUMIF(tbEquipe[Mês],Z$1,tbEquipe[Alocação])*Configuração!$D$14+SUM(tbRHI[%Aloc23])*Configuração!$D$15)/Configuração!$D$13)*tbRateio[[#This Row],[Custo Mensal]] -> 0
A6: Impressoras - Virtual Sistemas | B6: 560 | C6: =SUM(tbRateio[[#This Row],[1]],tbRateio[[#This Row],[2]],tbRateio[[#This Row],[3]],tbRateio[[#This Row],[4]],tbRateio[[#This Row],[5]],tbRateio[[#This Row],[6]],tbRateio[[#This Row],[7]],tbRateio[[#This Row],[8]],tbRateio[[#This Row],[9]],tbRateio[[#This Row],[10]],tbRateio[[#This Row],[11]],tbRateio[[#This Row],[12]],tbRateio[[#This Row],[13]],tbRateio[[#This Row],[14]],tbRateio[[#This Row],[15]],tbRateio[[#This Row],[16]],tbRateio[[#This Row],[17]],tbRateio[[#This Row],[18]],tbRateio[[#This Row],[19]],tbRateio[[#This Row],[20]],tbRateio[[#This Row],[21]],tbRateio[[#This Row],[22]],tbRateio[[#This Row],[23]]) -> 249.19623 | D6: =((SUMIF(tbEquipe[Mês],D$1,tbEquipe[Alocação])*Configuração!$D$14+SUM(tbRHI[%Aloc1])*Configuração!$D$15)/Configuração!$D$13)*tbRateio[[#This Row],[Custo Mensal]] -> 20.436721 | E6: =((SUMIF(tbEquipe[Mês],E$1,tbEquipe[Alocação])*Configuração!$D$14+SUM(tbRHI[%Aloc2])*Configuração!$D$15)/Configuração!$D$13)*tbRateio[[#This Row],[Custo Mensal]] -> 20.52307 | F6: =((SUMIF(tbEquipe[Mês],F$1,tbEquipe[Alocação])*Configuração!$D$14+SUM(tbRHI[%Aloc3])*Configuração!$D$15)/Configuração!$D$13)*tbRateio[[#This Row],[Custo Mensal]] -> 20.52307 | G6: =((SUMIF(tbEquipe[Mês],G$1,tbEquipe[Alocação])*Configuração!$D$14+SUM(tbRHI[%Aloc4])*Configuração!$D$15)/Configuração!$D$13)*tbRateio[[#This Row],[Custo Mensal]] -> 20.52307 | H6: =((SUMIF(tbEquipe[Mês],H$1,tbEquipe[Alocação])*Configuração!$D$14+SUM(tbRHI[%Aloc5])*Configuração!$D$15)/Configuração!$D$13)*tbRateio[[#This Row],[Custo Mensal]] -> 20.52307 | I6: =((SUMIF(tbEquipe[Mês],I$1,tbEquipe[Alocação])*Configuração!$D$14+SUM(tbRHI[%Aloc6])*Configuração!$D$15)/Configuração!$D$13)*tbRateio[[#This Row],[Custo Mensal]] -> 20.52307 | J6: =((SUMIF(tbEquipe[Mês],J$1,tbEquipe[Alocação])*Configuração!$D$14+SUM(tbRHI[%Aloc7])*Configuração!$D$15)/Configuração!$D$13)*tbRateio[[#This Row],[Custo Mensal]] -> 20.52307 | K6: =((SUMIF(tbEquipe[Mês],K$1,tbEquipe[Alocação])*Configuração!$D$14+SUM(tbRHI[%Aloc8])*Configuração!$D$15)/Configuração!$D$13)*tbRateio[[#This Row],[Custo Mensal]] -> 20.52307 | L6: =((SUMIF(tbEquipe[Mês],L$1,tbEquipe[Alocação])*Configuração!$D$14+SUM(tbRHI[%Aloc9])*Configuração!$D$15)/Configuração!$D$13)*tbRateio[[#This Row],[Custo Mensal]] -> 20.52307 | M6: =((SUMIF(tbEquipe[Mês],M$1,tbEquipe[Alocação])*Configuração!$D$14+SUM(tbRHI[%Aloc10])*Configuração!$D$15)/Configuração!$D$13)*tbRateio[[#This Row],[Custo Mensal]] -> 20.52307 | N6: =((SUMIF(tbEquipe[Mês],N$1,tbEquipe[Alocação])*Configuração!$D$14+SUM(tbRHI[%Aloc11])*Configuração!$D$15)/Configuração!$D$13)*tbRateio[[#This Row],[Custo Mensal]] -> 20.52307 | O6: =((SUMIF(tbEquipe[Mês],O$1,tbEquipe[Alocação])*Configuração!$D$14+SUM(tbRHI[%Aloc12])*Configuração!$D$15)/Configuração!$D$13)*tbRateio[[#This Row],[Custo Mensal]] -> 20.52307 | P6: =((SUMIF(tbEquipe[Mês],P$1,tbEquipe[Alocação])*Configuração!$D$14+SUM(tbRHI[%Aloc13])*Configuração!$D$15)/Configuração!$D$13)*tbRateio[[#This Row],[Custo Mensal]] -> 0.99392861 | Q6: =((SUMIF(tbEquipe[Mês],Q$1,tbEquipe[Alocação])*Configuração!$D$14+SUM(tbRHI[%Aloc14])*Configuração!$D$15)/Configuração!$D$13)*tbRateio[[#This Row],[Custo Mensal]] -> 1.0059048 | R6: =((SUMIF(tbEquipe[Mês],R$1,tbEquipe[Alocação])*Configuração!$D$14+SUM(tbRHI[%Aloc15])*Configuração!$D$15)/Configuração!$D$13)*tbRateio[[#This Row],[Custo Mensal]] -> 1.0059048 | S6: =((SUMIF(tbEquipe[Mês],S$1,tbEquipe[Alocação])*Configuração!$D$14+SUM(tbRHI[%Aloc16])*Configuração!$D$15)/Configuração!$D$13)*tbRateio[[#This Row],[Custo Mensal]] -> 0 | T6: =((SUMIF(tbEquipe[Mês],T$1,tbEquipe[Alocação])*Configuração!$D$14+SUM(tbRHI[%Aloc17])*Configuração!$D$15)/Configuração!$D$13)*tbRateio[[#This Row],[Custo Mensal]] -> 0 | U6: =((SUMIF(tbEquipe[Mês],U$1,tbEquipe[Alocação])*Configuração!$D$14+SUM(tbRHI[%Aloc18])*Configuração!$D$15)/Configuração!$D$13)*tbRateio[[#This Row],[Custo Mensal]] -> 0 | V6: =((SUMIF(tbEquipe[Mês],V$1,tbEquipe[Alocação])*Configuração!$D$14+SUM(tbRHI[%Aloc19])*Configuração!$D$15)/Configuração!$D$13)*tbRateio[[#This Row],[Custo Mensal]] -> 0 | W6: =((SUMIF(tbEquipe[Mês],W$1,tbEquipe[Alocação])*Configuração!$D$14+SUM(tbRHI[%Aloc20])*Configuração!$D$15)/Configuração!$D$13)*tbRateio[[#This Row],[Custo Mensal]] -> 0 | X6: =((SUMIF(tbEquipe[Mês],X$1,tbEquipe[Alocação])*Configuração!$D$14+SUM(tbRHI[%Aloc21])*Configuração!$D$15)/Configuração!$D$13)*tbRateio[[#This Row],[Custo Mensal]] -> 0 | Y6: =((SUMIF(tbEquipe[Mês],Y$1,tbEquipe[Alocação])*Configuração!$D$14+SUM(tbRHI[%Aloc22])*Configuração!$D$15)/Configuração!$D$13)*tbRateio[[#This Row],[Custo Mensal]] -> 0 | Z6: =((SUMIF(tbEquipe[Mês],Z$1,tbEquipe[Alocação])*Configuração!$D$14+SUM(tbRHI[%Aloc23])*Configuração!$D$15)/Configuração!$D$13)*tbRateio[[#This Row],[Custo Mensal]] -> 0
A7: Office 365/Project | B7: 19000 | C7: =SUM(tbRateio[[#This Row],[1]],tbRateio[[#This Row],[2]],tbRateio[[#This Row],[3]],tbRateio[[#This Row],[4]],tbRateio[[#This Row],[5]],tbRateio[[#This Row],[6]],tbRateio[[#This Row],[7]],tbRateio[[#This Row],[8]],tbRateio[[#This Row],[9]],tbRateio[[#This Row],[10]],tbRateio[[#This Row],[11]],tbRateio[[#This Row],[12]],tbRateio[[#This Row],[13]],tbRateio[[#This Row],[14]],tbRateio[[#This Row],[15]],tbRateio[[#This Row],[16]],tbRateio[[#This Row],[17]],tbRateio[[#This Row],[18]],tbRateio[[#This Row],[19]],tbRateio[[#This Row],[20]],tbRateio[[#This Row],[21]],tbRateio[[#This Row],[22]],tbRateio[[#This Row],[23]]) -> 8454.8721 | D7: =((SUMIF(tbEquipe[Mês],D$1,tbEquipe[Alocação])*Configuração!$D$14+SUM(tbRHI[%Aloc1])*Configuração!$D$15)/Configuração!$D$13)*tbRateio[[#This Row],[Custo Mensal]] -> 693.38876 | E7: =((SUMIF(tbEquipe[Mês],E$1,tbEquipe[Alocação])*Configuração!$D$14+SUM(tbRHI[%Aloc2])*Configuração!$D$15)/Configuração!$D$13)*tbRateio[[#This Row],[Custo Mensal]] -> 696.31845 | F7: =((SUMIF(tbEquipe[Mês],F$1,tbEquipe[Alocação])*Configuração!$D$14+SUM(tbRHI[%Aloc3])*Configuração!$D$15)/Configuração!$D$13)*tbRateio[[#This Row],[Custo Mensal]] -> 696.31845 | G7: =((SUMIF(tbEquipe[Mês],G$1,tbEquipe[Alocação])*Configuração!$D$14+SUM(tbRHI[%Aloc4])*Configuração!$D$15)/Configuração!$D$13)*tbRateio[[#This Row],[Custo Mensal]] -> 696.31845 | H7: =((SUMIF(tbEquipe[Mês],H$1,tbEquipe[Alocação])*Configuração!$D$14+SUM(tbRHI[%Aloc5])*Configuração!$D$15)/Configuração!$D$13)*tbRateio[[#This Row],[Custo Mensal]] -> 696.31845 | I7: =((SUMIF(tbEquipe[Mês],I$1,tbEquipe[Alocação])*Configuração!$D$14+SUM(tbRHI[%Aloc6])*Configuração!$D$15)/Configuração!$D$13)*tbRateio[[#This Row],[Custo Mensal]] -> 696.31845 | J7: =((SUMIF(tbEquipe[Mês],J$1,tbEquipe[Alocação])*Configuração!$D$14+SUM(tbRHI[%Aloc7])*Configuração!$D$15)/Configuração!$D$13)*tbRateio[[#This Row],[Custo Mensal]] -> 696.31845 | K7: =((SUMIF(tbEquipe[Mês],K$1,tbEquipe[Alocação])*Configuração!$D$14+SUM(tbRHI[%Aloc8])*Configuração!$D$15)/Configuração!$D$13)*tbRateio[[#This Row],[Custo Mensal]] -> 696.31845 | L7: =((SUMIF(tbEquipe[Mês],L$1,tbEquipe[Alocação])*Configuração!$D$14+SUM(tbRHI[%Aloc9])*Configuração!$D$15)/Configuração!$D$13)*tbRateio[[#This Row],[Custo Mensal]] -> 696.31845 | M7: =((SUMIF(tbEquipe[Mês],M$1,tbEquipe[Alocação])*Configuração!$D$14+SUM(tbRHI[%Aloc10])*Configuração!$D$15)/Configuração!$D$13)*tbRateio[[#This Row],[Custo Mensal]] -> 696.31845 | N7: =((SUMIF(tbEquipe[Mês],N$1,tbEquipe[Alocação])*Configuração!$D$14+SUM(tbRHI[%Aloc11])*Configuração!$D$15)/Configuração!$D$13)*tbRateio[[#This Row],[Custo Mensal]] -> 696.31845 | O7: =((SUMIF(tbEquipe[Mês],O$1,tbEquipe[Alocação])*Configuração!$D$14+SUM(tbRHI[%Aloc12])*Configuração!$D$15)/Configuração!$D$13)*tbRateio[[#This Row],[Custo Mensal]] -> 696.31845 | P7: =((SUMIF(tbEquipe[Mês],P$1,tbEquipe[Alocação])*Configuração!$D$14+SUM(tbRHI[%Aloc13])*Configuração!$D$15)/Configuração!$D$13)*tbRateio[[#This Row],[Custo Mensal]] -> 33.722578 | Q7: =((SUMIF(tbEquipe[Mês],Q$1,tbEquipe[Alocação])*Configuração!$D$14+SUM(tbRHI[%Aloc14])*Configuração!$D$15)/Configuração!$D$13)*tbRateio[[#This Row],[Custo Mensal]] -> 34.128911 | R7: =((SUMIF(tbEquipe[Mês],R$1,tbEquipe[Alocação])*Configuração!$D$14+SUM(tbRHI[%Aloc15])*Configuração!$D$15)/Configuração!$D$13)*tbRateio[[#This Row],[Custo Mensal]] -> 34.128911 | S7: =((SUMIF(tbEquipe[Mês],S$1,tbEquipe[Alocação])*Configuração!$D$14+SUM(tbRHI[%Aloc16])*Configuração!$D$15)/Configuração!$D$13)*tbRateio[[#This Row],[Custo Mensal]] -> 0 | T7: =((SUMIF(tbEquipe[Mês],T$1,tbEquipe[Alocação])*Configuração!$D$14+SUM(tbRHI[%Aloc17])*Configuração!$D$15)/Configuração!$D$13)*tbRateio[[#This Row],[Custo Mensal]] -> 0 | U7: =((SUMIF(tbEquipe[Mês],U$1,tbEquipe[Alocação])*Configuração!$D$14+SUM(tbRHI[%Aloc18])*Configuração!$D$15)/Configuração!$D$13)*tbRateio[[#This Row],[Custo Mensal]] -> 0 | V7: =((SUMIF(tbEquipe[Mês],V$1,tbEquipe[Alocação])*Configuração!$D$14+SUM(tbRHI[%Aloc19])*Configuração!$D$15)/Configuração!$D$13)*tbRateio[[#This Row],[Custo Mensal]] -> 0 | W7: =((SUMIF(tbEquipe[Mês],W$1,tbEquipe[Alocação])*Configuração!$D$14+SUM(tbRHI[%Aloc20])*Configuração!$D$15)/Configuração!$D$13)*tbRateio[[#This Row],[Custo Mensal]] -> 0 | X7: =((SUMIF(tbEquipe[Mês],X$1,tbEquipe[Alocação])*Configuração!$D$14+SUM(tbRHI[%Aloc21])*Configuração!$D$15)/Configuração!$D$13)*tbRateio[[#This Row],[Custo Mensal]] -> 0 | Y7: =((SUMIF(tbEquipe[Mês],Y$1,tbEquipe[Alocação])*Configuração!$D$14+SUM(tbRHI[%Aloc22])*Configuração!$D$15)/Configuração!$D$13)*tbRateio[[#This Row],[Custo Mensal]] -> 0 | Z7: =((SUMIF(tbEquipe[Mês],Z$1,tbEquipe[Alocação])*Configuração!$D$14+SUM(tbRHI[%Aloc23])*Configuração!$D$15)/Configuração!$D$13)*tbRateio[[#This Row],[Custo Mensal]] -> 0
A8: Conservacao e Limpeza | B8: 32000 | C8: =SUM(tbRateio[[#This Row],[1]],tbRateio[[#This Row],[2]],tbRateio[[#This Row],[3]],tbRateio[[#This Row],[4]],tbRateio[[#This Row],[5]],tbRateio[[#This Row],[6]],tbRateio[[#This Row],[7]],tbRateio[[#This Row],[8]],tbRateio[[#This Row],[9]],tbRateio[[#This Row],[10]],tbRateio[[#This Row],[11]],tbRateio[[#This Row],[12]],tbRateio[[#This Row],[13]],tbRateio[[#This Row],[14]],tbRateio[[#This Row],[15]],tbRateio[[#This Row],[16]],tbRateio[[#This Row],[17]],tbRateio[[#This Row],[18]],tbRateio[[#This Row],[19]],tbRateio[[#This Row],[20]],tbRateio[[#This Row],[21]],tbRateio[[#This Row],[22]],tbRateio[[#This Row],[23]]) -> 14239.785 | D8: =((SUMIF(tbEquipe[Mês],D$1,tbEquipe[Alocação])*Configuração!$D$14+SUM(tbRHI[%Aloc1])*Configuração!$D$15)/Configuração!$D$13)*tbRateio[[#This Row],[Custo Mensal]] -> 1167.8126 | E8: =((SUMIF(tbEquipe[Mês],E$1,tbEquipe[Alocação])*Configuração!$D$14+SUM(tbRHI[%Aloc2])*Configuração!$D$15)/Configuração!$D$13)*tbRateio[[#This Row],[Custo Mensal]] -> 1172.7469 | F8: =((SUMIF(tbEquipe[Mês],F$1,tbEquipe[Alocação])*Configuração!$D$14+SUM(tbRHI[%Aloc3])*Configuração!$D$15)/Configuração!$D$13)*tbRateio[[#This Row],[Custo Mensal]] -> 1172.7469 | G8: =((SUMIF(tbEquipe[Mês],G$1,tbEquipe[Alocação])*Configuração!$D$14+SUM(tbRHI[%Aloc4])*Configuração!$D$15)/Configuração!$D$13)*tbRateio[[#This Row],[Custo Mensal]] -> 1172.7469 | H8: =((SUMIF(tbEquipe[Mês],H$1,tbEquipe[Alocação])*Configuração!$D$14+SUM(tbRHI[%Aloc5])*Configuração!$D$15)/Configuração!$D$13)*tbRateio[[#This Row],[Custo Mensal]] -> 1172.7469 | I8: =((SUMIF(tbEquipe[Mês],I$1,tbEquipe[Alocação])*Configuração!$D$14+SUM(tbRHI[%Aloc6])*Configuração!$D$15)/Configuração!$D$13)*tbRateio[[#This Row],[Custo Mensal]] -> 1172.7469 | J8: =((SUMIF(tbEquipe[Mês],J$1,tbEquipe[Alocação])*Configuração!$D$14+SUM(tbRHI[%Aloc7])*Configuração!$D$15)/Configuração!$D$13)*tbRateio[[#This Row],[Custo Mensal]] -> 1172.7469 | K8: =((SUMIF(tbEquipe[Mês],K$1,tbEquipe[Alocação])*Configuração!$D$14+SUM(tbRHI[%Aloc8])*Configuração!$D$15)/Configuração!$D$13)*tbRateio[[#This Row],[Custo Mensal]] -> 1172.7469 | L8: =((SUMIF(tbEquipe[Mês],L$1,tbEquipe[Alocação])*Configuração!$D$14+SUM(tbRHI[%Aloc9])*Configuração!$D$15)/Configuração!$D$13)*tbRateio[[#This Row],[Custo Mensal]] -> 1172.7469 | M8: =((SUMIF(tbEquipe[Mês],M$1,tbEquipe[Alocação])*Configuração!$D$14+SUM(tbRHI[%Aloc10])*Configuração!$D$15)/Configuração!$D$13)*tbRateio[[#This Row],[Custo Mensal]] -> 1172.7469 | N8: =((SUMIF(tbEquipe[Mês],N$1,tbEquipe[Alocação])*Configuração!$D$14+SUM(tbRHI[%Aloc11])*Configuração!$D$15)/Configuração!$D$13)*tbRateio[[#This Row],[Custo Mensal]] -> 1172.7469 | O8: =((SUMIF(tbEquipe[Mês],O$1,tbEquipe[Alocação])*Configuração!$D$14+SUM(tbRHI[%Aloc12])*Configuração!$D$15)/Configuração!$D$13)*tbRateio[[#This Row],[Custo Mensal]] -> 1172.7469 | P8: =((SUMIF(tbEquipe[Mês],P$1,tbEquipe[Alocação])*Configuração!$D$14+SUM(tbRHI[%Aloc13])*Configuração!$D$15)/Configuração!$D$13)*tbRateio[[#This Row],[Custo Mensal]] -> 56.795921 | Q8: =((SUMIF(tbEquipe[Mês],Q$1,tbEquipe[Alocação])*Configuração!$D$14+SUM(tbRHI[%Aloc14])*Configuração!$D$15)/Configuração!$D$13)*tbRateio[[#This Row],[Custo Mensal]] -> 57.480272 | R8: =((SUMIF(tbEquipe[Mês],R$1,tbEquipe[Alocação])*Configuração!$D$14+SUM(tbRHI[%Aloc15])*Configuração!$D$15)/Configuração!$D$13)*tbRateio[[#This Row],[Custo Mensal]] -> 57.480272 | S8: =((SUMIF(tbEquipe[Mês],S$1,tbEquipe[Alocação])*Configuração!$D$14+SUM(tbRHI[%Aloc16])*Configuração!$D$15)/Configuração!$D$13)*tbRateio[[#This Row],[Custo Mensal]] -> 0 | T8: =((SUMIF(tbEquipe[Mês],T$1,tbEquipe[Alocação])*Configuração!$D$14+SUM(tbRHI[%Aloc17])*Configuração!$D$15)/Configuração!$D$13)*tbRateio[[#This Row],[Custo Mensal]] -> 0 | U8: =((SUMIF(tbEquipe[Mês],U$1,tbEquipe[Alocação])*Configuração!$D$14+SUM(tbRHI[%Aloc18])*Configuração!$D$15)/Configuração!$D$13)*tbRateio[[#This Row],[Custo Mensal]] -> 0 | V8: =((SUMIF(tbEquipe[Mês],V$1,tbEquipe[Alocação])*Configuração!$D$14+SUM(tbRHI[%Aloc19])*Configuração!$D$15)/Configuração!$D$13)*tbRateio[[#This Row],[Custo Mensal]] -> 0 | W8: =((SUMIF(tbEquipe[Mês],W$1,tbEquipe[Alocação])*Configuração!$D$14+SUM(tbRHI[%Aloc20])*Configuração!$D$15)/Configuração!$D$13)*tbRateio[[#This Row],[Custo Mensal]] -> 0 | X8: =((SUMIF(tbEquipe[Mês],X$1,tbEquipe[Alocação])*Configuração!$D$14+SUM(tbRHI[%Aloc21])*Configuração!$D$15)/Configuração!$D$13)*tbRateio[[#This Row],[Custo Mensal]] -> 0 | Y8: =((SUMIF(tbEquipe[Mês],Y$1,tbEquipe[Alocação])*Configuração!$D$14+SUM(tbRHI[%Aloc22])*Configuração!$D$15)/Configuração!$D$13)*tbRateio[[#This Row],[Custo Mensal]] -> 0 | Z8: =((SUMIF(tbEquipe[Mês],Z$1,tbEquipe[Alocação])*Configuração!$D$14+SUM(tbRHI[%Aloc23])*Configuração!$D$15)/Configuração!$D$13)*tbRateio[[#This Row],[Custo Mensal]] -> 0
A9: Manutenção de Ar Condicionando | B9: 6000 | C9: =SUM(tbRateio[[#This Row],[1]],tbRateio[[#This Row],[2]],tbRateio[[#This Row],[3]],tbRateio[[#This Row],[4]],tbRateio[[#This Row],[5]],tbRateio[[#This Row],[6]],tbRateio[[#This Row],[7]],tbRateio[[#This Row],[8]],tbRateio[[#This Row],[9]],tbRateio[[#This Row],[10]],tbRateio[[#This Row],[11]],tbRateio[[#This Row],[12]],tbRateio[[#This Row],[13]],tbRateio[[#This Row],[14]],tbRateio[[#This Row],[15]],tbRateio[[#This Row],[16]],tbRateio[[#This Row],[17]],tbRateio[[#This Row],[18]],tbRateio[[#This Row],[19]],tbRateio[[#This Row],[20]],tbRateio[[#This Row],[21]],tbRateio[[#This Row],[22]],tbRateio[[#This Row],[23]]) -> 2669.9596 | D9: =((SUMIF(tbEquipe[Mês],D$1,tbEquipe[Alocação])*Configuração!$D$14+SUM(tbRHI[%Aloc1])*Configuração!$D$15)/Configuração!$D$13)*tbRateio[[#This Row],[Custo Mensal]] -> 218.96487 | E9: =((SUMIF(tbEquipe[Mês],E$1,tbEquipe[Alocação])*Configuração!$D$14+SUM(tbRHI[%Aloc2])*Configuração!$D$15)/Configuração!$D$13)*tbRateio[[#This Row],[Custo Mensal]] -> 219.89004 | F9: =((SUMIF(tbEquipe[Mês],F$1,tbEquipe[Alocação])*Configuração!$D$14+SUM(tbRHI[%Aloc3])*Configuração!$D$15)/Configuração!$D$13)*tbRateio[[#This Row],[Custo Mensal]] -> 219.89004 | G9: =((SUMIF(tbEquipe[Mês],G$1,tbEquipe[Alocação])*Configuração!$D$14+SUM(tbRHI[%Aloc4])*Configuração!$D$15)/Configuração!$D$13)*tbRateio[[#This Row],[Custo Mensal]] -> 219.89004 | H9: =((SUMIF(tbEquipe[Mês],H$1,tbEquipe[Alocação])*Configuração!$D$14+SUM(tbRHI[%Aloc5])*Configuração!$D$15)/Configuração!$D$13)*tbRateio[[#This Row],[Custo Mensal]] -> 219.89004 | I9: =((SUMIF(tbEquipe[Mês],I$1,tbEquipe[Alocação])*Configuração!$D$14+SUM(tbRHI[%Aloc6])*Configuração!$D$15)/Configuração!$D$13)*tbRateio[[#This Row],[Custo Mensal]] -> 219.89004 | J9: =((SUMIF(tbEquipe[Mês],J$1,tbEquipe[Alocação])*Configuração!$D$14+SUM(tbRHI[%Aloc7])*Configuração!$D$15)/Configuração!$D$13)*tbRateio[[#This Row],[Custo Mensal]] -> 219.89004 | K9: =((SUMIF(tbEquipe[Mês],K$1,tbEquipe[Alocação])*Configuração!$D$14+SUM(tbRHI[%Aloc8])*Configuração!$D$15)/Configuração!$D$13)*tbRateio[[#This Row],[Custo Mensal]] -> 219.89004 | L9: =((SUMIF(tbEquipe[Mês],L$1,tbEquipe[Alocação])*Configuração!$D$14+SUM(tbRHI[%Aloc9])*Configuração!$D$15)/Configuração!$D$13)*tbRateio[[#This Row],[Custo Mensal]] -> 219.89004 | M9: =((SUMIF(tbEquipe[Mês],M$1,tbEquipe[Alocação])*Configuração!$D$14+SUM(tbRHI[%Aloc10])*Configuração!$D$15)/Configuração!$D$13)*tbRateio[[#This Row],[Custo Mensal]] -> 219.89004 | N9: =((SUMIF(tbEquipe[Mês],N$1,tbEquipe[Alocação])*Configuração!$D$14+SUM(tbRHI[%Aloc11])*Configuração!$D$15)/Configuração!$D$13)*tbRateio[[#This Row],[Custo Mensal]] -> 219.89004 | O9: =((SUMIF(tbEquipe[Mês],O$1,tbEquipe[Alocação])*Configuração!$D$14+SUM(tbRHI[%Aloc12])*Configuração!$D$15)/Configuração!$D$13)*tbRateio[[#This Row],[Custo Mensal]] -> 219.89004 | P9: =((SUMIF(tbEquipe[Mês],P$1,tbEquipe[Alocação])*Configuração!$D$14+SUM(tbRHI[%Aloc13])*Configuração!$D$15)/Configuração!$D$13)*tbRateio[[#This Row],[Custo Mensal]] -> 10.649235 | Q9: =((SUMIF(tbEquipe[Mês],Q$1,tbEquipe[Alocação])*Configuração!$D$14+SUM(tbRHI[%Aloc14])*Configuração!$D$15)/Configuração!$D$13)*tbRateio[[#This Row],[Custo Mensal]] -> 10.777551 | R9: =((SUMIF(tbEquipe[Mês],R$1,tbEquipe[Alocação])*Configuração!$D$14+SUM(tbRHI[%Aloc15])*Configuração!$D$15)/Configuração!$D$13)*tbRateio[[#This Row],[Custo Mensal]] -> 10.777551 | S9: =((SUMIF(tbEquipe[Mês],S$1,tbEquipe[Alocação])*Configuração!$D$14+SUM(tbRHI[%Aloc16])*Configuração!$D$15)/Configuração!$D$13)*tbRateio[[#This Row],[Custo Mensal]] -> 0 | T9: =((SUMIF(tbEquipe[Mês],T$1,tbEquipe[Alocação])*Configuração!$D$14+SUM(tbRHI[%Aloc17])*Configuração!$D$15)/Configuração!$D$13)*tbRateio[[#This Row],[Custo Mensal]] -> 0 | U9: =((SUMIF(tbEquipe[Mês],U$1,tbEquipe[Alocação])*Configuração!$D$14+SUM(tbRHI[%Aloc18])*Configuração!$D$15)/Configuração!$D$13)*tbRateio[[#This Row],[Custo Mensal]] -> 0 | V9: =((SUMIF(tbEquipe[Mês],V$1,tbEquipe[Alocação])*Configuração!$D$14+SUM(tbRHI[%Aloc19])*Configuração!$D$15)/Configuração!$D$13)*tbRateio[[#This Row],[Custo Mensal]] -> 0 | W9: =((SUMIF(tbEquipe[Mês],W$1,tbEquipe[Alocação])*Configuração!$D$14+SUM(tbRHI[%Aloc20])*Configuração!$D$15)/Configuração!$D$13)*tbRateio[[#This Row],[Custo Mensal]] -> 0 | X9: =((SUMIF(tbEquipe[Mês],X$1,tbEquipe[Alocação])*Configuração!$D$14+SUM(tbRHI[%Aloc21])*Configuração!$D$15)/Configuração!$D$13)*tbRateio[[#This Row],[Custo Mensal]] -> 0 | Y9: =((SUMIF(tbEquipe[Mês],Y$1,tbEquipe[Alocação])*Configuração!$D$14+SUM(tbRHI[%Aloc22])*Configuração!$D$15)/Configuração!$D$13)*tbRateio[[#This Row],[Custo Mensal]] -> 0 | Z9: =((SUMIF(tbEquipe[Mês],Z$1,tbEquipe[Alocação])*Configuração!$D$14+SUM(tbRHI[%Aloc23])*Configuração!$D$15)/Configuração!$D$13)*tbRateio[[#This Row],[Custo Mensal]] -> 0
A10: Serviço de Suporte Administrativo Contábil | B10: 10000 | C10: =SUM(tbRateio[[#This Row],[1]],tbRateio[[#This Row],[2]],tbRateio[[#This Row],[3]],tbRateio[[#This Row],[4]],tbRateio[[#This Row],[5]],tbRateio[[#This Row],[6]],tbRateio[[#This Row],[7]],tbRateio[[#This Row],[8]],tbRateio[[#This Row],[9]],tbRateio[[#This Row],[10]],tbRateio[[#This Row],[11]],tbRateio[[#This Row],[12]],tbRateio[[#This Row],[13]],tbRateio[[#This Row],[14]],tbRateio[[#This Row],[15]],tbRateio[[#This Row],[16]],tbRateio[[#This Row],[17]],tbRateio[[#This Row],[18]],tbRateio[[#This Row],[19]],tbRateio[[#This Row],[20]],tbRateio[[#This Row],[21]],tbRateio[[#This Row],[22]],tbRateio[[#This Row],[23]]) -> 4449.9327 | D10: =((SUMIF(tbEquipe[Mês],D$1,tbEquipe[Alocação])*Configuração!$D$14+SUM(tbRHI[%Aloc1])*Configuração!$D$15)/Configuração!$D$13)*tbRateio[[#This Row],[Custo Mensal]] -> 364.94145 | E10: =((SUMIF(tbEquipe[Mês],E$1,tbEquipe[Alocação])*Configuração!$D$14+SUM(tbRHI[%Aloc2])*Configuração!$D$15)/Configuração!$D$13)*tbRateio[[#This Row],[Custo Mensal]] -> 366.48339 | F10: =((SUMIF(tbEquipe[Mês],F$1,tbEquipe[Alocação])*Configuração!$D$14+SUM(tbRHI[%Aloc3])*Configuração!$D$15)/Configuração!$D$13)*tbRateio[[#This Row],[Custo Mensal]] -> 366.48339 | G10: =((SUMIF(tbEquipe[Mês],G$1,tbEquipe[Alocação])*Configuração!$D$14+SUM(tbRHI[%Aloc4])*Configuração!$D$15)/Configuração!$D$13)*tbRateio[[#This Row],[Custo Mensal]] -> 366.48339 | H10: =((SUMIF(tbEquipe[Mês],H$1,tbEquipe[Alocação])*Configuração!$D$14+SUM(tbRHI[%Aloc5])*Configuração!$D$15)/Configuração!$D$13)*tbRateio[[#This Row],[Custo Mensal]] -> 366.48339 | I10: =((SUMIF(tbEquipe[Mês],I$1,tbEquipe[Alocação])*Configuração!$D$14+SUM(tbRHI[%Aloc6])*Configuração!$D$15)/Configuração!$D$13)*tbRateio[[#This Row],[Custo Mensal]] -> 366.48339 | J10: =((SUMIF(tbEquipe[Mês],J$1,tbEquipe[Alocação])*Configuração!$D$14+SUM(tbRHI[%Aloc7])*Configuração!$D$15)/Configuração!$D$13)*tbRateio[[#This Row],[Custo Mensal]] -> 366.48339 | K10: =((SUMIF(tbEquipe[Mês],K$1,tbEquipe[Alocação])*Configuração!$D$14+SUM(tbRHI[%Aloc8])*Configuração!$D$15)/Configuração!$D$13)*tbRateio[[#This Row],[Custo Mensal]] -> 366.48339 | L10: =((SUMIF(tbEquipe[Mês],L$1,tbEquipe[Alocação])*Configuração!$D$14+SUM(tbRHI[%Aloc9])*Configuração!$D$15)/Configuração!$D$13)*tbRateio[[#This Row],[Custo Mensal]] -> 366.48339 | M10: =((SUMIF(tbEquipe[Mês],M$1,tbEquipe[Alocação])*Configuração!$D$14+SUM(tbRHI[%Aloc10])*Configuração!$D$15)/Configuração!$D$13)*tbRateio[[#This Row],[Custo Mensal]] -> 366.48339 | N10: =((SUMIF(tbEquipe[Mês],N$1,tbEquipe[Alocação])*Configuração!$D$14+SUM(tbRHI[%Aloc11])*Configuração!$D$15)/Configuração!$D$13)*tbRateio[[#This Row],[Custo Mensal]] -> 366.48339 | O10: =((SUMIF(tbEquipe[Mês],O$1,tbEquipe[Alocação])*Configuração!$D$14+SUM(tbRHI[%Aloc12])*Configuração!$D$15)/Configuração!$D$13)*tbRateio[[#This Row],[Custo Mensal]] -> 366.48339 | P10: =((SUMIF(tbEquipe[Mês],P$1,tbEquipe[Alocação])*Configuração!$D$14+SUM(tbRHI[%Aloc13])*Configuração!$D$15)/Configuração!$D$13)*tbRateio[[#This Row],[Custo Mensal]] -> 17.748725 | Q10: =((SUMIF(tbEquipe[Mês],Q$1,tbEquipe[Alocação])*Configuração!$D$14+SUM(tbRHI[%Aloc14])*Configuração!$D$15)/Configuração!$D$13)*tbRateio[[#This Row],[Custo Mensal]] -> 17.962585 | R10: =((SUMIF(tbEquipe[Mês],R$1,tbEquipe[Alocação])*Configuração!$D$14+SUM(tbRHI[%Aloc15])*Configuração!$D$15)/Configuração!$D$13)*tbRateio[[#This Row],[Custo Mensal]] -> 17.962585 | S10: =((SUMIF(tbEquipe[Mês],S$1,tbEquipe[Alocação])*Configuração!$D$14+SUM(tbRHI[%Aloc16])*Configuração!$D$15)/Configuração!$D$13)*tbRateio[[#This Row],[Custo Mensal]] -> 0 | T10: =((SUMIF(tbEquipe[Mês],T$1,tbEquipe[Alocação])*Configuração!$D$14+SUM(tbRHI[%Aloc17])*Configuração!$D$15)/Configuração!$D$13)*tbRateio[[#This Row],[Custo Mensal]] -> 0 | U10: =((SUMIF(tbEquipe[Mês],U$1,tbEquipe[Alocação])*Configuração!$D$14+SUM(tbRHI[%Aloc18])*Configuração!$D$15)/Configuração!$D$13)*tbRateio[[#This Row],[Custo Mensal]] -> 0 | V10: =((SUMIF(tbEquipe[Mês],V$1,tbEquipe[Alocação])*Configuração!$D$14+SUM(tbRHI[%Aloc19])*Configuração!$D$15)/Configuração!$D$13)*tbRateio[[#This Row],[Custo Mensal]] -> 0 | W10: =((SUMIF(tbEquipe[Mês],W$1,tbEquipe[Alocação])*Configuração!$D$14+SUM(tbRHI[%Aloc20])*Configuração!$D$15)/Configuração!$D$13)*tbRateio[[#This Row],[Custo Mensal]] -> 0 | X10: =((SUMIF(tbEquipe[Mês],X$1,tbEquipe[Alocação])*Configuração!$D$14+SUM(tbRHI[%Aloc21])*Configuração!$D$15)/Configuração!$D$13)*tbRateio[[#This Row],[Custo Mensal]] -> 0 | Y10: =((SUMIF(tbEquipe[Mês],Y$1,tbEquipe[Alocação])*Configuração!$D$14+SUM(tbRHI[%Aloc22])*Configuração!$D$15)/Configuração!$D$13)*tbRateio[[#This Row],[Custo Mensal]] -> 0 | Z10: =((SUMIF(tbEquipe[Mês],Z$1,tbEquipe[Alocação])*Configuração!$D$14+SUM(tbRHI[%Aloc23])*Configuração!$D$15)/Configuração!$D$13)*tbRateio[[#This Row],[Custo Mensal]] -> 0
A11: Serviço suporte de informática (operação de datacenter e hospedagem de servidores | B11: 34494.27 | C11: =SUM(tbRateio[[#This Row],[1]],tbRateio[[#This Row],[2]],tbRateio[[#This Row],[3]],tbRateio[[#This Row],[4]],tbRateio[[#This Row],[5]],tbRateio[[#This Row],[6]],tbRateio[[#This Row],[7]],tbRateio[[#This Row],[8]],tbRateio[[#This Row],[9]],tbRateio[[#This Row],[10]],tbRateio[[#This Row],[11]],tbRateio[[#This Row],[12]],tbRateio[[#This Row],[13]],tbRateio[[#This Row],[14]],tbRateio[[#This Row],[15]],tbRateio[[#This Row],[16]],tbRateio[[#This Row],[17]],tbRateio[[#This Row],[18]],tbRateio[[#This Row],[19]],tbRateio[[#This Row],[20]],tbRateio[[#This Row],[21]],tbRateio[[#This Row],[22]],tbRateio[[#This Row],[23]]) -> 15349.718 | D11: =((SUMIF(tbEquipe[Mês],D$1,tbEquipe[Alocação])*Configuração!$D$14+SUM(tbRHI[%Aloc1])*Configuração!$D$15)/Configuração!$D$13)*tbRateio[[#This Row],[Custo Mensal]] -> 1258.8389 | E11: =((SUMIF(tbEquipe[Mês],E$1,tbEquipe[Alocação])*Configuração!$D$14+SUM(tbRHI[%Aloc2])*Configuração!$D$15)/Configuração!$D$13)*tbRateio[[#This Row],[Custo Mensal]] -> 1264.1577 | F11: =((SUMIF(tbEquipe[Mês],F$1,tbEquipe[Alocação])*Configuração!$D$14+SUM(tbRHI[%Aloc3])*Configuração!$D$15)/Configuração!$D$13)*tbRateio[[#This Row],[Custo Mensal]] -> 1264.1577 | G11: =((SUMIF(tbEquipe[Mês],G$1,tbEquipe[Alocação])*Configuração!$D$14+SUM(tbRHI[%Aloc4])*Configuração!$D$15)/Configuração!$D$13)*tbRateio[[#This Row],[Custo Mensal]] -> 1264.1577 | H11: =((SUMIF(tbEquipe[Mês],H$1,tbEquipe[Alocação])*Configuração!$D$14+SUM(tbRHI[%Aloc5])*Configuração!$D$15)/Configuração!$D$13)*tbRateio[[#This Row],[Custo Mensal]] -> 1264.1577 | I11: =((SUMIF(tbEquipe[Mês],I$1,tbEquipe[Alocação])*Configuração!$D$14+SUM(tbRHI[%Aloc6])*Configuração!$D$15)/Configuração!$D$13)*tbRateio[[#This Row],[Custo Mensal]] -> 1264.1577 | J11: =((SUMIF(tbEquipe[Mês],J$1,tbEquipe[Alocação])*Configuração!$D$14+SUM(tbRHI[%Aloc7])*Configuração!$D$15)/Configuração!$D$13)*tbRateio[[#This Row],[Custo Mensal]] -> 1264.1577 | K11: =((SUMIF(tbEquipe[Mês],K$1,tbEquipe[Alocação])*Configuração!$D$14+SUM(tbRHI[%Aloc8])*Configuração!$D$15)/Configuração!$D$13)*tbRateio[[#This Row],[Custo Mensal]] -> 1264.1577 | L11: =((SUMIF(tbEquipe[Mês],L$1,tbEquipe[Alocação])*Configuração!$D$14+SUM(tbRHI[%Aloc9])*Configuração!$D$15)/Configuração!$D$13)*tbRateio[[#This Row],[Custo Mensal]] -> 1264.1577 | M11: =((SUMIF(tbEquipe[Mês],M$1,tbEquipe[Alocação])*Configuração!$D$14+SUM(tbRHI[%Aloc10])*Configuração!$D$15)/Configuração!$D$13)*tbRateio[[#This Row],[Custo Mensal]] -> 1264.1577 | N11: =((SUMIF(tbEquipe[Mês],N$1,tbEquipe[Alocação])*Configuração!$D$14+SUM(tbRHI[%Aloc11])*Configuração!$D$15)/Configuração!$D$13)*tbRateio[[#This Row],[Custo Mensal]] -> 1264.1577 | O11: =((SUMIF(tbEquipe[Mês],O$1,tbEquipe[Alocação])*Configuração!$D$14+SUM(tbRHI[%Aloc12])*Configuração!$D$15)/Configuração!$D$13)*tbRateio[[#This Row],[Custo Mensal]] -> 1264.1577 | P11: =((SUMIF(tbEquipe[Mês],P$1,tbEquipe[Alocação])*Configuração!$D$14+SUM(tbRHI[%Aloc13])*Configuração!$D$15)/Configuração!$D$13)*tbRateio[[#This Row],[Custo Mensal]] -> 61.222932 | Q11: =((SUMIF(tbEquipe[Mês],Q$1,tbEquipe[Alocação])*Configuração!$D$14+SUM(tbRHI[%Aloc14])*Configuração!$D$15)/Configuração!$D$13)*tbRateio[[#This Row],[Custo Mensal]] -> 61.960625 | R11: =((SUMIF(tbEquipe[Mês],R$1,tbEquipe[Alocação])*Configuração!$D$14+SUM(tbRHI[%Aloc15])*Configuração!$D$15)/Configuração!$D$13)*tbRateio[[#This Row],[Custo Mensal]] -> 61.960625 | S11: =((SUMIF(tbEquipe[Mês],S$1,tbEquipe[Alocação])*Configuração!$D$14+SUM(tbRHI[%Aloc16])*Configuração!$D$15)/Configuração!$D$13)*tbRateio[[#This Row],[Custo Mensal]] -> 0 | T11: =((SUMIF(tbEquipe[Mês],T$1,tbEquipe[Alocação])*Configuração!$D$14+SUM(tbRHI[%Aloc17])*Configuração!$D$15)/Configuração!$D$13)*tbRateio[[#This Row],[Custo Mensal]] -> 0 | U11: =((SUMIF(tbEquipe[Mês],U$1,tbEquipe[Alocação])*Configuração!$D$14+SUM(tbRHI[%Aloc18])*Configuração!$D$15)/Configuração!$D$13)*tbRateio[[#This Row],[Custo Mensal]] -> 0 | V11: =((SUMIF(tbEquipe[Mês],V$1,tbEquipe[Alocação])*Configuração!$D$14+SUM(tbRHI[%Aloc19])*Configuração!$D$15)/Configuração!$D$13)*tbRateio[[#This Row],[Custo Mensal]] -> 0 | W11: =((SUMIF(tbEquipe[Mês],W$1,tbEquipe[Alocação])*Configuração!$D$14+SUM(tbRHI[%Aloc20])*Configuração!$D$15)/Configuração!$D$13)*tbRateio[[#This Row],[Custo Mensal]] -> 0 | X11: =((SUMIF(tbEquipe[Mês],X$1,tbEquipe[Alocação])*Configuração!$D$14+SUM(tbRHI[%Aloc21])*Configuração!$D$15)/Configuração!$D$13)*tbRateio[[#This Row],[Custo Mensal]] -> 0 | Y11: =((SUMIF(tbEquipe[Mês],Y$1,tbEquipe[Alocação])*Configuração!$D$14+SUM(tbRHI[%Aloc22])*Configuração!$D$15)/Configuração!$D$13)*tbRateio[[#This Row],[Custo Mensal]] -> 0 | Z11: =((SUMIF(tbEquipe[Mês],Z$1,tbEquipe[Alocação])*Configuração!$D$14+SUM(tbRHI[%Aloc23])*Configuração!$D$15)/Configuração!$D$13)*tbRateio[[#This Row],[Custo Mensal]] -> 0
A12: IPTU | B12: 6569.44 | C12: =SUM(tbRateio[[#This Row],[1]],tbRateio[[#This Row],[2]],tbRateio[[#This Row],[3]],tbRateio[[#This Row],[4]],tbRateio[[#This Row],[5]],tbRateio[[#This Row],[6]],tbRateio[[#This Row],[7]],tbRateio[[#This Row],[8]],tbRateio[[#This Row],[9]],tbRateio[[#This Row],[10]],tbRateio[[#This Row],[11]],tbRateio[[#This Row],[12]],tbRateio[[#This Row],[13]],tbRateio[[#This Row],[14]],tbRateio[[#This Row],[15]],tbRateio[[#This Row],[16]],tbRateio[[#This Row],[17]],tbRateio[[#This Row],[18]],tbRateio[[#This Row],[19]],tbRateio[[#This Row],[20]],tbRateio[[#This Row],[21]],tbRateio[[#This Row],[22]],tbRateio[[#This Row],[23]]) -> 2923.3566 | D12: =((SUMIF(tbEquipe[Mês],D$1,tbEquipe[Alocação])*Configuração!$D$14+SUM(tbRHI[%Aloc1])*Configuração!$D$15)/Configuração!$D$13)*tbRateio[[#This Row],[Custo Mensal]] -> 239.7461 | E12: =((SUMIF(tbEquipe[Mês],E$1,tbEquipe[Alocação])*Configuração!$D$14+SUM(tbRHI[%Aloc2])*Configuração!$D$15)/Configuração!$D$13)*tbRateio[[#This Row],[Custo Mensal]] -> 240.75907 | F12: =((SUMIF(tbEquipe[Mês],F$1,tbEquipe[Alocação])*Configuração!$D$14+SUM(tbRHI[%Aloc3])*Configuração!$D$15)/Configuração!$D$13)*tbRateio[[#This Row],[Custo Mensal]] -> 240.75907 | G12: =((SUMIF(tbEquipe[Mês],G$1,tbEquipe[Alocação])*Configuração!$D$14+SUM(tbRHI[%Aloc4])*Configuração!$D$15)/Configuração!$D$13)*tbRateio[[#This Row],[Custo Mensal]] -> 240.75907 | H12: =((SUMIF(tbEquipe[Mês],H$1,tbEquipe[Alocação])*Configuração!$D$14+SUM(tbRHI[%Aloc5])*Configuração!$D$15)/Configuração!$D$13)*tbRateio[[#This Row],[Custo Mensal]] -> 240.75907 | I12: =((SUMIF(tbEquipe[Mês],I$1,tbEquipe[Alocação])*Configuração!$D$14+SUM(tbRHI[%Aloc6])*Configuração!$D$15)/Configuração!$D$13)*tbRateio[[#This Row],[Custo Mensal]] -> 240.75907 | J12: =((SUMIF(tbEquipe[Mês],J$1,tbEquipe[Alocação])*Configuração!$D$14+SUM(tbRHI[%Aloc7])*Configuração!$D$15)/Configuração!$D$13)*tbRateio[[#This Row],[Custo Mensal]] -> 240.75907 | K12: =((SUMIF(tbEquipe[Mês],K$1,tbEquipe[Alocação])*Configuração!$D$14+SUM(tbRHI[%Aloc8])*Configuração!$D$15)/Configuração!$D$13)*tbRateio[[#This Row],[Custo Mensal]] -> 240.75907 | L12: =((SUMIF(tbEquipe[Mês],L$1,tbEquipe[Alocação])*Configuração!$D$14+SUM(tbRHI[%Aloc9])*Configuração!$D$15)/Configuração!$D$13)*tbRateio[[#This Row],[Custo Mensal]] -> 240.75907 | M12: =((SUMIF(tbEquipe[Mês],M$1,tbEquipe[Alocação])*Configuração!$D$14+SUM(tbRHI[%Aloc10])*Configuração!$D$15)/Configuração!$D$13)*tbRateio[[#This Row],[Custo Mensal]] -> 240.75907 | N12: =((SUMIF(tbEquipe[Mês],N$1,tbEquipe[Alocação])*Configuração!$D$14+SUM(tbRHI[%Aloc11])*Configuração!$D$15)/Configuração!$D$13)*tbRateio[[#This Row],[Custo Mensal]] -> 240.75907 | O12: =((SUMIF(tbEquipe[Mês],O$1,tbEquipe[Alocação])*Configuração!$D$14+SUM(tbRHI[%Aloc12])*Configuração!$D$15)/Configuração!$D$13)*tbRateio[[#This Row],[Custo Mensal]] -> 240.75907 | P12: =((SUMIF(tbEquipe[Mês],P$1,tbEquipe[Alocação])*Configuração!$D$14+SUM(tbRHI[%Aloc13])*Configuração!$D$15)/Configuração!$D$13)*tbRateio[[#This Row],[Custo Mensal]] -> 11.659919 | Q12: =((SUMIF(tbEquipe[Mês],Q$1,tbEquipe[Alocação])*Configuração!$D$14+SUM(tbRHI[%Aloc14])*Configuração!$D$15)/Configuração!$D$13)*tbRateio[[#This Row],[Custo Mensal]] -> 11.800412 | R12: =((SUMIF(tbEquipe[Mês],R$1,tbEquipe[Alocação])*Configuração!$D$14+SUM(tbRHI[%Aloc15])*Configuração!$D$15)/Configuração!$D$13)*tbRateio[[#This Row],[Custo Mensal]] -> 11.800412 | S12: =((SUMIF(tbEquipe[Mês],S$1,tbEquipe[Alocação])*Configuração!$D$14+SUM(tbRHI[%Aloc16])*Configuração!$D$15)/Configuração!$D$13)*tbRateio[[#This Row],[Custo Mensal]] -> 0 | T12: =((SUMIF(tbEquipe[Mês],T$1,tbEquipe[Alocação])*Configuração!$D$14+SUM(tbRHI[%Aloc17])*Configuração!$D$15)/Configuração!$D$13)*tbRateio[[#This Row],[Custo Mensal]] -> 0 | U12: =((SUMIF(tbEquipe[Mês],U$1,tbEquipe[Alocação])*Configuração!$D$14+SUM(tbRHI[%Aloc18])*Configuração!$D$15)/Configuração!$D$13)*tbRateio[[#This Row],[Custo Mensal]] -> 0 | V12: =((SUMIF(tbEquipe[Mês],V$1,tbEquipe[Alocação])*Configuração!$D$14+SUM(tbRHI[%Aloc19])*Configuração!$D$15)/Configuração!$D$13)*tbRateio[[#This Row],[Custo Mensal]] -> 0 | W12: =((SUMIF(tbEquipe[Mês],W$1,tbEquipe[Alocação])*Configuração!$D$14+SUM(tbRHI[%Aloc20])*Configuração!$D$15)/Configuração!$D$13)*tbRateio[[#This Row],[Custo Mensal]] -> 0 | X12: =((SUMIF(tbEquipe[Mês],X$1,tbEquipe[Alocação])*Configuração!$D$14+SUM(tbRHI[%Aloc21])*Configuração!$D$15)/Configuração!$D$13)*tbRateio[[#This Row],[Custo Mensal]] -> 0 | Y12: =((SUMIF(tbEquipe[Mês],Y$1,tbEquipe[Alocação])*Configuração!$D$14+SUM(tbRHI[%Aloc22])*Configuração!$D$15)/Configuração!$D$13)*tbRateio[[#This Row],[Custo Mensal]] -> 0 | Z12: =((SUMIF(tbEquipe[Mês],Z$1,tbEquipe[Alocação])*Configuração!$D$14+SUM(tbRHI[%Aloc23])*Configuração!$D$15)/Configuração!$D$13)*tbRateio[[#This Row],[Custo Mensal]] -> 0
